Workbook

Sheet Amarillo T12
A1: Income Statement - 12 Month
A3: Fund Type: All
A4: Period Range: Apr 2025 to Mar 2026 (Trailing 12 Months)
A5: Accounting Basis: Accrual
A6: GL Account Map: None - use master chart of accounts
A7: Level of Detail: Detail View
A8: Include Zero Balance GL Accounts: No
A10: Account Name | B10: Apr 2025 | C10: May 2025 | D10: Jun 2025 | E10: Jul 2025 | F10: Aug 2025 | G10: Sep 2025 | H10: Oct 2025 | I10: Nov 2025 | J10: Dec 2025 | K10: Jan 2026 | L10: Feb 2026 | M10: Mar 2026 | N10: Total | O10: Account Number
A11: Operating Income & Expense
A12: Income
A13: Rental Income
A14: Rent Income | B14: 78897.79 | C14: 79496 | D14: 77736 | E14: 83287.8 | F14: 84069 | G14: 79301 | H14: 72960.69 | I14: 72265 | J14: 70194.25 | K14: 69825 | L14: 69443.58 | M14: 76874.1 | N14: 914350.21 | O14: 4002
A15: Housing Choice Voucher- HUD or PCS | B15: 9599 | C15: 9847 | D15: 9838 | E15: 9024 | F15: 7454 | G15: 7454 | H15: 7757 | I15: 8124 | J15: 9236 | K15: 9918 | L15: 9860 | M15: 9962 | N15: 108073 | O15: 4003
A16: Concessions - Promotion | B16: -1978 | C16: -3000 | D16: -3043.5 | E16: -1269 | F16: -1646.5 | G16: -104.5 | H16: -1502.5 | I16: -1446 | J16: -1350 | K16: -3270 | L16: -6365 | M16: -12870 | N16: -37845 | O16: 4007
A17: Concessions - Resident Concession | B17: 0 | C17: -873.98 | D17: -75 | E17: 0 | F17: 0 | G17: -75 | H17: 0 | I17: -20.54 | J17: 0 | K17: -150.54 | L17: -885 | M17: 0 | N17: -2080.06 | O17: 4009
A18: Concessions - Student Discount | B18: 0 | C18: 0 | D18: 0 | E18: 0 | F18: 0 | G18: 0 | H18: -56 | I18: 0 | J18: 0 | K18: 0 | L18: 0 | M18: 0 | N18: -56 | O18: 4010
A19: Total Rental Income | B19: 86518.79 | C19: 85469.02 | D19: 84455.5 | E19: 91042.8 | F19: 89876.5 | G19: 86575.5 | H19: 79159.19 | I19: 78922.46 | J19: 78080.25 | K19: 76322.46 | L19: 72053.58 | M19: 73966.1 | N19: 982442.15
A20: Fee Income
A21: Month-to-Month Fee | B21: 350 | C21: 250 | D21: 250 | E21: 300 | F21: 250 | G21: 150 | H21: 150 | I21: 150 | J21: 200 | K21: 200 | L21: 350 | M21: 300 | N21: 2900 | O21: 4101
A22: Late Fee | B22: 497.5 | C22: -501 | D22: 303.38 | E22: -159.78 | F22: 483.6 | G22: -16.93 | H22: 127.13 | I22: -50.6 | J22: -56.09 | K22: -81.81 | L22: 70 | M22: -39 | N22: 576.4 | O22: 4102
A23: NSF Fee | B23: 40 | C23: -40 | D23: 0 | E23: 0 | F23: 0 | G23: 0 | H23: 0 | I23: 100 | J23: -100 | K23: 0 | L23: 0 | M23: 0 | N23: 0 | O23: 4104
A24: One Time Pet Fee | B24: 250 | C24: 525 | D24: 225 | E24: 1750 | F24: 550 | G24: 500 | H24: 450 | I24: 750 | J24: 150 | K24: 150 | L24: 450 | M24: 1300 | N24: 7050 | O24: 4105
A25: Monthly Pet Fee | B25: 400 | C25: 429 | D25: 425 | E25: 515 | F25: 534 | G25: 515.8 | H25: 605.67 | I25: 740 | J25: 650 | K25: 625 | L25: 550 | M25: 667 | N25: 6656.47 | O25: 4106
A26: RBP Income | B26: 118.11 | C26: 157.93 | D26: 49.34 | E26: 511.71 | F26: 60 | G26: 30 | H26: -30 | I26: 30 | J26: -40 | K26: 11 | L26: 0 | M26: 0 | N26: 898.09 | O26: 4121
A27: LLI Income | B27: 11.36 | C27: 82.29 | D27: 52.13 | E27: 172.99 | F27: 10 | G27: 10 | H27: -10 | I27: 10 | J27: 0 | K27: 0 | L27: 0 | M27: 0 | N27: 338.77 | O27: 4123
A28: Beagle TLW | B28: 0 | C28: 0 | D28: 11 | E28: -597.8 | F28: -58.95 | G28: -227.51 | H28: -181.25 | I28: 648.34 | J28: -368.21 | K28: 154.9 | L28: -589.88 | M28: 448.03 | N28: -761.33 | O28: 4124
A29: Total Fee Income | B29: 1666.97 | C29: 903.22 | D29: 1315.85 | E29: 2492.12 | F29: 1828.65 | G29: 961.36 | H29: 1111.55 | I29: 2377.74 | J29: 435.7 | K29: 1059.09 | L29: 830.12 | M29: 2676.03 | N29: 17658.4
A30: Pass Through
A31: Fixed Utility Income | B31: 0 | C31: 997.16 | D31: 423.66 | E31: 334.72 | F31: 567.5 | G31: 958.45 | H31: 897.33 | I31: 852.09 | J31: 1788.12 | K31: 1557.94 | L31: 1190.06 | M31: 1702.1 | N31: 11269.13 | O31: 4201
A32: Total Pass Through | B32: 0 | C32: 997.16 | D32: 423.66 | E32: 334.72 | F32: 567.5 | G32: 958.45 | H32: 897.33 | I32: 852.09 | J32: 1788.12 | K32: 1557.94 | L32: 1190.06 | M32: 1702.1 | N32: 11269.13
A33: Deposit & Maintenance Income
A34: Surrendered Security Deposit | B34: 0 | C34: 800 | D34: 800 | E34: 578 | F34: 351 | G34: 820 | H34: 560 | I34: 1060 | J34: 1000 | K34: 1900 | L34: 2325 | M34: 198 | N34: 10392 | O34: 4301
A35: Resident Responsible - Labor | B35: 0 | C35: 175 | D35: 0 | E35: 500 | F35: 0 | G35: 0 | H35: 0 | I35: 180 | J35: 0 | K35: 0 | L35: 0 | M35: 0 | N35: 855 | O35: 4303
A36: Resident Responsible - Supplies | B36: 0 | C36: 130 | D36: 45 | E36: 580 | F36: 415 | G36: 1540 | H36: 430 | I36: 4040 | J36: 0 | K36: 580 | L36: 640 | M36: 1840 | N36: 10240 | O36: 4304
A37: Resident Responsible - Cleaning | B37: 300 | C37: 1718.32 | D37: 1171 | E37: 1787 | F37: 1282 | G37: 2178.2 | H37: 1041.4 | I37: 837 | J37: 310 | K37: 4134 | L37: 5250 | M37: 1340 | N37: 21348.92 | O37: 4305
A38: Resident Responsible - Lockout/Lock Change | B38: 0 | C38: 0 | D38: 75 | E38: 230 | F38: 0 | G38: 0 | H38: 0 | I38: 80 | J38: 0 | K38: 0 | L38: 0 | M38: 0 | N38: 385 | O38: 4307
A39: Resident Responsible - Plumbing | B39: 0 | C39: 93.75 | D39: 0 | E39: 112.5 | F39: 0 | G39: 0 | H39: 0 | I39: 0 | J39: 0 | K39: 105.22 | L39: 0 | M39: 0 | N39: 311.47 | O39: 4309
A40: Resident Responsible - Haul Off | B40: 200 | C40: 1200 | D40: 1200 | E40: 1200 | F40: 1200 | G40: 2400 | H40: 400 | I40: 400 | J40: 200 | K40: 1200 | L40: 800 | M40: 800 | N40: 11200 | O40: 4310
A41: Resident Responsible - Miscellaneous | B41: 0 | C41: 130 | D41: 140 | E41: 711 | F41: 1500 | G41: 110 | H41: 800 | I41: 2602 | J41: 490 | K41: 90 | L41: 1575 | M41: 1830 | N41: 9978 | O41: 4311
A42: Total Deposit & Maintenance Income | B42: 500 | C42: 4247.07 | D42: 3431 | E42: 5698.5 | F42: 4748 | G42: 7048.2 | H42: 3231.4 | I42: 9199 | J42: 2000 | K42: 8009.22 | L42: 10590 | M42: 6008 | N42: 64710.39
A43: Other Income
A44: Laundry Income | B44: 494.5 | C44: 578 | D44: 868.5 | E44: 716.5 | F44: 464.75 | G44: 448.25 | H44: 496.5 | I44: 0 | J44: 301 | K44: 409.75 | L44: 0 | M44: 602.25 | N44: 5380 | O44: 4401
A45: Cable/Internet Income | B45: 0 | C45: 0 | D45: 605.22 | E45: 0 | F45: 0 | G45: 0 | H45: 557.06 | I45: 0 | J45: 0 | K45: 0 | L45: 0 | M45: 0 | N45: 1162.28 | O45: 4406
A46: Miscellaneous Income | B46: 0 | C46: 108 | D46: 0 | E46: 150 | F46: 0 | G46: 0 | H46: 0 | I46: 0 | J46: 0 | K46: 673.84 | L46: 0 | M46: 0 | N46: 931.84 | O46: 4407
A47: Total Other Income | B47: 494.5 | C47: 686 | D47: 1473.72 | E47: 866.5 | F47: 464.75 | G47: 448.25 | H47: 1053.56 | I47: 0 | J47: 301 | K47: 1083.59 | L47: 0 | M47: 602.25 | N47: 7474.12
A48: Management Income
A49: Management Supplies Income | B49: 0 | C49: 0 | D49: 0 | E49: 0 | F49: -106.3 | G49: 0 | H49: 0 | I49: 0 | J49: 0 | K49: 0 | L49: 0 | M49: 0 | N49: -106.3 | O49: 4702
A50: Total Management Income | B50: 0 | C50: 0 | D50: 0 | E50: 0 | F50: -106.3 | G50: 0 | H50: 0 | I50: 0 | J50: 0 | K50: 0 | L50: 0 | M50: 0 | N50: -106.3
A51: Total Operating Income | B51: 89180.26 | C51: 92302.47 | D51: 91099.73 | E51: 100434.64 | F51: 97379.1 | G51: 95991.76 | H51: 85453.03 | I51: 91351.29 | J51: 82605.07 | K51: 88032.3 | L51: 84663.76 | M51: 84954.48 | N51: 1083447.9
A52: Expense
A53: Expenses
A54: General & Administrative
A55: Bank Fees | B55: 0 | C55: 0 | D55: 0 | E55: 0 | F55: 16.6 | G55: 0 | H55: 0 | I55: 21.4 | J55: 0 | K55: 12.6 | L55: 654.2 | M55: 14.6 | N55: 719.4 | O55: 6009
A56: Advertising | B56: 468 | C56: 986 | D56: 986 | E56: 986 | F56: 986 | G56: 819.94 | H56: 518 | I56: 1036 | J56: 518 | K56: 518 | L56: 518 | M56: 518 | N56: 8857.94 | O56: 6010
A57: Management Fees | B57: 2505.2 | C57: 2472.57 | D57: 2545.79 | E57: 2792.79 | F57: 2432.12 | G57: 2295.26 | H57: 2719.39 | I57: 1973.56 | J57: 2556.82 | K57: 2272.97 | L57: 2493.96 | M57: 2458.33 | N57: 29518.76 | O57: 6014
A58: Postage and Delivery | B58: 0 | C58: 0 | D58: 0 | E58: 69 | F58: 0 | G58: 0 | H58: 0 | I58: 0 | J58: 0 | K58: 0 | L58: 0 | M58: 0 | N58: 69 | O58: 6015
A59: Total General & Administrative | B59: 2973.2 | C59: 3458.57 | D59: 3531.79 | E59: 3847.79 | F59: 3434.72 | G59: 3115.2 | H59: 3237.39 | I59: 3030.96 | J59: 3074.82 | K59: 2803.57 | L59: 3666.16 | M59: 2990.93 | N59: 39165.1
A60: Total Expenses | B60: 2973.2 | C60: 3458.57 | D60: 3531.79 | E60: 3847.79 | F60: 3434.72 | G60: 3115.2 | H60: 3237.39 | I60: 3030.96 | J60: 3074.82 | K60: 2803.57 | L60: 3666.16 | M60: 2990.93 | N60: 39165.1
A61: Repairs & Maintenance
A62: Maintenance | B62: 1698.75 | C62: 4232.5 | D62: 2137.5 | E62: 4906.25 | F62: 1218.5 | G62: 4225.25 | H62: 1742.5 | I62: 152.5 | J62: 1177.39 | K62: 356.67 | L62: 2080.3 | M62: 3569.77 | N62: 27497.88 | O62: 6101
A63: Plumbing Repairs | B63: 2648.75 | C63: 2684.95 | D63: 2175 | E63: 2175 | F63: 1462.5 | G63: 2632.5 | H63: 3430 | I63: 695 | J63: 75 | K63: 827.65 | L63: 610.1 | M63: 495.88 | N63: 19912.33 | O63: 6104
A64: Electrical Repairs | B64: 0 | C64: 0 | D64: 0 | E64: 0 | F64: 0 | G64: 0 | H64: 0 | I64: 979.65 | J64: 0 | K64: 0 | L64: 0 | M64: 0 | N64: 979.65 | O64: 6105
A65: Lock Sets | B65: 270 | C65: 400 | D65: 237.5 | E65: 500 | F65: 0 | G65: 50 | H65: 75 | I65: 550 | J65: 50 | K65: 337.5 | L65: 527.49 | M65: 412.5 | N65: 3409.99 | O65: 6106
A66: Pest Control | B66: 2381.55 | C66: 838.97 | D66: 764.47 | E66: 1596.75 | F66: 714.47 | G66: 2155.33 | H66: 1530.71 | I66: 952.63 | J66: 1872.78 | K66: 1018.61 | L66: 1535.52 | M66: 844.38 | N66: 16206.17 | O66: 6107
A67: Repairs | B67: 2010.78 | C67: 802.7 | D67: 2697.1 | E67: 3246.51 | F67: 785 | G67: 385.6 | H67: 470 | I67: 109.5 | J67: 129.5 | K67: 255.06 | L67: 438.54 | M67: 462.8 | N67: 11793.09 | O67: 6108
A68: Supplies | B68: 3423.68 | C68: 3634.3 | D68: 5777.52 | E68: 6958.93 | F68: 5864.97 | G68: 4099.77 | H68: 7150.33 | I68: 1927.48 | J68: 3925.82 | K68: 1703.02 | L68: 1592.72 | M68: 3644.49 | N68: 49703.03 | O68: 6110
A69: Contractor Labor | B69: 1538.69 | C69: 2796 | D69: -650 | E69: 5805.8 | F69: 1735 | G69: 4673 | H69: 2575 | I69: 300 | J69: 0 | K69: 1550 | L69: 1100 | M69: 1536.98 | N69: 22960.47 | O69: 6114
A70: Air filter Maintenance | B70: 0 | C70: 0 | D70: 0 | E70: 2800 | F70: 0 | G70: 0 | H70: 2800 | I70: 0 | J70: 0 | K70: 3175 | L70: 0 | M70: 0 | N70: 8775 | O70: 6190
A71: Total Repairs & Maintenance | B71: 13972.2 | C71: 15389.42 | D71: 13139.09 | E71: 27989.24 | F71: 11780.44 | G71: 18221.45 | H71: 19773.54 | I71: 5666.76 | J71: 7230.49 | K71: 9223.51 | L71: 7884.67 | M71: 10966.8 | N71: 161237.61
A72: Contracted Services
A73: Landscaping | B73: 675 | C73: 325 | D73: 400 | E73: 375 | F73: 0 | G73: 0 | H73: 0 | I73: 0 | J73: 0 | K73: 0 | L73: 0 | M73: 0 | N73: 1775 | O73: 6201
A74: Haul trash | B74: 400 | C74: 2000 | D74: 2400 | E74: 3600 | F74: 2000 | G74: 2037.5 | H74: 2000 | I74: 487.5 | J74: 450 | K74: 987.5 | L74: 2000 | M74: 1012.5 | N74: 19375 | O74: 6202
A75: Vendor Property Trash Removal | B75: 0 | C75: 0 | D75: 2307.91 | E75: 1911.79 | F75: 2065.16 | G75: 0 | H75: 2996.47 | I75: 1993.93 | J75: 0 | K75: 1102.99 | L75: 1088.02 | M75: 1271.38 | N75: 14737.65 | O75: 6210
A76: Total Contracted Services | B76: 1075 | C76: 2325 | D76: 5107.91 | E76: 5886.79 | F76: 4065.16 | G76: 2037.5 | H76: 4996.47 | I76: 2481.43 | J76: 450 | K76: 2090.49 | L76: 3088.02 | M76: 2283.88 | N76: 35887.65
A77: Cleaning & Janitorial
A78: Cleaning | B78: 1176.8 | C78: 652.8 | D78: 2475.96 | E78: 3837.6 | F78: 1096.8 | G78: 1270.2 | H78: 2102.4 | I78: 1594.2 | J78: 852.6 | K78: 2395.8 | L78: 1864.6 | M78: 1943.8 | N78: 21263.56 | O78: 6301
A79: Carpet Cleaning | B79: 146.14 | C79: 1356.43 | D79: 605.53 | E79: 437.89 | F79: 0 | G79: 297.84 | H79: 678.39 | I79: 100 | J79: 2188.92 | K79: 1248.37 | L79: 1529.73 | M79: 259.8 | N79: 8849.04 | O79: 6302
A80: Total Cleaning & Janitorial | B80: 1322.94 | C80: 2009.23 | D80: 3081.49 | E80: 4275.49 | F80: 1096.8 | G80: 1568.04 | H80: 2780.79 | I80: 1694.2 | J80: 3041.52 | K80: 3644.17 | L80: 3394.33 | M80: 2203.6 | N80: 30112.6
A81: Utility Expenses
A82: Utilities | B82: 0 | C82: 0 | D82: 0 | E82: 0 | F82: 0 | G82: 1074.08 | H82: 1343.48 | I82: 1368.96 | J82: 1178.82 | K82: 1075.27 | L82: 1097.46 | M82: 2122.68 | N82: 9260.75 | O82: 6401
A83: Utilities Electric | B83: 5329.43 | C83: 274.78 | D83: 1207.88 | E83: 8448.99 | F83: 9007.85 | G83: 9338.28 | H83: 8834.86 | I83: 5875.11 | J83: 1639.69 | K83: 7833.94 | L83: 4676.03 | M83: 11772.27 | N83: 74239.11 | O83: 6402
A84: Utilities Gas | B84: 0 | C84: 0 | D84: 500.63 | E84: 863.56 | F84: 1565.74 | G84: 0 | H84: 740.42 | I84: 1307.99 | J84: 3240.85 | K84: 3543.86 | L84: 3610.38 | M84: 1286.14 | N84: 16659.57 | O84: 6403
A85: Utilities Water | B85: 2544.5 | C85: 1045.76 | D85: 1445.05 | E85: 293.7 | F85: 1250.58 | G85: 0 | H85: 190.14 | I85: 0 | J85: 0 | K85: 190.14 | L85: 190.14 | M85: 190.14 | N85: 7340.15 | O85: 6404
A86: Total Utility Expenses | B86: 7873.93 | C86: 1320.54 | D86: 3153.56 | E86: 9606.25 | F86: 11824.17 | G86: 10412.36 | H86: 11108.9 | I86: 8552.06 | J86: 6059.36 | K86: 12643.21 | L86: 9574.01 | M86: 15371.23 | N86: 107499.58
A87: Tax Expenses
A88: Property Taxes | B88: 0 | C88: 0 | D88: 0 | E88: 0 | F88: 0 | G88: 0 | H88: 0 | I88: 61639.03 | J88: 0 | K88: 0 | L88: 0 | M88: 0 | N88: 61639.03 | O88: 6501
A89: Total Tax Expenses | B89: 0 | C89: 0 | D89: 0 | E89: 0 | F89: 0 | G89: 0 | H89: 0 | I89: 61639.03 | J89: 0 | K89: 0 | L89: 0 | M89: 0 | N89: 61639.03
A90: Insurance Expenses
A91: Insurance | B91: 7581.72 | C91: 1248.66 | D91: 6065.87 | E91: 6065.87 | F91: 6065.87 | G91: 20957.8 | H91: 6065.87 | I91: 6065.87 | J91: 12131.74 | K91: 6724.87 | L91: 6065.87 | M91: 6065.87 | N91: 91105.88 | O91: 6601
A92: Total Insurance Expenses | B92: 7581.72 | C92: 1248.66 | D92: 6065.87 | E92: 6065.87 | F92: 6065.87 | G92: 20957.8 | H92: 6065.87 | I92: 6065.87 | J92: 12131.74 | K92: 6724.87 | L92: 6065.87 | M92: 6065.87 | N92: 91105.88
A93: Onsite Salaries & Wages
A94: Onsite Maintenance | B94: 0 | C94: 0 | D94: 0 | E94: 0 | F94: 4333.33 | G94: 4333.33 | H94: 4333.33 | I94: 4333.33 | J94: 4333.33 | K94: 4333.33 | L94: 4333.33 | M94: 4333.33 | N94: 34666.64 | O94: 6701
A95: On Site Manger | B95: 4325 | C95: 4325 | D95: 4325 | E95: 4325 | F95: 4325 | G95: 4325 | H95: 4325 | I95: 4325 | J95: 4325 | K95: 4325 | L95: 4325 | M95: 4325 | N95: 51900 | O95: 6702
A96: On Site Assistant Manager | B96: 3114 | C96: 3114 | D96: 3114 | E96: 3114 | F96: 0 | G96: 0 | H96: 0 | I96: 0 | J96: 0 | K96: 0 | L96: 0 | M96: 0 | N96: 12456 | O96: 6703
A97: Total Onsite Salaries & Wages | B97: 7439 | C97: 7439 | D97: 7439 | E97: 7439 | F97: 8658.33 | G97: 8658.33 | H97: 8658.33 | I97: 8658.33 | J97: 8658.33 | K97: 8658.33 | L97: 8658.33 | M97: 8658.33 | N97: 99022.64
A98: Misc. Operating Expenses
A99: Other Expenses | B99: 0 | C99: 94.18 | D99: 53.7 | E99: 54.45 | F99: 0 | G99: 0 | H99: 0 | I99: -850 | J99: 0 | K99: 0 | L99: 0 | M99: 0 | N99: -647.67 | O99: 6901
A100: Court Cost-Eviction | B100: 154 | C100: 1024 | D100: 154 | E100: 921 | F100: 2248 | G100: -408 | H100: 767 | I100: 408 | J100: -254 | K100: 154 | L100: 0 | M100: 254 | N100: 5422 | O100: 6903
A101: Office Supplies | B101: 0 | C101: 0 | D101: 0 | E101: 151.86 | F101: 117.26 | G101: 55.33 | H101: 51.89 | I101: 105.77 | J101: 65.97 | K101: 0 | L101: 429.66 | M101: 97.23 | N101: 1074.97 | O101: 6910
A102: Security System | B102: 0 | C102: 0 | D102: 0 | E102: 39.48 | F102: 39.48 | G102: 39.48 | H102: 0 | I102: 78.84 | J102: 39.36 | K102: 39.36 | L102: 39.36 | M102: 39.36 | N102: 354.72 | O102: 6918
...

Sheet Amarillo RR
A1: Rent Roll
A3: Units: Active
A4: Include Non-Revenue Units: No
A6: Unit | B6: BD/BA | C6: Tenant | D6: Status | E6: Sqft | F6: Market Rent | G6: Rent | H6: Deposit | I6: Lease From | J6: Lease To | K6: Move-in | L6: Move-out | M6: Monthly Rent / SF
A7: 101E | B7: 3/2.00 | C7: Alejandra M. Lopez | D7: Current | E7: 1184 | F7: 950 | G7: 1225 | H7: 0 | I7: 46066 | J7: 46418 | K7: 46066 | M7: 1.03
A8: 101W | B8: 2/1.00 | C8: Jackie L. Clark | D8: Current | E8: 784 | F8: 760 | G8: 952 | H8: 0 | I8: 45476 | J8: 46234 | K8: 45476 | M8: 1.21
A9: 102E | B9: 0/1.00 | C9: David M. Ardoff | D9: Current | E9: 400 | F9: 625 | G9: 650 | H9: 210 | I9: 45425 | J9: 46142 | K9: 45425 | M9: 1.63
A10: 102W | B10: 1/1.00 | C10: Ransom B. Wilson | D10: Current | E10: 592 | F10: 675 | G10: 952 | H10: 200 | I10: 45086 | J10: 46326 | K10: 45086 | M10: 1.61
A11: 103E | B11: 2/1.00 | C11: Tiarra L. Harris | D11: Current | E11: 784 | F11: 760 | G11: 1075 | H11: 200 | I11: 45288 | J11: 46265 | K11: 45288 | M11: 1.37
A12: 103W | B12: 3/2.00 | C12: Selena Montes | D12: Current | E12: 1184 | F12: 950 | G12: 1225 | H12: 350 | I12: 45890 | J12: 46234 | K12: 45890 | M12: 1.03
A13: 104E | B13: 1/1.00 | C13: Bobby R. Lamb | D13: Current | E13: 592 | F13: 675 | G13: 675 | H13: 0 | I13: 46071 | J13: 46418 | K13: 46071 | M13: 1.14
A14: 104W | B14: 1/1.00 | C14: Ruby Renteria | D14: Evict | E14: 592 | F14: 675 | G14: 675 | H14: 0 | I14: 45995 | J14: 46356 | K14: 45995 | M14: 1.14
A15: 105E | B15: 1/1.00 | C15: Adam C. Chinea | D15: Current | E15: 592 | F15: 675 | G15: 952 | H15: 200 | I15: 45328 | J15: 46418 | K15: 45328 | M15: 1.61
A16: 105W | B16: 1/1.00 | C16: Mary C. Purviance | D16: Current | E16: 592 | F16: 675 | G16: 845 | H16: 200 | I16: 45303 | J16: 46387 | K16: 45303 | M16: 1.43
A17: 106E | B17: 1/1.00 | C17: Torrey Welch | D17: Notice-Unrented | E17: 592 | F17: 675 | G17: 952 | H17: 200 | I17: 45761 | J17: 46112 | K17: 45761 | L17: 46121 | M17: 1.61
A18: 106W | B18: 1/1.00 | C18: Charles L. Lutz | D18: Current | E18: 592 | F18: 675 | G18: 952 | H18: 850 | I18: 45008 | J18: 46446 | K18: 45008 | M18: 1.61
A19: 107E | B19: 3/2.00 | C19: Natalia Garza | D19: Current | E19: 1184 | F19: 950 | G19: 1147 | H19: 210 | I19: 45474 | K19: 45474 | M19: 0.97
A20: 107W | B20: 1/1.00 | C20: Quinston C. Graves | D20: Current | E20: 592 | F20: 675 | G20: 675 | H20: 0 | I20: 46087 | J20: 46446 | K20: 46087 | M20: 1.14
A21: 108E | B21: 2/1.00 | C21: Jiorge Ayala | D21: Current | E21: 784 | F21: 760 | G21: 825 | H21: 0 | I21: 46082 | J21: 46446 | K21: 46082 | M21: 1.05
A22: 108W | B22: 1/1.00 | C22: Chris K. Even | D22: Current | E22: 592 | F22: 675 | G22: 845 | H22: 350 | I22: 45839 | J22: 46203 | K22: 45839 | M22: 1.43
A23: 109E | B23: 0/1.00 | C23: Meagon R. Laws | D23: Evict | E23: 400 | F23: 625 | G23: 750 | H23: 350 | I23: 45791 | J23: 46326 | K23: 45791 | M23: 1.88
A24: 109W | B24: 1/1.00 | C24: Nichole A. Servantez | D24: Current | E24: 592 | F24: 675 | G24: 845 | H24: 350 | I24: 45918 | J24: 46265 | K24: 45918 | M24: 1.43
A25: 110E | B25: 1/1.00 | D25: Vacant-Unrented | E25: 592 | F25: 675 | H25: 0
A26: 110W | B26: 1/1.00 | C26: Christopher C. Hood | D26: Current | E26: 592 | F26: 675 | G26: 675 | H26: 0 | I26: 46000 | J26: 46356 | K26: 46000 | M26: 1.14
A27: 111E | B27: 1/1.00 | C27: Kaylee H. Bunt | D27: Current | E27: 592 | F27: 675 | G27: 825 | H27: 0 | I27: 46023 | J27: 46387 | K27: 46023 | M27: 1.39
A28: 111W | B28: 1/1.00 | C28: Terry Morford | D28: Current | E28: 592 | F28: 675 | G28: 675 | H28: 0 | I28: 44652 | J28: 46418 | K28: 44805 | M28: 1.14
A29: 112E | B29: 1/1.00 | C29: Tara Pantel | D29: Current | E29: 592 | F29: 675 | G29: 795 | H29: 0 | I29: 44652 | K29: 44805 | M29: 1.34
A30: 112W | B30: 1/1.00 | C30: Robert C. Lyons | D30: Current | E30: 592 | F30: 675 | G30: 952 | H30: 350 | I30: 45790 | J30: 46507 | K30: 45790 | M30: 1.61
A31: 113E | B31: 1/1.00 | C31: Paul Maurice | D31: Current | E31: 592 | F31: 650 | G31: 952 | H31: 200 | I31: 45267 | J31: 46387 | K31: 45267 | M31: 1.61
A32: 113W | B32: 1/1.00 | C32: Travis L. Hart | D32: Notice-Unrented | E32: 592 | F32: 675 | G32: 845 | H32: 350 | I32: 45863 | J32: 46234 | K32: 45863 | L32: 46121 | M32: 1.43
A33: 114E | B33: 0/1.00 | C33: Jorden N. Zimmermann | D33: Notice-Unrented | E33: 400 | F33: 625 | G33: 625 | H33: 0 | I33: 46078 | J33: 46418 | K33: 46078 | L33: 46125 | M33: 1.56
A34: 114W | B34: 1/1.00 | C34: Pablo S. Davila | D34: Current | E34: 592 | F34: 675 | G34: 825 | H34: 825 | I34: 46082 | J34: 46265 | K34: 46082 | M34: 1.39
A35: 115E | B35: 2/1.00 | C35: Suzette A. Marsh | D35: Current | E35: 784 | F35: 760 | G35: 1158 | H35: 200 | I35: 45575 | J35: 46295 | K35: 45575 | M35: 1.48
A36: 115W | B36: 1/1.00 | C36: Amanda R. Montez | D36: Current | E36: 592 | F36: 675 | G36: 650 | H36: 625 | I36: 45078 | J36: 46538 | K36: 45078 | M36: 1.1
A37: 116E | B37: 3/2.00 | C37: Shuquetia R. Dexter | D37: Current | E37: 1184 | F37: 950 | G37: 1075 | H37: 210 | I37: 45484 | J37: 46203 | K37: 45484 | M37: 0.91
A38: 116W | B38: 1/1.00 | C38: Joseph D. Moore | D38: Notice-Rented | E38: 592 | F38: 675 | G38: 952 | H38: 0 | I38: 45078 | J38: 46295 | K38: 45078 | L38: 46112 | M38: 1.61
A39: 117E | B39: 1/1.00 | C39: Rolando G. Rodriguez | D39: Current | E39: 592 | F39: 675 | G39: 695 | H39: 0 | I39: 45964 | J39: 46326 | K39: 45964 | M39: 1.17
A40: 117W | B40: 1/1.00 | C40: Kerry L. Dittrich | D40: Current | E40: 592 | F40: 675 | G40: 993 | H40: 0 | I40: 46057 | J40: 46418 | K40: 46057 | M40: 1.68
A41: 118E | B41: 1/1.00 | C41: Cassandra K. Gonzales | D41: Current | E41: 592 | F41: 675 | G41: 825 | H41: 0 | I41: 46071 | J41: 46418 | K41: 46071 | M41: 1.39
A42: 118W | B42: 1/1.00 | C42: Christopher Mitchell | D42: Current | E42: 592 | F42: 675 | G42: 879 | H42: 0 | I42: 45055 | J42: 46173 | K42: 45055 | M42: 1.48
A43: 119E | B43: 1/1.00 | C43: Yesenia Davila | D43: Current | E43: 592 | F43: 675 | G43: 845 | H43: 210 | I43: 45444 | J43: 46173 | K43: 45444 | M43: 1.43
A44: 119W | B44: 1/1.00 | C44: Justin L. Utera | D44: Current | E44: 592 | F44: 675 | G44: 952 | H44: 200 | I44: 45093 | J44: 46295 | K44: 45093 | M44: 1.61
A45: 120E | B45: 0/1.00 | C45: Teresa S. Villegas | D45: Current | E45: 400 | F45: 625 | G45: 750 | H45: 0 | I45: 46097 | J45: 46295 | K45: 46097 | M45: 1.88
A46: 120W | B46: 1/1.00 | C46: Colby J. Williams | D46: Current | E46: 592 | F46: 675 | G46: 825 | H46: 0 | I46: 46082 | J46: 46446 | K46: 46082 | M46: 1.39
A47: 121E | B47: 2/1.00 | C47: Landan R. Mclain | D47: Notice-Unrented | E47: 784 | F47: 760 | G47: 760 | H47: 0 | I47: 45968 | J47: 46326 | K47: 45968 | L47: 46116 | M47: 0.97
A48: 121W | B48: 1/1.00 | C48: Katiuska N. Pulido | D48: Current | E48: 592 | F48: 650 | G48: 825 | H48: 200 | I48: 45627 | J48: 46173 | K48: 45627 | M48: 1.39
A49: 122E | B49: 3/2.00 | D49: Vacant-Unrented | E49: 1184 | F49: 950 | H49: 0
A50: 122W | B50: 3/2.00 | C50: Davon R. Hart | D50: Current | E50: 1184 | F50: 950 | G50: 1075 | H50: 170 | I50: 45450 | J50: 46538 | K50: 45450 | M50: 0.91
A51: 123E | B51: 1/1.00 | D51: Vacant-Unrented | E51: 592 | F51: 675 | H51: 0
A52: 123W | B52: 1/1.00 | C52: Michael W. Pilkington | D52: Current | E52: 592 | F52: 675 | G52: 845 | H52: 250 | I52: 45778 | J52: 46507 | K52: 45778 | M52: 1.43
A53: 124E | B53: 1/1.00 | C53: Bryan T. Blankenburg | D53: Current | E53: 592 | F53: 675 | G53: 800 | H53: 210 | I53: 45569 | J53: 46295 | K53: 45569 | M53: 1.35
A54: 124W | B54: 1/1.00 | C54: Gregorio Villanueva | D54: Current | E54: 592 | F54: 675 | G54: 845 | H54: 350 | I54: 45883 | J54: 46234 | K54: 45883 | M54: 1.43
A55: 125E | B55: 1/1.00 | C55: Anthony T. McKnight | D55: Current | E55: 592 | F55: 675 | G55: 650 | H55: 0 | I55: 44946 | J55: 46477 | K55: 44946 | M55: 1.1
A56: 126E | B56: 1/1.00 | D56: Vacant-Unrented | E56: 592 | F56: 675 | H56: 0
A57: 127E | B57: 1/1.00 | C57: John R. Meehan | D57: Current | E57: 592 | F57: 675 | G57: 952 | H57: 200 | I57: 45329 | J57: 46418 | K57: 45329 | M57: 1.61
A58: 128E | B58: 1/1.00 | C58: Grant A. Cox | D58: Notice-Unrented | E58: 592 | F58: 675 | G58: 825 | H58: 0 | I58: 46049 | J58: 46387 | K58: 46049 | L58: 46112 | M58: 1.39
A59: 201E | B59: 2/1.50 | C59: Madison R. Moore | D59: Evict | E59: 992 | F59: 780 | G59: 1005 | H59: 350 | I59: 45839 | J59: 46203 | K59: 45839 | M59: 1.01
A60: 201W | B60: 1/1.00 | C60: Harvey R. Patteson | D60: Current | E60: 592 | F60: 675 | G60: 825 | H60: 0 | I60: 46097 | J60: 46446 | K60: 46097 | M60: 1.39
A61: 202E | B61: 2/1.50 | C61: Ethan B. Borden | D61: Current | E61: 992 | F61: 780 | G61: 780 | H61: 780 | I61: 46009 | J61: 46356 | K61: 46009 | M61: 0.79
A62: 202W | B62: 1/1.00 | C62: Stephon D. Woods | D62: Current | E62: 592 | F62: 675 | G62: 825 | H62: 0 | I62: 46023 | J62: 46203 | K62: 46023 | M62: 1.39
A63: 203E | B63: 2/1.50 | C63: Haley N. Garza | D63: Current | E63: 992 | F63: 780 | G63: 1005 | H63: 0 | I63: 46085 | J63: 46446 | K63: 46085 | M63: 1.01
A64: 203W | B64: 1/1.00 | C64: Austin B. Walsh | D64: Current | E64: 592 | F64: 675 | G64: 845 | H64: 0 | I64: 45712 | J64: 46234 | K64: 45712 | M64: 1.43
A65: 204E | B65: 2/1.50 | C65: Javier J. Delgado Torres | D65: Notice-Unrented | E65: 992 | F65: 780 | G65: 780 | H65: 780 | I65: 46044 | J65: 46418 | K65: 46044 | L65: 46118 | M65: 0.79
A66: 204W | B66: 1/1.00 | C66: Gary M. Vandiver | D66: Current | E66: 592 | F66: 675 | G66: 675 | H66: 0 | I66: 44998 | J66: 46265 | K66: 44998 | M66: 1.14
A67: 205E | B67: 2/1.50 | C67: Alitash I. Eubank | D67: Current | E67: 992 | F67: 780 | G67: 1005 | H67: 1005 | I67: 46101 | J67: 46446 | K67: 46101 | M67: 1.01
A68: 205W | B68: 1/1.00 | C68: Israel X. Ramos | D68: Current | E68: 592 | F68: 675 | G68: 695 | H68: 350 | I68: 45764 | K68: 45764 | M68: 1.17
A69: 206E | B69: 2/1.50 | C69: Aurelia C. Valenzuela | D69: Current | E69: 992 | F69: 780 | G69: 1005 | H69: 0 | I69: 45688 | J69: 46387 | K69: 45688 | M69: 1.01
A70: 206W | B70: 1/1.00 | C70: Erik J. Reimers | D70: Current | E70: 592 | F70: 675 | G70: 845 | H70: 350 | I70: 45839 | J70: 46203 | K70: 45839 | M70: 1.43
A71: 207E | B71: 2/1.50 | C71: Kalija V. Bell | D71: Current | E71: 992 | F71: 780 | G71: 1158 | H71: 200 | I71: 45251 | J71: 46326 | K71: 45251 | M71: 1.17
A72: 207W | B72: 1/1.00 | C72: Jeremy D. Wesley | D72: Current | E72: 592 | F72: 675 | G72: 695 | H72: 250 | I72: 45730 | J72: 46265 | K72: 45730 | M72: 1.17
A73: 208E | B73: 1/1.00 | D73: Vacant-Unrented | E73: 592 | F73: 675 | H73: 0
A74: 208W | B74: 1/1.00 | C74: Michael A. Reynolds | D74: Current | E74: 592 | F74: 650 | G74: 845 | H74: 350 | I74: 45839 | J74: 46203 | K74: 45839 | M74: 1.43
A75: 209E | B75: 2/1.50 | C75: Melissa S. Bittner | D75: Current | E75: 992 | F75: 780 | G75: 850 | H75: 250 | I75: 45625 | J75: 46326 | K75: 45625 | M75: 0.86
A76: 209W | B76: 1/1.00 | C76: Kerry D. Kilpatrick | D76: Current | E76: 592 | F76: 650 | G76: 695 | H76: 200 | I76: 45211 | J76: 46295 | K76: 45211 | M76: 1.17
A77: 210E | B77: 2/1.50 | C77: Marco A. Saenz | D77: Current | E77: 992 | F77: 780 | G77: 1175 | H77: 200 | I77: 45240 | K77: 45240 | M77: 1.18
A78: 210W | B78: 1/1.00 | C78: Myrella A. Garcia | D78: Current | E78: 592 | F78: 675 | G78: 825 | H78: 825 | I78: 46108 | J78: 46446 | K78: 46108 | M78: 1.39
A79: 211E | B79: 2/1.50 | C79: Juan Sanjavier | D79: Current | E79: 992 | F79: 850 | G79: 1005 | H79: 0 | I79: 46096 | J79: 46295 | K79: 46096 | M79: 1.01
A80: 211W | B80: 1/1.00 | C80: Margaret K. Ardry | D80: Current | E80: 592 | F80: 675 | G80: 845 | H80: 350 | I80: 45853 | J80: 46203 | K80: 45853 | M80: 1.43
A81: 212E | B81: 2/1.50 | C81: Jamey C. Tevebaugh | D81: Current | E81: 992 | F81: 780 | G81: 1075 | H81: 250 | I81: 45597 | J81: 46356 | K81: 45597 | M81: 1.08
A82: 212W | B82: 1/1.00 | C82: Easton T. West | D82: Current | E82: 592 | F82: 675 | G82: 945 | H82: 350 | I82: 45809 | K82: 45809 | M82: 1.6
A83: 213E | B83: 2/1.50 | C83: Corey L. Million | D83: Current | E83: 992 | F83: 780 | G83: 1005 | H83: 350 | I83: 45938 | K83: 45938 | M83: 1.01
A84: 213W | B84: 1/1.00 | C84: Ashlie P. Montoya | D84: Current | E84: 592 | F84: 675 | G84: 845 | H84: 170 | I84: 45566 | J84: 46295 | K84: 45566 | M84: 1.43
A85: 214E | B85: 2/1.50 | C85: Brandon M. Williams | D85: Current | E85: 992 | F85: 780 | G85: 780 | H85: 0 | I85: 46106 | J85: 46295 | K85: 46106 | M85: 0.79
A86: 214W | B86: 1/1.00 | C86: Miguel D. Candanedo | D86: Current | E86: 592 | F86: 675 | G86: 825 | H86: 0 | I86: 46082 | J86: 46446 | K86: 46082 | M86: 1.39
A87: 215E | B87: 2/1.50 | C87: Elijah A. Pardee | D87: Current | E87: 992 | F87: 780 | G87: 780 | H87: 0 | I87: 46054 | J87: 46418 | K87: 46054 | M87: 0.79
A88: 215W | B88: 1/1.00 | C88: Joshua L. Edwards | D88: Current | E88: 592 | F88: 675 | G88: 800 | H88: 0 | I88: 45044 | J88: 46507 | K88: 45044 | M88: 1.35
A89: 216E | B89: 2/1.50 | C89: Trienan C. Haiduk | D89: Current | E89: 992 | F89: 780 | G89: 780 | H89: 0 | I89: 45705 | J89: 46265 | K89: 45705 | M89: 0.79
A90: 216W | B90: 1/1.00 | C90: Katelyn J. Gunter | D90: Current | E90: 592 | F90: 675 | G90: 695 | H90: 350 | I90: 45922 | J90: 46265 | K90: 45922 | M90: 1.17
A91: 217E | B91: 2/1.50 | C91: Benjamin W. Tyson | D91: Current | E91: 992 | F91: 780 | G91: 1005 | H91: 0 | I91: 45967 | J91: 46326 | K91: 45967 | M91: 1.01
A92: 217W | B92: 1/1.00 | C92: Tametris March | D92: Current | E92: 592 | F92: 675 | G92: 695 | H92: 0 | I92: 44593 | J92: 46265 | K92: 44805 | M92: 1.17
A93: 218E | B93: 2/1.50 | C93: Sherry R. Polite | D93: Current | E93: 992 | F93: 780 | G93: 780 | H93: 0 | I93: 46111 | J93: 46295 | K93: 46111 | M93: 0.79
A94: 218W | B94: 1/1.00 | C94: Michael Alexander | D94: Current | E94: 592 | F94: 675 | G94: 952 | H94: 0 | I94: 44409 | J94: 46234 | K94: 44805 | M94: 1.61
A95: 219E | B95: 2/1.50 | C95: Haylie I. Hernnandez | D95: Current | E95: 992 | F95: 780 | G95: 1005 | H95: 350 | I95: 46111 | J95: 46446 | K95: 46111 | M95: 1.01
A96: 219W | B96: 3/2.00 | C96: Chelsea M. Taylor | D96: Current | E96: 1184 | F96: 950 | G96: 1300 | H96: 250 | I96: 45658 | K96: 45658 | M96: 1.1
A97: 220E | B97: 2/1.50 | C97: Maria D. Cabrera | D97: Current | E97: 992 | F97: 780 | G97: 1005 | H97: 350 | I97: 45905 | J97: 46265 | K97: 45905 | M97: 1.01
A98: 220W | B98: 1/1.00 | C98: Dalton T. Barrett | D98: Current | E98: 592 | F98: 675 | G98: 952 | H98: 0 | I98: 44965 | J98: 46418 | K98: 44965 | M98: 1.61
A99: 221E | B99: 1/1.00 | D99: Vacant-Unrented | E99: 592 | F99: 675 | H99: 0
A100: 221W | B100: 1/1.00 | C100: Sandy Balentine | D100: Current | E100: 592 | F100: 675 | G100: 845 | H100: 210 | I100: 45448 | J100: 46538 | K100: 45448 | M100: 1.43
A101: 222E | B101: 2/1.50 | C101: Crescence A. Miller | D101: Current | E101: 992 | F101: 780 | G101: 780 | H101: 0 | I101: 45706 | J101: 46234 | K101: 45706 | M101: 0.79
A102: 222W | B102: 1/1.00 | C102: Ryan A. Johnson | D102: Current | E102: 592 | F102: 675 | G102: 845 | H102: 250 | I102: 45733 | J102: 46265 | K102: 45733 | M102: 1.43
...

Sheet Oak T-12
A1: Oak Cliff Multifamily
A2: Profit and Loss by Month
A3: Rolling 12 Month
B5: Jun-25 | C5: Jul-25 | D5: Aug-25 | E5: Sep-25 | F5: Oct-25 | G5: Nov-25 | H5: Dec-25 | I5: Jan-26 | J5: Feb-26 | K5: Mar-26 | L5: Apr-26 | M5: May-26 | N5: Total
A6: Income
A7: RENTAL INCOME | B7: 122840.49 | C7: 123040.73 | D7: 121596.41 | E7: 121318.15 | F7: 123154.81 | G7: 130433.66 | H7: 128103.55 | I7: 133464.29 | J7: 139847.48 | K7: 141809.5 | L7: 136166.73 | M7: 140383.68 | N7: 1562159.5
A8: TOTAL RENTS | B8: 122840.49 | C8: 123040.73 | D8: 121596.41 | E8: 121318.15 | F8: 123154.81 | G8: 130433.66 | H8: 128103.55 | I8: 133464.29 | J8: 139847.48 | K8: 141809.5 | L8: 136166.73 | M8: 140383.68 | N8: 1562159.5
A9: CONCESSIONS | B9: -200 | C9: -400 | D9: -425 | E9: -850 | F9: -510 | G9: -2965 | H9: -1105 | I9: -840 | J9: -1401 | K9: -1309 | L9: -850 | M9: -1399.68 | N9: -12254.68
A10: FEES
A11: NSF Fees Collected | B11: 0 | C11: 0 | D11: 0 | E11: 0 | F11: 0 | G11: 0 | H11: 0 | I11: 0 | J11: 35 | K11: 35 | L11: 0 | M11: 140 | N11: 210
A12: Transfer Fee | B12: 0 | C12: 0 | D12: 0 | E12: 200 | F12: 0 | G12: 0 | H12: 0 | I12: 0 | J12: 0 | K12: 0 | L12: 0 | M12: 0 | N12: 200
A13: Pet Fee | B13: 0 | C13: 0 | D13: 200 | E13: 100 | F13: 0 | G13: 100 | H13: 50 | I13: 300 | J13: 300 | K13: 0 | L13: 0 | M13: 0 | N13: 1050
A14: Admin Fee | B14: 0 | C14: 0 | D14: 268 | E14: 0 | F14: 0 | G14: 0 | H14: 0 | I14: 0 | J14: 0 | K14: 0 | L14: 0 | M14: 0 | N14: 268
A15: Application Fee | B15: 0 | C15: 0 | D15: 0 | E15: 0 | F15: 0 | G15: 0 | H15: 0 | I15: 0 | J15: 0 | K15: 0 | L15: 0 | M15: 0 | N15: 0
A16: Risk Fee | B16: 0 | C16: 0 | D16: 0 | E16: 0 | F16: 0 | G16: 0 | H16: 0 | I16: 0 | J16: 0 | K16: 0 | L16: 0 | M16: 0 | N16: 0
A17: Late Fee | B17: 1350.84 | C17: 563 | D17: 772.5 | E17: 742 | F17: 220 | G17: 1244 | H17: 881.7 | I17: 279.5 | J17: 546 | K17: 388.2 | L17: 0 | M17: 725.17 | N17: 7712.91
A18: Utility Reimbursement Fee | B18: 140 | C18: 101 | D18: 59 | E18: 90 | F18: 50 | G18: 110 | H18: 65 | I18: 65 | J18: 70 | K18: 80 | L18: 50 | M18: 80 | N18: 960
A19: TOTAL FEES | B19: 1490.84 | C19: 664 | D19: 1299.5 | E19: 1132 | F19: 270 | G19: 1454 | H19: 996.7 | I19: 644.5 | J19: 951 | K19: 503.2 | L19: 50 | M19: 945.17 | N19: 10400.91
A20: PARKING INCOME | B20: 707 | C20: 625 | D20: 645 | E20: 505 | F20: 410 | G20: 525 | H20: 375 | I20: 485 | J20: 505 | K20: 405 | L20: 480 | M20: 455 | N20: 6122
A21: TENANT IMPROVEMENTS | B21: 25 | C21: 0 | D21: 60 | E21: 60 | F21: 0 | G21: 40 | H21: 0 | I21: 100 | J21: 0 | K21: 0 | L21: 0 | M21: 0 | N21: 285
A22: MISCELLANEOUS INCOME | B22: 0 | C22: 0 | D22: 0 | E22: 0 | F22: 0 | G22: 0 | H22: 0 | I22: 25 | J22: 10 | K22: 0 | L22: 0 | M22: 0 | N22: 35
A23: Total Operating Income | B23: 124863.33 | C23: 123929.73 | D23: 123175.91 | E23: 122165.15 | F23: 123324.81 | G23: 129487.66 | H23: 128370.25 | I23: 133878.79 | J23: 139912.48 | K23: 141408.7 | L23: 135846.73 | M23: 140384.17 | N23: 1566747.7
A26: Expenses
A27: 1. OPERATING EXPENSES (CONTROLLABLE)
A28: CONTROLLABLE EXPENSES
A29: CONTRACT SERVICES - ALL OTHER / REPAIRS & MAINTENANCE | C29: 85 | D29: 1255 | F29: 1885 | G29: 1500 | K29: 3200 | L29: 350 | M29: 6664 | N29: 14939
A30: COURT / EVICTION FEES | B30: 1000 | C30: 1541.82 | F30: 1231 | G30: 695.5 | H30: 1740.41 | I30: 1349 | J30: 948 | K30: 828 | L30: 1623 | M30: 1632.01 | N30: 12588.74
A31: LANDSCAPING | B31: 250 | C31: 250 | D31: 250 | E31: 250 | F31: 250 | G31: 250 | H31: 250 | I31: 250 | J31: 250 | K31: 250 | L31: 250 | M31: 250 | N31: 3000
A32: PAYROLL MAINTENANCE TEAM | B32: 10011 | C32: 9581.5 | D32: 9525.25 | E32: 10592.63 | F32: 11379.51 | G32: 12385.5 | H32: 10418.7 | I32: 11598 | J32: 14400 | K32: 14794.92 | L32: 11108 | M32: 14624.82 | N32: 140419.83
A33: PAYROLL OFFICE TEAM | B33: 8312 | C33: 10516 | D33: 14379.73 | E33: 10870.98 | F33: 12896 | G33: 10030 | H33: 15149.31 | I33: 6786.4 | J33: 9080 | K33: 13578.5 | L33: 11430.5 | M33: 13323 | N33: 136352.42
A34: PEST CONTROL | B34: 252 | C34: 252 | D34: 266 | E34: 266 | F34: 266 | G34: 266 | H34: 266 | I34: 266 | J34: 266 | K34: 266 | L34: 222.54 | M34: 81.19 | N34: 2935.73
A35: SOFTWARE / SUBSCRIPTIONS | B35: 205 | C35: 745.29 | D35: 800 | E35: 324.24 | F35: 1347.12 | G35: 1108.06 | H35: 428.12 | I35: 428.12 | J35: 868.12 | K35: 28.12 | L35: 428.12 | M35: 428.12 | N35: 7138.43
A36: LICENSE / PERMITS | F36: 1768 | M36: 609 | N36: 2377
A37: SECURITY | E37: 420 | F37: 780 | G37: 1120 | H37: 880 | I37: 320 | J37: 680 | K37: 720 | L37: 375 | M37: 480 | N37: 5775
A38: SUPPLIES | B38: 3090.92 | C38: 3306 | D38: 4404.3 | E38: 2868 | F38: 2938.66 | G38: 3667.32 | H38: 4005.48 | I38: 3880.87 | J38: 3341 | K38: 2126.55 | L38: 2974.63 | M38: 1563.61 | N38: 38167.34
A39: TELEPHONE / INTERNET | B39: 185.78 | C39: 195.84 | D39: 195.84 | E39: 195.84 | F39: 195.84 | G39: 195.84 | H39: 195.84 | I39: 195.84 | J39: 195.84 | K39: 140.74 | L39: 222.54 | M39: 222.49 | N39: 2338.27
A40: UTILITY - ELECTRIC | B40: 527.87 | C40: 561.65 | D40: 567.47 | E40: 617.3 | F40: 630.54 | G40: 604.17 | H40: 533.98 | I40: 616.74 | J40: 569.6 | K40: 555.17 | L40: 499.5 | M40: 527.35 | N40: 6811.34
A41: UTILITY - GAS | B41: 110.26 | C41: 117.38 | D41: 118.18 | E41: 117.06 | F41: 115.91 | G41: 117.36 | H41: 128.56 | I41: 127.18 | J41: 123.34 | K41: 121.26 | L41: 127.82 | M41: 125.52 | N41: 1449.83
A42: UTILITY - TRASH | B42: 3618.74 | C42: 3796.42 | D42: 3839.15 | E42: 3671.33 | F42: 3667.32 | G42: 4434.35 | H42: 4087 | I42: 3821.57 | J42: 2478.05 | K42: 3793.62 | L42: 4974.67 | M42: 4974.67 | N42: 47156.89
A43: UTILITY - WATER | B43: 8686.1 | C43: 9248.03 | D43: 8487.01 | E43: 10964.96 | F43: 8066.87 | G43: 8070.54 | H43: 8288.13 | I43: 10766.26 | J43: 8988.06 | K43: 7897.11 | L43: 6566.42 | M43: 6580.74 | N43: 102610.23
A44: Total CONTROLLABLE EXPENSES | B44: 36249.67 | C44: 40196.93 | D44: 44087.93 | E44: 41158.34 | F44: 47417.77 | G44: 44444.64 | H44: 46371.53 | I44: 40405.98 | J44: 42188.01 | K44: 48299.99 | L44: 41152.74 | M44: 52086.52 | N44: 524060.05
A45: Total 1. OPERATING EXPENSES (CONTROLLABLE) | B45: 36249.67 | C45: 40196.93 | D45: 44087.93 | E45: 41158.34 | F45: 47417.77 | G45: 44444.64 | H45: 46371.53 | I45: 40405.98 | J45: 42188.01 | K45: 48299.99 | L45: 41152.74 | M45: 52086.52 | N45: 524060.05
A46: 2. OPERATING EXPENSES (NON-CONTROLLABLE)
A47: NON-CONTROLLABLE
A48: Total PROPERTY MANAGEMENT FEE | B48: 4914.46 | C48: 4986.61 | D48: 5182.78 | E48: 4821.97 | F48: 5084.72 | G48: 4725.92 | H48: 5729.55 | I48: 4992.64 | J48: 5679.73 | K48: 5726.32 | L48: 5275.31 | M48: 5529.78 | N48: 62649.79
A49: PROPERTY INSURANCE | B49: 5036 | C49: 5036 | D49: 6041.25 | E49: 6332.14 | F49: 6332.14 | G49: 6332.14 | H49: 6332.14 | I49: 6332.14 | J49: 6332.14 | K49: 6332.14 | L49: 6332.14 | M49: 6332.14 | N49: 73102.51
A50: PROPERTY TAX | B50: 14945 | C50: 14945 | D50: 14945 | E50: 14945 | F50: 14945 | G50: 14945 | H50: 14945 | I50: 14945 | J50: 14945 | K50: 14945 | L50: 14945 | M50: 14945 | N50: 179340
A51: Total NON-CONTROLLABLE | B51: 24895.46 | C51: 24967.61 | D51: 26169.03 | E51: 26099.11 | F51: 26361.86 | G51: 26003.06 | H51: 27006.69 | I51: 26269.78 | J51: 26956.87 | K51: 27003.46 | L51: 26552.45 | M51: 26806.92 | N51: 315092.3
A53: NOI
A54: Total Operating Expenses | B54: 61145.13 | C54: 65164.54 | D54: 70256.96 | E54: 67257.45 | F54: 73779.63 | G54: 70447.7 | H54: 73378.22 | I54: 66675.76 | J54: 69144.88 | K54: 75303.45 | L54: 67705.19 | M54: 78893.44 | N54: 839152.35
A55: Net Operating Income (NOI) | B55: 63718.2 | C55: 58765.19 | D55: 52918.95 | E55: 54907.7 | F55: 49545.18 | G55: 59039.96 | H55: 54992.03 | I55: 67203.03 | J55: 70767.6 | K55: 66105.25 | L55: 68141.54 | M55: 61490.73 | N55: 727595.36

Sheet Oak RR
A1: Oak Cliff Multifamily As of: 06/17/2026 (Today) Include Non-Revenue Units: No Include Advertised Rent: Yes
A2: Unit | B2: BD/ BA | C2: Unit Type | D2: Tenant | E2: Status | F2: Sqft | G2: Market Rent | H2: Rent | I2: Monthly Charges | J2: Deposit | K2: Lease From | L2: Lease To | M2: Move-in | N2: Move-out
A3: Unit2/1.00 101 | C3: 2/1 | E3: Vacant-Rented | F3: 762 | G3: 1200 | I3: 0 | J3: 0
A4: Unit1/1.00 102 | C4: 1/1 | D4: James Burks | E4: Current | F4: 651 | G4: 1100 | H4: 1100 | J4: 0 | K4: 45003 | L4: 46446 | M4: 45312
A5: Unit1/1.00 103 | C5: 1/1 | D5: Don Boyd (DHA - VOUCHER) | E5: Current | F5: 651 | G5: 1100 | H5: 1050 | J5: 300 | K5: 44927 | L5: 46428 | M5: 44945
A6: Unit1/1.00 104 | C6: 1/1 | D6: Audrey (GPH-Voucher) Jones | E6: Current | F6: 651 | G6: 1100 | H6: 1050 | J6: 500 | K6: 45499 | L6: 46568 | M6: 45499
A7: Unit1/1.00 105 | C7: 1/1 | D7: Tradavius Walker | E7: Current | F7: 651 | G7: 1100 | H7: 1050 | J7: 500 | K7: 46042 | L7: 46387 | M7: 46042
A8: Unit1/1.00 106 | C8: 1/1 | D8: Victoria Burley | E8: Current | F8: 651 | G8: 1100 | H8: 1010 | J8: 500 | K8: 45936 | L8: 46300 | M8: 45936
A9: Unit1/1.00 107 | C9: 1/1 | D9: Gloria Nzeadibe | E9: Current | F9: 651 | G9: 1100 | H9: 1050 | J9: 500 | K9: 46054 | L9: 46418 | M9: 46054
A10: Unit2/1.00 108 | C10: 2/1 | D10: Crystal Brazile | E10: Current | F10: 762 | G10: 1200 | H10: 1200 | J10: 500 | K10: 46178 | L10: 46568 | M10: 46178
A11: Unit2/1.00 109 | C11: 2/1 | D11: Anita Rincon | E11: Current | F11: 762 | G11: 1200 | H11: 1150 | J11: 300 | K11: 45084 | L11: 46538 | M11: 45085
A12: Unit1/1.00 110 | C12: 1/1 | D12: Floyd Johnson | E12: Current | F12: 651 | G12: 1100 | H12: 1050 | J12: 400 | K12: 46054 | L12: 46418 | M12: 46054
A13: Unit1/1.00 111 | C13: 1/1 | D13: Pearlie Smith | E13: Current | F13: 651 | G13: 1100 | H13: 1010 | J13: 500 | K13: 45841 | L13: 46599 | M13: 45841
A14: Unit1/1.00 112 | C14: 1/1 | D14: Christopher Tarver (DHA - VOUCHER) | E14: Current | F14: 651 | G14: 1100 | H14: 1050 | J14: 250 | K14: 45352 | L14: 46479 | M14: 44615
A15: Unit1/1.00 113 | C15: 1/1 | D15: Chesley Griffin (DHA - RAPID - NO VOUCHER) | E15: Current | F15: 651 | G15: 1100 | H15: 1075 | J15: 500 | K15: 45514 | L15: 46234 | M15: 45154
A16: Unit1/1.00 114 | C16: 1/1 | D16: Andre Johnson | E16: Current | F16: 651 | G16: 1100 | H16: 1030 | I16: 15 | J16: 0 | K16: 45108 | L16: 46568 | M16: 44348
A17: Unit1/1.00 115 | C17: 1/1 | D17: Mary/Billy Prater/ Skinner | E17: Current | F17: 651 | G17: 1100 | H17: 975 | I17: 15 | J17: 0 | K17: 45905 | L17: 46446 | M17: 45905
A18: Unit2/1.00 116 | C18: 2/1 | D18: Jimmy Pipkins | E18: Current | F18: 762 | G18: 1200 | H18: 1150 | J18: 0 | K18: 45383 | L18: 46477 | M18: 44169
A19: Unit2/1.00 201 | C19: 2/1 | D19: Lashonna Weaver | E19: Current | F19: 762 | G19: 1200 | H19: 1100 | J19: 0 | K19: 45818 | L19: 46507 | M19: 45818
A20: Unit2/1.00 202 | C20: 2/1 | D20: Vermon Mixon | E20: Current | F20: 762 | G20: 1200 | H20: 1035 | J20: 500 | K20: 45550 | L20: 46295 | M20: 45550
A21: Unit2/1.00 203 | C21: 2/1 | D21: Carol Williams | E21: Current | F21: 762 | G21: 1200 | H21: 1100 | J21: 0 | K21: 45912 | L21: 46276 | M21: 45912
A22: Unit2/1.00 204 | C22: 2/1 | D22: Kenya Bryant | E22: Current | F22: 762 | G22: 1200 | H22: 1100 | J22: 0 | K22: 46129 | L22: 46203 | M22: 46129
A23: Unit2/1.00 205 | C23: 2/1 | D23: Robert Brown | E23: Current | F23: 762 | G23: 1200 | H23: 1100 | J23: 500 | K23: 46116 | L23: 46480 | M23: 46116
A24: Unit2/1.00 206 | C24: 2/1 | D24: Rebecca Tinnell | E24: Current | F24: 762 | G24: 1200 | H24: 1100 | J24: 300 | K24: 45992 | L24: 46356 | M24: 45992
A25: Unit2/1.00 207 | C25: 2/1 | D25: Rayshundre Jackson | E25: Notice-Unrented | F25: 762 | G25: 1200 | H25: 1100 | J25: 500 | K25: 46054 | L25: 46418 | M25: 46054 | N25: 46190
A26: Unit1/1.00 208 | C26: 1/1 | D26: Jamie Aubrey (DHA - RAPID - NO VOUCHER) | E26: Current | F26: 651 | G26: 1100 | H26: 925 | J26: 500 | K26: 45222 | L26: 46568 | M26: 45231
A27: Unit2/1.00 209 | C27: 2/1 | D27: Quellar Malone | E27: Current | F27: 762 | G27: 1200 | H27: 1150 | I27: 25 | J27: 500 | K27: 45530 | L27: 46259 | M27: 45530
A28: Unit2/1.00 210 | C28: 2/1 | D28: Billy Hall | E28: Current | F28: 762 | G28: 1200 | H28: 1150 | J28: 500 | K28: 45352 | L28: 46568 | M28: 45352
A29: Unit2/1.00 211 | C29: 2/1 | D29: Schreta Goynes | E29: Current | F29: 762 | G29: 1200 | H29: 1100 | J29: 300 | K29: 45962 | L29: 46326 | M29: 45962
A30: Unit2/1.00 212 | C30: 2/1 | D30: Robert Moffett | E30: Current | F30: 762 | G30: 1200 | H30: 1075 | J30: 0 | K30: 45819 | L30: 46568 | M30: 45819
A31: Unit2/1.00 213 | C31: 2/1 | D31: Evangelina Cueto | E31: Current | F31: 762 | G31: 1200 | H31: 1125 | J31: 500 | K31: 45332 | L31: 46446 | M31: 45332
A32: Unit2/1.00 214 | C32: 2/1 | D32: Jacobyia Johnson | E32: Current | F32: 762 | G32: 1200 | H32: 1100 | J32: 300 | K32: 45999 | L32: 46356 | M32: 45999
A33: Unit2/1.00 215 | C33: 2/1 | D33: Metro Care | E33: Current | F33: 762 | G33: 1200 | H33: 1075 | J33: 0 | K33: 45909 | L33: 46273 | M33: 45909
A34: Unit2/1.00 216 | C34: 2/1 | D34: Sadie Bernard | E34: Current | F34: 762 | G34: 1200 | H34: 1150 | I34: 25 | J34: 500 | K34: 45544 | L34: 46273 | M34: 45544
A35: Unit2/1.00 217 | C35: 2/1 | D35: Arnoldo Rafael Torrealba Mujica | E35: Current | F35: 762 | G35: 1200 | H35: 1100 | J35: 0 | K35: 45282 | L35: 46356 | M35: 45334
A36: Unit2/1.00 218 | C36: 2/1 | D36: Jessie Johnson | E36: Current | F36: 762 | G36: 1200 | H36: 1100 | I36: 10 | J36: 500 | K36: 46120 | L36: 46484 | M36: 46120
A37: Unit1/1.00 219 | C37: 1/1 | D37: Helene Johnson | E37: Current | F37: 651 | G37: 1100 | H37: 1050 | J37: 300 | K37: 45992 | L37: 46356 | M37: 45992
A38: Unit2/1.00 220 | C38: 2/1 | E38: Vacant-Unrented | F38: 762 | G38: 1200 | I38: 0 | J38: 0
A39: Unit2/1.00 221 | C39: 2/1 | D39: Hugo Sanchez | E39: Current | F39: 762 | G39: 1200 | H39: 1150 | I39: 100 | J39: 0 | K39: 45653 | L39: 46507 | M39: 45653
A40: Unit2/1.00 222 | C40: 2/1 | D40: Willie Jackson | E40: Current | F40: 762 | G40: 1200 | H40: 1100 | J40: 0 | K40: 46096 | L40: 46446 | M40: 46096
A41: Unit2/1.00 223 | C41: 2/1 | D41: Miguel Angel Esteban | E41: Current | F41: 762 | G41: 1200 | H41: 1150 | I41: 50 | J41: 500 | K41: 45721 | L41: 46450 | M41: 45721
A42: Unit2/1.00 224 | C42: 2/1 | E42: Vacant-Unrented | F42: 762 | G42: 1200 | I42: 0 | J42: 0
A43: Unit2/1.00 301 | C43: 2/1 | D43: Jacquline Irving | E43: Current | F43: 762 | G43: 1200 | H43: 1150 | J43: 500 | K43: 45547 | L43: 46265 | M43: 45547
A44: Unit2/1.00 302 | C44: 2/1 | D44: Glenda Hudson | E44: Current | F44: 762 | G44: 1200 | H44: 1100 | J44: 0 | K44: 45951 | L44: 46315 | M44: 45951
A45: Unit2/1.00 303 | C45: 2/1 | D45: Angela Smith | E45: Current | F45: 762 | G45: 1200 | H45: 1140 | J45: 500 | K45: 45720 | L45: 46449 | M45: 45720
A46: Unit2/1.00 304 | C46: 2/1 | D46: Nakia Mauldin | E46: Current | F46: 762 | G46: 1200 | H46: 1150 | J46: 500 | K46: 45565 | L46: 46265 | M46: 45565
A47: Unit2/1.00 305 | C47: 2/1 | D47: Rochelle Smith | E47: Current | F47: 762 | G47: 1200 | H47: 1100 | J47: 300 | K47: 46023 | L47: 46387 | M47: 46023
A48: Unit2/1.00 306 | C48: 2/1 | D48: Morgan Lambert | E48: Current | F48: 762 | G48: 1200 | H48: 1100 | J48: 300 | K48: 45954 | L48: 46318 | M48: 45954
A49: Unit2/1.00 307 | C49: 2/1 | D49: Jasmine Brown (DHA-VOUCHER) | E49: Current | F49: 762 | G49: 1200 | H49: 1150 | J49: 300 | K49: 45323 | L49: 46418 | M49: 44835
A50: Unit1/1.00 308 | C50: 1/1 | D50: Henry Simpkins (Family Gateway) | E50: Current | F50: 651 | G50: 1100 | H50: 1050 | J50: 500 | K50: 45786 | L50: 46265 | M50: 45786
A51: Unit2/1.00 309 | C51: 2/1 | D51: Gloria Allen | E51: Current | F51: 762 | G51: 1200 | H51: 1115 | I51: 20 | J51: 0 | K51: 45078 | L51: 46599 | M51: 44410
A52: Unit2/1.00 310 | C52: 2/1 | D52: Khyla Miller | E52: Current | F52: 762 | G52: 1200 | H52: 1100 | J52: 0 | K52: 45906 | L52: 46270 | M52: 45906
A53: Unit2/1.00 311 | C53: 2/1 | E53: Vacant-Rented | F53: 762 | G53: 1200 | I53: 0 | J53: 0
A54: Unit2/1.00 312 | C54: 2/1 | D54: Tiqusha Cromarty | E54: Current | F54: 762 | G54: 1200 | H54: 1100 | I54: 25 | J54: 0 | K54: 45804 | L54: 46234 | M54: 45804
A55: Unit2/1.00 313 | C55: 2/1 | D55: Tarsl Dixon | E55: Current | F55: 762 | G55: 1200 | H55: 1100 | J55: 300 | K55: 45954 | L55: 46318 | M55: 45954
A56: Unit2/1.00 314 | C56: 2/1 | D56: Sydney Butts | E56: Current | F56: 762 | G56: 1200 | H56: 1100 | J56: 250 | K56: 46185 | L56: 46538 | M56: 46185
A57: Unit2/1.00 315 | C57: 2/1 | E57: Vacant-Unrented | F57: 762 | G57: 1200 | I57: 0 | J57: 0
A58: Unit1/1.00 316 | C58: 1/1 | D58: Charles Potter | E58: Current | F58: 651 | G58: 1100 | H58: 1050 | J58: 500 | K58: 46143 | L58: 46326 | M58: 46143
A59: Unit2/1.00 317 | C59: 2/1 | D59: Regina Delk (DHA) | E59: Current | F59: 762 | G59: 1200 | H59: 1100 | J59: 300 | K59: 45975 | L59: 46326 | M59: 45975
A60: Unit2/1.00 | C60: 2/1 | D60: Wallace Wigfall | E60: Current | F60: 762 | G60: 1200 | H60: 1100 | J60: 500 | K60: 45783 | L60: 46512 | M60: 45783
A61: Unit2/1.00 319 | C61: 2/1 | D61: Todd Murphy | E61: Current | F61: 762 | G61: 1200 | H61: 1115 | J61: 500 | K61: 45549 | L61: 46326 | M61: 45184
A62: Unit2/1.00 320 | C62: 2/1 | D62: Carolyn Davis | E62: Current | F62: 762 | G62: 1200 | H62: 1100 | J62: 500 | K62: 45964 | L62: 46329 | M62: 45964
A63: Unit2/1.00 321 | C63: 2/1 | D63: Stefon Baker | E63: Current | F63: 762 | G63: 1200 | H63: 1100 | J63: 500 | K63: 46126 | L63: 46507 | M63: 46126
A64: Unit2/1.00 322 | C64: 2/1 | D64: Luciano Guerrero | E64: Current | F64: 762 | G64: 1200 | H64: 1150 | J64: 0 | K64: 45748 | L64: 46235 | M64: 45748
A65: Unit2/1.00 323 | C65: 2/1 | D65: Gladys Turner | E65: Current | F65: 762 | G65: 1200 | H65: 1100 | J65: 500 | K65: 45931 | L65: 46295 | M65: 45931
A66: Unit2/1.00 324 | C66: 2/1 | D66: Nicole Johnson | E66: Current | F66: 762 | G66: 1200 | H66: 1100 | J66: 300 | K66: 45968 | L66: 46332 | M66: 45968
A67: Unit2/1.00 401 | C67: 2/1 | D67: Ty'Shawnna Miller (DHA-VOUCHER) | E67: Current | F67: 762 | G67: 1200 | H67: 1100 | J67: 0 | K67: 45903 | L67: 46265 | M67: 45904
A68: Unit1/1.00 402 | C68: 1/1 | D68: Richard Roberson | E68: Current | F68: 651 | G68: 1100 | H68: 1050 | J68: 500 | K68: 46146 | L68: 46538 | M68: 46148
A69: Unit2/1.00 403 | C69: 2/1 | D69: Jose Herrera | E69: Current | F69: 762 | G69: 1200 | H69: 1200 | I69: 10 | J69: 0 | K69: 45413 | L69: 46326 | M69: 43709
A70: Unit2/1.00 404 | C70: 2/1 | D70: Victor Velazco | E70: Current | F70: 762 | G70: 1200 | H70: 1150 | J70: 0 | K70: 45170 | L70: 46265 | M70: 43770
A71: Unit2/1.00 405 | C71: 2/1 | D71: Tory Lewis | E71: Current | F71: 762 | G71: 1200 | H71: 1100 | J71: 279.1 | K71: 46168 | L71: 46507 | M71: 46168
A72: Unit2/1.00 406 | C72: 2/1 | E72: Vacant-Unrented | F72: 762 | G72: 1200 | I72: 0 | J72: 0
A73: Unit1/1.00 407 | C73: 1/1 | D73: Keithan Johnson (DHA) | E73: Current | F73: 651 | G73: 1100 | H73: 1100 | J73: 500 | K73: 45540 | L73: 46295 | M73: 45540
A74: Unit2/1.00 408 | C74: 2/1 | D74: Cindy Sillas | E74: Current | F74: 762 | G74: 1200 | H74: 1200 | I74: 10.5 | J74: 0 | K74: 46178 | L74: 46568 | M74: 46178
A75: Unit2/1.00 409 | C75: 2/1 | D75: Natonya Smith | E75: Current | F75: 762 | G75: 1200 | H75: 1150 | J75: 500 | K75: 45597 | L75: 46326 | M75: 45597
A76: Unit2/1.00 410 | C76: 2/1 | D76: Rosa Gutierrez | E76: Current | F76: 762 | G76: 1200 | H76: 1115 | J76: 300 | K76: 45323 | L76: 46418 | M76: 44916
A77: Unit2/1.00 411 | C77: 2/1 | D77: Ashieya Webb | E77: Current | F77: 762 | G77: 1200 | H77: 1100 | J77: 500 | K77: 46054 | L77: 46418 | M77: 46054
A78: Unit2/1.00 412 | C78: 2/1 | D78: Dora Barren | E78: Current | F78: 762 | G78: 1200 | H78: 1100 | J78: 500 | K78: 46031 | L78: 46387 | M78: 46031
A79: Unit2/1.00 413 | C79: 2/1 | D79: Datron Mitchell | E79: Current | F79: 762 | G79: 1200 | H79: 1100 | J79: 500 | K79: 46054 | L79: 46418 | M79: 46054
A80: Unit2/1.00 414 | C80: 2/1 | E80: Vacant-Unrented | F80: 762 | G80: 1200 | I80: 0 | J80: 0
A81: Unit1/1.00 415 | C81: 1/1 | D81: Alisa Orta | E81: Current | F81: 651 | G81: 1100 | H81: 1050 | I81: 25 | J81: 500 | K81: 45931 | L81: 46295 | M81: 45931
A82: Unit2/1.00 416 | C82: 2/1 | D82: Juan Antonio Rodriguez | E82: Current | F82: 762 | G82: 1200 | H82: 1150 | J82: 500 | K82: 45577 | L82: 46306 | M82: 45577
A83: Unit2/1.00 417 | C83: 2/1 | D83: Gina Blanton | E83: Current | F83: 762 | G83: 1200 | H83: 1100 | I83: 25 | J83: 500 | K83: 45471 | L83: 46568 | M83: 45471
A84: Unit2/1.00 418 | C84: 2/1 | D84: Canandra Boyce (GPH-VOUCHER) | E84: Current | F84: 762 | G84: 1200 | H84: 1005 | J84: 300 | K84: 45200 | L84: 46326 | M84: 44825
A85: Unit2/1.00 419 | C85: 2/1 | E85: Vacant-Unrented | F85: 762 | G85: 1200 | I85: 0 | J85: 0
A86: Unit2/1.00 420 | C86: 2/1 | D86: Octavius Jackson | E86: Current | F86: 762 | G86: 1200 | H86: 1100 | J86: 500 | K86: 46085 | L86: 46446 | M86: 46085
A87: Unit2/1.00 421 | C87: 2/1 | D87: Hugo Sanchez | E87: Current | F87: 762 | G87: 1200 | H87: 1150 | J87: 0 | K87: 45555 | L87: 46265 | M87: 45555
A88: Unit2/1.00 422 | C88: 2/1 | D88: Nacole Lacey | E88: Current | F88: 762 | G88: 1200 | H88: 1100 | I88: 20 | J88: 500 | K88: 45931 | L88: 46295 | M88: 45931
A89: Unit2/1.00 423 | C89: 2/1 | D89: Jarius Critterdon (DHA-VOUCHER) | E89: Current | F89: 762 | G89: 1200 | H89: 1200 | J89: 500 | K89: 45231 | L89: 46326 | M89: 45231
A90: Unit2/1.00 424 | C90: 2/1 | D90: Eddie Tenison | E90: Current | F90: 762 | G90: 1200 | H90: 1100 | J90: 500 | K90: 46056 | L90: 46418 | M90: 46056
A91: Unit2/1.00 501 | C91: 2/1 | D91: Arianna (Family Gateway) Mason | E91: Current | F91: 762 | G91: 1200 | H91: 1200 | J91: 500 | K91: 45252 | L91: 46326 | M91: 45261
A92: Unit2/1.00 502 | C92: 2/1 | D92: Samone Furlough | E92: Current | F92: 762 | G92: 1200 | H92: 1050 | J92: 0 | K92: 45231 | L92: 46356 | M92: 44440
A93: Unit2/1.00 503 | C93: 2/1 | D93: Hipolito Gutierrez | E93: Current | F93: 762 | G93: 1200 | H93: 1150 | J93: 0 | K93: 45697 | L93: 46426 | M93: 45697
A94: Unit2/1.00 504 | C94: 2/1 | D94: Shimeka Boyce (DHA) | E94: Current | F94: 762 | G94: 1200 | H94: 1200 | J94: 500 | K94: 45461 | L94: 46568 | M94: 45461
A95: Unit2/1.00 505 | C95: 2/1 | E95: Vacant-Rented | F95: 762 | G95: 1200 | I95: 0 | J95: 0
A96: Unit2/1.00 506 | C96: 2/1 | D96: LeBaron Wallace | E96: Current | F96: 762 | G96: 1200 | H96: 1100 | J96: 500 | K96: 46055 | L96: 46418 | M96: 46055
A97: Unit2/1.00 507 | C97: 2/1 | D97: Runnell Zachery | E97: Current | F97: 762 | G97: 1200 | H97: 1100 | J97: 500 | K97: 46072 | L97: 46418 | M97: 46072
A98: Unit2/1.00 508 | C98: 2/1 | D98: Kurt (VET-DHA- VOUCHER) Harris | E98: Current | F98: 762 | G98: 1200 | H98: 1100 | J98: 500 | K98: 45261 | L98: 46356 | M98: 45231
A99: Unit2/1.00 509 | C99: 2/1 | D99: Janet W. Smith | E99: Current | F99: 762 | G99: 1200 | H99: 1105 | J99: 0 | K99: 45658 | L99: 46387 | M99: 44569
A100: Unit2/1.00 510 | C100: 2/1 | D100: Jerry Benjamin | E100: Current | F100: 762 | G100: 1200 | H100: 1050 | J100: 500 | K100: 45722 | L100: 46451 | M100: 45722
...

Sheet WTAMSH T-12
A1: Income Statement
A2: April 2025 - Mar 2026
B4: Account | C4: Apr 2025 | D4: May 2025 | E4: Jun 2025 | F4: Jul 2025 | G4: Aug 2025 | H4: Sep 2025 | I4: Oct 2025 | J4: Nov 2025 | K4: Dec 2025 | L4: Jan 2026 | M4: Feb 2026 | N4: Mar 2026 | O4: Total
B6: Gross Potential Rent
B7: Market Rent | C7: 126104.35 | D7: 140785.18 | E7: 107855.71 | F7: 99225.4 | G7: 96782.6 | H7: 117223.97 | I7: 109514.26 | J7: 109580.51 | K7: 108553.11 | L7: 99242.36 | M7: 105029.49 | N7: 109528.05 | O7: =SUM(C7:N7) -> 1329425
B8: Gross Potential Rent | C8: 126104.35 | D8: 140785.18 | E8: 107855.71 | F8: 99225.4 | G8: 96782.6 | H8: 117223.97 | I8: 109514.26 | J8: 109580.51 | K8: 108553.11 | L8: 99242.36 | M8: 105029.49 | N8: 109528.05 | O8: =SUM(C8:N8) -> 1329425
B10: Utility set up fee-Recovery | C10: 150 | D10: 1500 | E10: 525 | F10: 600 | G10: 8475 | H10: 675 | I10: 300 | J10: 225 | K10: 150 | L10: 900 | M10: 300 | N10: 430.65 | O10: =SUM(C10:N10) -> 14230.65
B12: Residential Rental Adjustments
B13: Application Fees | C13: 0 | D13: 0 | E13: 0 | F13: 0 | G13: 0 | H13: 0 | I13: 0 | J13: 0 | K13: -200 | L13: 0 | M13: 0 | N13: 0 | O13: =SUM(C13:N13) -> -200
B14: Residential Rental Adjustments | C14: 0 | D14: 0 | E14: 0 | F14: 0 | G14: 0 | H14: 0 | I14: 0 | J14: 0 | K14: -200 | L14: 0 | M14: 0 | N14: 0 | O14: =SUM(C14:N14) -> -200
B16: Residential Other Revenues
B17: Admin Fee | C17: 154 | D17: 0 | E17: 0 | F17: 0 | G17: 0 | H17: 0 | I17: 0 | J17: 0 | K17: 0 | L17: 0 | M17: 0 | N17: 0 | O17: =SUM(C17:N17) -> 154
B18: Late Charges | C18: 1847.82 | D18: 1830.54 | E18: 1503.26 | F18: 1403.56 | G18: 710.78 | H18: 1153.7 | I18: 1046.31 | J18: 1170.97 | K18: 1543.04 | L18: 1388.53 | M18: 1922.81 | N18: 1173.08 | O18: =SUM(C18:N18) -> 16694.4
B19: Miscellaneous Income | C19: 0 | D19: 3102.76 | E19: 1155.53 | F19: 552.5 | G19: 287.54 | H19: 212.46 | I19: 60 | J19: 35 | K19: 1752.5 | L19: 1265.78 | M19: 353.28 | N19: -303.55 | O19: =SUM(C19:N19) -> 8473.8
B20: NSF Fees | C20: 160 | D20: 80 | E20: 40 | F20: 0 | G20: 40 | H20: 120 | I20: 40 | J20: 80 | K20: 160 | L20: 120 | M20: 160 | N20: 80 | O20: =SUM(C20:N20) -> 1080
B21: One-Time Pet Fees | C21: 0 | D21: 0 | E21: 0 | F21: 0 | G21: 0 | H21: 450 | I21: 450 | J21: 451.81 | K21: 0 | L21: 450 | M21: 0 | N21: 450 | O21: =SUM(C21:N21) -> 2251.81
B22: Resident Damage Assessments- Quarterly | C22: 0 | D22: 0 | E22: 0 | F22: 0 | G22: 0 | H22: 0 | I22: 0 | J22: 0 | K22: 275 | L22: 908.23 | M22: 92.5 | N22: 0 | O22: =SUM(C22:N22) -> 1275.73
B23: Trash & Cleaning Fees | C23: 0 | D23: 0 | E23: -29.06 | F23: -88.61 | G23: -130.03 | H23: -65.75 | I23: 0 | J23: -57.64 | K23: 0 | L23: 0 | M23: 0 | N23: 0 | O23: =SUM(C23:N23) -> -371.09
B24: Resident Transfer Fees | C24: 250 | D24: 0 | E24: 0 | F24: 0 | G24: 0 | H24: 0 | I24: 0 | J24: 1700 | K24: 2010.92 | L24: -368.44 | M24: 1348.79 | N24: 253.85 | O24: =SUM(C24:N24) -> 5195.12
B25: Monthly Pet Rent | C25: 290.31 | D25: 259.69 | E25: 300 | F25: 250 | G25: 75 | H25: 125 | I25: 75 | J25: 150 | K25: 125 | L25: 100 | M25: 125 | N25: 150 | O25: =SUM(C25:N25) -> 2025
B26: Short Term Lease Premium | C26: 475 | D26: 475 | E26: 100 | F26: 100 | G26: 0 | H26: 0 | I26: 0 | J26: 0 | K26: 0 | L26: 0 | M26: 0 | N26: 0 | O26: =SUM(C26:N26) -> 1150
B27: Student Turnover - Interior Paint/Dry Wall Reimbursement | C27: 0 | D27: 173.62 | E27: 838.62 | F27: 50 | G27: 2169.34 | H27: -2342.61 | I27: 0 | J27: 0 | K27: 0 | L27: 0 | M27: 0 | N27: 0 | O27: =SUM(C27:N27) -> 888.97
B28: Student Turnover - Carpet Cleaning Reimbursement | C28: 0 | D28: 0 | E28: 0 | F28: 0 | G28: 0 | H28: 6.59 | I28: 0 | J28: 0 | K28: 0 | L28: 0 | M28: 0 | N28: 0 | O28: =SUM(C28:N28) -> 6.59
B29: Student Turnover - General Cleaning | D29: 200 | E29: 1903.28 | F29: 150 | G29: 2109.13 | H29: 650 | I29: 0 | J29: 90.72 | K29: 0 | L29: 360.35 | M29: 0 | N29: 0 | O29: =SUM(C29:N29) -> 5463.48
B30: Student Turnover - Miscellaneous Reimbursement | C30: 0 | D30: 50 | E30: 100 | F30: 0 | G30: 200 | H30: 50 | I30: 0 | J30: 0 | K30: 0 | L30: 0 | M30: 0 | N30: 0 | O30: =SUM(C30:N30) -> 400
B31: Utility Reimbursements - Residents | C31: 17208.71 | D31: 13273.54 | E31: 12732.35 | F31: 14287.09 | G31: 10701.66 | H31: 7769.16 | I31: 10129.73 | J31: 12436.12 | K31: 11106.65 | L31: 10735.03 | M31: 11493.22 | N31: 14259.07 | O31: =SUM(C31:N31) -> 146132.33
B32: Residential Other Revenues | C32: 20385.84 | D32: 19445.15 | E32: 18643.98 | F32: 16704.54 | G32: 16163.42 | H32: 8128.55 | I32: 11801.04 | J32: 16056.98 | K32: 16973.11 | L32: 14959.48 | M32: 15495.6 | N32: 16062.45 | O32: =SUM(C32:N32) -> 190820.14
B34: Income | C34: 146640.19 | D34: 161730.33 | E34: 127024.69 | F34: 116529.94 | G34: 121421.02 | H34: 126027.52 | I34: 121615.3 | J34: 125862.49 | K34: 125476.22 | L34: 115101.84 | M34: 120825.09 | N34: 126021.15 | O34: =SUM(C34:N34) -> 1534275.8
B36: Operating Expenses
B37: Mortgage | C37: 41985.09 | D37: 41985.09 | E37: 0 | F37: 41915 | G37: 41915.18 | H37: 41915 | I37: 41015 | J37: 41915.09 | K37: 41915.09 | L37: 41915.09 | M37: 41915.09 | N37: 41915.09 | O37: =SUM(C37:N37) -> 460305.81
B38: Payroll | C38: 11284.83 | D38: 14155.61 | E38: 13441.07 | F38: 12046.72 | G38: 15760.74 | H38: 9953.3 | I38: 9054.63 | J38: 10307.8 | K38: 11795.41 | L38: 13663.59 | M38: 7493.57 | N38: 9010.85 | O38: =SUM(C38:N38) -> 137968.12
B39: Payroll Taxes | C39: 2040.23 | D39: 3631.38 | E39: 3676.97 | F39: 3049.05 | G39: 5321.36 | H39: 2325.77 | I39: 2148.39 | J39: 2348.91 | K39: 1414.52 | L39: 3547.41 | M39: 1773.3 | N39: 2100.85 | O39: =SUM(C39:N39) -> 33378.14
B40: Payroll Processing Service | C40: 725.67 | D40: 965.72 | E40: 642.3 | F40: 952.02 | G40: 4269.02 | H40: 720.9 | I40: 826.09 | J40: 663.4 | K40: 2029.15 | L40: 884.16 | M40: 847.32 | N40: 723.95 | O40: =SUM(C40:N40) -> 14249.7
B41: Payroll & Related Costs | C41: 14050.73 | D41: 18752.71 | E41: 17760.34 | F41: 16047.79 | G41: 25351.12 | H41: 12999.97 | I41: 12029.11 | J41: 13320.11 | K41: 15239.08 | L41: 18095.16 | M41: 10114.19 | N41: 11835.65 | O41: =SUM(C41:N41) -> 185595.96
B43: Repairs & Maintenance
B44: Pool/Repairs | C44: 0 | D44: 0 | E44: 334.14 | F44: 549.29 | G44: 35.69 | H44: 0 | I44: 0 | J44: 0 | K44: 0 | L44: 0 | M44: 0 | N44: 0 | O44: =SUM(C44:N44) -> 919.12
B45: HVAC Supplies/Repairs | C45: 0 | D45: 0 | E45: 0 | F45: 378.31 | G45: 360.47 | H45: 0 | I45: 427.68 | J45: 0 | K45: 0 | L45: 0 | M45: 0 | N45: 0 | O45: =SUM(C45:N45) -> 1166.46
B46: Maintenance Supplies | C46: 4834.71 | D46: 3095.15 | E46: 19655.28 | F46: 26061.56 | G46: 15498.73 | H46: 7387.23 | I46: 4114.8 | J46: 7826.72 | K46: 4110.32 | L46: 4226.6 | M46: 5311.79 | N46: 3688.26 | O46: =SUM(C46:N46) -> 105811.15
B47: Repairs & Maintenance | C47: =C46 -> 4834.71 | D47: 3095.15 | E47: 19989.42 | F47: 26989.16 | G47: 15894.89 | H47: 7387.23 | I47: 4542.48 | J47: 7826.72 | K47: 4110.32 | L47: 4226.6 | M47: 5311.79 | N47: 3688.26 | O47: =SUM(C47:N47) -> 107896.73
B49: Turnover Expense
B50: Student Turnover - Interior Painting/Dry Wall | C50: 0 | D50: 0 | E50: 0 | F50: 0 | G50: 545.46 | H50: 0 | I50: 0 | J50: 0 | K50: 0 | L50: 0 | M50: 0 | N50: 0 | O50: =SUM(C50:N50) -> 545.46
B51: Turnover Expense | D51: 0 | E51: 0 | F51: 0 | G51: 545.46 | H51: 0 | I51: 0 | J51: 0 | K51: 0 | L51: 0 | M51: 0 | N51: 0 | O51: =SUM(C51:N51) -> 545.46
B53: Common Area Utilities
B54: Electric - House Meters | C54: 12525.08 | D54: 25206.74 | E54: 11967.38 | F54: 14741.16 | G54: 16075.96 | H54: 15359.48 | I54: 14840.23 | J54: 932.91 | K54: 13246.32 | L54: 17545.83 | M54: 20219.1 | N54: 17069.11 | O54: =SUM(C54:N54) -> 179729.3
B55: Water & Sewer - House Meters | C55: 7883.87 | D55: 0 | E55: 0 | F55: 0 | G55: 0 | H55: 0 | I55: 0 | J55: 0 | K55: 0 | L55: 0 | M55: 0 | N55: 0 | O55: =SUM(C55:N55) -> 7883.87
B56: Electric-Ancillary | C56: 1598.65 | D56: 1326.86 | E56: 0 | F56: 0 | G56: 0 | H56: 0 | I56: 0 | J56: 0 | K56: 0 | L56: 0 | M56: 0 | N56: 0 | O56: =SUM(C56:N56) -> 2925.51
B57: Trash Removal Contract | C57: 0 | D57: 0 | E57: 0 | F57: 43.83 | G57: 0 | H57: 0 | I57: 0 | J57: 0 | K57: 0 | L57: 0 | M57: 0 | N57: 0 | O57: =SUM(C57:N57) -> 43.83
B58: Common Area Utilities | C58: 22007.6 | D58: 26533.6 | E58: 11967.38 | F58: 14784.99 | G58: 16075.96 | H58: 15359.48 | I58: 14840.23 | J58: 932.91 | K58: 13246.32 | L58: 17545.83 | M58: 20219.1 | N58: 17069.11 | O58: =SUM(C58:N58) -> 190582.51
B60: Unit/Bedroom Utilities
B61: Utility Billing Fee | C61: 1117.74 | D61: 1128.6 | E61: 0 | F61: 0 | G61: 0 | H61: 0 | I61: 0 | J61: 0 | K61: 0 | L61: 0 | M61: 0 | N61: 0 | O61: =SUM(C61:N61) -> 2246.34
B62: Internet - Resident Units | C62: 175.53 | D62: 175.53 | E62: 362.37 | F62: 332.17 | G62: 340.53 | H62: 340.53 | I62: 175.53 | J62: 504.53 | K62: 340.53 | L62: 175.52 | M62: 175.53 | N62: 175.53 | O62: =SUM(C62:N62) -> 3273.83
B63: Unit/Bedroom Utilities | C63: 1293.27 | D63: 1304.13 | E63: 362.37 | F63: 332.17 | G63: 340.53 | H63: 340.53 | I63: 175.53 | J63: 504.53 | K63: 340.53 | L63: 175.52 | M63: 175.53 | N63: 175.53 | O63: =SUM(C63:N63) -> 5520.17
B65: Marketing & Leasing
B66: Promotional - Other | C66: 0 | D66: 0 | E66: 0 | F66: 0 | G66: 0 | H66: 0 | I66: 0 | J66: 100.27 | K66: 0 | L66: 0 | M66: 0 | N66: 0 | O66: =SUM(C66:N66) -> 100.27
B67: Appeal - Signage/Flags/Banners | C67: 0 | D67: 0 | E67: 0 | F67: 0 | G67: 0 | H67: 0 | I67: 0 | J67: 0 | K67: 0 | L67: 56.68 | M67: 0 | N67: 0 | O67: =SUM(C67:N67) -> 56.68
B68: Promotional - Giveaways & Swag | C68: 0 | D68: 0 | E68: 0 | F68: 0 | G68: 0 | H68: 0 | I68: 0 | J68: 0 | K68: 231.1 | L68: 0 | M68: 0 | N68: 0 | O68: =SUM(C68:N68) -> 231.1
B69: Appeal - Model Expense | C69: 0 | D69: 0 | E69: 0 | F69: 0 | G69: 0 | H69: 0 | I69: 0 | J69: 0 | K69: 0 | L69: 0 | M69: 126.54 | N69: 0 | O69: =SUM(C69:N69) -> 126.54
B70: Clubhouse appeal | C70: 0 | D70: 0 | E70: 64.4 | F70: 170.34 | G70: 59.31 | H70: 181.74 | I70: 0 | J70: 0 | K70: 60.6 | L70: 0 | M70: 0 | N70: 76.64 | O70: =SUM(C70:N70) -> 613.03
B71: Advertising - Internet Vendors | C71: 155.27 | D71: 307.79 | E71: 2986.51 | F71: 2960.5 | G71: 1491.97 | H71: 828.08 | I71: 0 | J71: 80.06 | K71: 217.47 | L71: 441.51 | M71: 381.58 | N71: 539.69 | O71: =SUM(C71:N71) -> 10390.43
B72: Referral - Resident Referral Fees | C72: 0 | D72: 0 | E72: 0 | F72: 0 | G72: 0 | H72: 250 | I72: 0 | J72: 0 | K72: 0 | L72: 0 | M72: 0 | N72: 0 | O72: =SUM(C72:N72) -> 250
B73: Marketing & Leasing | C73: 155.27 | D73: 307.79 | E73: 3050.91 | F73: 3130.84 | G73: 1551.28 | H73: 1259.82 | I73: 0 | J73: 180.33 | K73: 509.17 | L73: 498.19 | M73: 508.12 | N73: 616.33 | O73: =SUM(C73:N73) -> 11768.05
B75: Resident Life
B76: Clubhouse Coffee / Refreshments | C76: 10.98 | D76: 0 | E76: 15.96 | F76: 0 | G76: 153.87 | H76: 0 | I76: 0 | J76: 0 | K76: 0 | L76: 0 | M76: 0 | N76: 0 | O76: =SUM(C76:N76) -> 180.81
B77: Resident Life | C77: 10.98 | D77: 0 | E77: 15.96 | F77: 0 | G77: 153.87 | H77: 0 | I77: 0 | J77: 0 | K77: 0 | L77: 0 | M77: 0 | N77: 0 | O77: =SUM(C77:N77) -> 180.81
B79: General & Administrative
B80: Bad Debt Recovery | C80: 0 | D80: -5220.39 | E80: 0 | F80: 0 | G80: 0 | H80: 0 | I80: 0 | J80: 0 | K80: 0 | L80: 0 | M80: 0 | N80: 0 | O80: =SUM(C80:N80) -> -5220.39
B81: General Rent Concessions | C81: 0 | D81: 0 | E81: 0 | F81: 0 | G81: 531.11 | H81: 0 | I81: 0 | J81: 0 | K81: 0 | L81: 0 | M81: 0 | N81: 0 | O81: =SUM(C81:N81) -> 531.11
B82: Office - General Office Expense | C82: 0 | D82: 0 | E82: 0 | F82: 0 | G82: 0 | H82: 0 | I82: 0 | J82: 243.45 | K82: 0 | L82: 0 | M82: 0 | N82: 0 | O82: =SUM(C82:N82) -> 243.45
B83: Office - Equipment & Maintenance | C83: 0 | D83: 0 | E83: 0 | F83: 0 | G83: 0 | H83: 0 | I83: 0 | J83: 0 | K83: 0 | L83: 475.33 | M83: 0 | N83: 0 | O83: =SUM(C83:N83) -> 475.33
B84: Bad Debts | C84: 0 | D84: 551.07 | E84: 0 | F84: 0 | G84: 0 | H84: 0 | I84: 0 | J84: 0 | K84: 0 | L84: 0 | M84: 0 | N84: 0 | O84: =SUM(C84:N84) -> 551.07
B85: Office - Supplies | C85: 0 | D85: 470.25 | E85: 452.25 | F85: 1074.88 | G85: 1753.36 | H85: 1100.62 | I85: 882.27 | J85: 1073.9 | K85: 531.06 | L85: 806.91 | M85: 133.74 | N85: 1226.06 | O85: =SUM(C85:N85) -> 9505.3
B86: Office - Telephone | C86: 155.39 | D86: 155.39 | E86: 155.39 | F86: 155.34 | G86: 155.53 | H86: 155.53 | I86: 155.66 | J86: 155.66 | K86: 155.66 | L86: 155.63 | M86: 155.63 | N86: 155.63 | O86: =SUM(C86:N86) -> 1866.44
B87: General - Bank Charges | C87: 104.24 | D87: 67.48 | E87: 87.56 | F87: 52.16 | G87: 2754.02 | H87: 56.44 | I87: 51.44 | J87: 0 | K87: 41.4 | L87: 43.2 | M87: 80.4 | N87: 42 | O87: =SUM(C87:N87) -> 3380.34
B88: Office - Computer Software License Fees | C88: 0 | D88: 0 | E88: 0 | F88: 296.79 | G88: 1606.79 | H88: 1383.45 | I88: 505.11 | J88: 631.46 | K88: 1669.27 | L88: 191.23 | M88: 0 | N88: 0 | O88: =SUM(C88:N88) -> 6284.1
B89: General - Website Design & Maintenance | C89: 0 | D89: 0 | E89: 0 | F89: 0 | G89: 0 | H89: 0 | I89: 0 | J89: 0 | K89: 0 | L89: 22.19 | M89: 0 | N89: 0 | O89: =SUM(C89:N89) -> 22.19
B90: Employee - Recognition | C90: 0 | D90: 0 | E90: 0 | F90: 0 | G90: 0 | H90: 0 | I90: 0 | J90: 0 | K90: 132.34 | L90: 0 | M90: 0 | N90: 0 | O90: =SUM(C90:N90) -> 132.34
B91: General - Miscellaneous Expense | C91: 0 | D91: 0 | E91: 69.43 | F91: 205.45 | G91: 135.37 | H91: 362.32 | I91: 61.34 | J91: 180.35 | K91: 0 | L91: 0 | M91: 44.61 | N91: 28.53 | O91: =SUM(C91:N91) -> 1087.4
B92: General & Administrative | C92: 259.63 | D92: -3976.2 | E92: 764.63 | F92: 1784.62 | G92: 6936.18 | H92: 3058.36 | I92: 1655.82 | J92: 2284.82 | K92: 2529.73 | L92: 1694.49 | M92: 414.38 | N92: 1452.22 | O92: =SUM(C92:N92) -> 18858.68
B94: Ownership Expenses
B95: Owner Payout | C95: 11000 | D95: 22172.46 | E95: 12500 | F95: 11000 | G95: 9000 | H95: 10500 | I95: 9000 | J95: 8500 | K95: 11500 | L95: 8000 | M95: 8500 | N95: 10500 | O95: =SUM(C95:N95) -> 132172.46
B96: Ownership Expenses | C96: 0 | D96: 0 | E96: 0 | F96: 0 | G96: 0 | H96: 0 | I96: 0 | J96: 0 | K96: 0 | L96: 1000 | M96: 0 | N96: 0 | O96: =SUM(C96:N96) -> 1000
B97: Ownership Expenses | C97: 11000 | D97: 22172.46 | E97: 12500 | F97: 11000 | G97: 9000 | H97: 10500 | I97: 9000 | J97: 8500 | K97: 11500 | L97: 9000 | M97: 8500 | N97: 10500 | O97: =SUM(C97:N97) -> 133172.46
B99: Professional Fees
B100: Legal Fees | C100: 0 | D100: 0 | E100: 0 | F100: 0 | G100: 0 | H100: 0 | I100: 0 | J100: 0 | K100: 161.7 | L100: 0 | M100: 0 | N100: 0 | O100: =SUM(C100:N100) -> 161.7
B101: Professional Fees | C101: 0 | D101: 0 | E101: 0 | F101: 0 | G101: 0 | H101: 0 | I101: 0 | J101: 0 | K101: 161.7 | L101: 0 | M101: 0 | N101: 0 | O101: =SUM(C101:N101) -> 161.7
B103: Taxes & Insurance
B104: Property Insurance Expense | C104: 5586.23 | D104: 0 | E104: 7086.23 | F104: 0 | G104: 0 | H104: 0 | I104: 0 | J104: 5586.23 | K104: 5586.23 | L104: 17504.79 | M104: 0 | N104: 12660 | O104: =SUM(C104:N104) -> 54009.71
B105: Taxes & Insurance | C105: 5586.23 | D105: 0 | E105: 7086.23 | F105: 0 | G105: 0 | H105: 0 | I105: 0 | J105: 5586.23 | K105: 5586.23 | L105: 17504.79 | M105: 0 | N105: 12660 | O105: =SUM(C105:N105) -> 54009.71
B107: Capital Expenses
B108: Cap-Ex Flooring | C108: 0 | D108: 0 | E108: 0 | F108: 0 | G108: 90.93 | H108: 0 | I108: 0 | J108: 0 | K108: 0 | L108: 0 | M108: 0 | N108: 0 | O108: =SUM(C108:N108) -> 90.93
B109: CapEx-Computer Equipment & Software | C109: 942.62 | D109: 1415.73 | E109: 1662.07 | F109: 1217.43 | G109: 176.43 | H109: 151.21 | I109: 142.08 | J109: 183.73 | K109: 239.4 | L109: 2888.9 | M109: 1341.52 | N109: 1343.76 | O109: =SUM(C109:N109) -> 11704.88
B110: CapEx-HVAC | C110: 0 | D110: 0 | E110: 0 | F110: 0 | G110: 0 | H110: 0 | I110: 0 | J110: 71.24 | K110: 0 | L110: 0 | M110: 0 | N110: 0 | O110: =SUM(C110:N110) -> 71.24
B111: CapEx-Miscellaneous Expense | C111: 0 | D111: 0 | E111: 65.47 | F111: 168.21 | G111: 0 | H111: 0 | I111: 0 | J111: 0 | K111: 0 | L111: 0 | M111: 0 | N111: 0 | O111: =SUM(C111:N111) -> 233.68
B112: Capital Expenses | C112: 942.62 | D112: 1415.73 | E112: 1727.54 | F112: 1385.64 | G112: 267.36 | H112: 151.21 | I112: 142.08 | J112: 254.97 | K112: 239.4 | L112: 2888.9 | M112: 1341.52 | N112: 1343.76 | O112: =SUM(C112:N112) -> 12100.73
B114: Operating Expenses | C114: 102126.13 | D114: 111590.46 | E114: 75224.78 | F114: 117370.21 | G114: 118031.83 | H114: 92971.6 | I114: 83400.25 | J114: 81305.71 | K114: 95377.57 | L114: 113544.57 | M114: 88499.72 | N114: 101255.95 | O114: =SUM(C114:N114) -> 1180698.8
B116: Net Operating Income | C116: 44514.06 | D116: 50139.87 | E116: 51799.91 | F116: -840.27 | G116: 3389.19 | H116: 33055.92 | I116: 38215.05 | J116: 44556.78 | K116: 30098.65 | L116: 1557.27 | M116: 32325.37 | N116: 24765.2 | O116: =SUM(C116:N116) -> 353577
B118: Net Income | C118: 44514.06 | D118: 50139.87 | E118: 51799.91 | F118: -840.27 | G118: 3389.19 | H118: 33055.92 | I118: 38215.05 | J118: 44556.78 | K118: 30098.65 | L118: 1557.27 | M118: 32325.37 | N118: 24765.2 | O118: =SUM(C118:N118) -> 353577
B120: Positive Adjustments (+)
B121: =+B94 -> Ownership Expenses
B122: =+B95 -> Owner Payout | C122: =+C95 -> 11000 | D122: =+D95 -> 22172.46 | E122: =+E95 -> 12500 | F122: =+F95 -> 11000 | G122: =+G95 -> 9000 | H122: =+H95 -> 10500 | I122: =+I95 -> 9000 | ... O122: =+O95 -> 132172.46
...

Sheet WTAMSH RR
A1: Bldg-Unit | B1: Unit Type | C1: SQFT | D1: Unit Status | E1: Resident | F1: Move-In | G1: Lease Start | H1: Lease End | I1: Expected Move-Out | J1: Market Rent | K1: Actual Charges | L1: Scheduled Charges | M1: Balance | N1: Deposit Held
A2: 1-112-A | B2: D1 | C2: 75.75 | D2: Occupied No Notice | E2: Model 1, Canyon | F2: 40798 | G2: 45139 | J2: 525 | K2: 13 | L2: 0 | M2: 20.13 | N2: 0
A3: 1-112-B | B3: D1 | C3: 75.75 | D3: Occupied No Notice | E3: Model 2, Canyon | F3: 40798 | G3: 45139 | J3: 525 | K3: 13 | L3: 0 | M3: 20.13 | N3: 0
A4: 1-112-C | B4: D1 | C4: 75.75 | D4: Occupied No Notice | E4: Model 3, Canyon | F4: 40798 | G4: 45139 | J4: 525 | K4: 13 | L4: 0 | M4: 20.13 | N4: 0
A5: 1-112-D | B5: D1 | C5: 75.75 | D5: Occupied No Notice | E5: Model 4, Canyon | F5: 40798 | G5: 45139 | J5: 525 | K5: 13 | L5: 0 | M5: 20.13 | N5: 0
A6: 1-113-A | B6: B1 | C6: 180 | D6: Notice Unrented | E6: Robles, Kimberlee | F6: 45499 | G6: 45860 | H6: 46227 | I6: 46227 | J6: 650 | K6: 821.13 | L6: 650 | M6: 0 | N6: 250
A7: 1-113-B | B7: B1 | C7: 180 | D7: Notice Unrented | E7: Robles, Mariah | F7: 45499 | G7: 45860 | H7: 46227 | I7: 46227 | J7: 1300 | K7: 781.19 | L7: 675 | M7: -0.84 | N7: 250
A8: 1-114-A | B8: D1 | C8: 281.25 | D8: Notice Rented | E8: Smith, Sydni | F8: 45863 | G8: 45863 | H8: 46227 | I8: 46227 | J8: 525 | K8: 591.36 | L8: 525 | M8: 13 | N8: 250
A9: 1-114-B | B9: D1 | C9: 281.25 | D9: Vacant Unrented Ready | E9: -- Vacant -- | J9: 1950 | K9: 0 | L9: 0 | N9: 0
A10: 1-114-C | B10: D1 | C10: 281.25 | D10: Notice Unrented | E10: Castro, Jalynn | F10: 45860 | G10: 45860 | H10: 46227 | I10: 46227 | J10: 1050 | K10: 566.36 | L10: 500 | M10: 20.13 | N10: 250
A11: 1-114-D | B11: D1 | C11: 281.25 | D11: Vacant Rented Ready | E11: -- Vacant -- | J11: 1900 | K11: 0 | L11: 0
A12: 1-115-A | B12: B1 | C12: 180 | D12: Notice Unrented | E12: Bonilla, Amy | F12: 45870 | G12: 45870 | H12: 46227 | I12: 46204 | J12: 650 | K12: 702.66 | L12: 650 | M12: 0 | N12: 250
A13: 1-115-B | B13: B1 | C13: 180 | D13: Occupied No Notice | E13: Warren, Kayla | F13: 45873 | G13: 45873 | H13: 46227 | J13: 650 | K13: 702.66 | L13: 650 | M13: 0 | N13: 250
A14: 1-116-A | B14: D1 | C14: 75.75 | D14: Vacant Rented Ready | E14: -- Vacant -- | J14: 1950 | K14: 0 | L14: 0
A15: 1-116-B | B15: D1 | C15: 75.75 | D15: Vacant Rented Ready | E15: -- Vacant -- | J15: 600 | K15: 0 | L15: 0
A16: 1-116-C | B16: D1 | C16: 75.75 | D16: Occupied No Notice | E16: Reynolds, Hunter | F16: 46174 | G16: 46174 | H16: 46599 | J16: 1200 | K16: 600 | L16: 525 | M16: 0 | N16: 0
A17: 1-116-D | B17: D1 | C17: 75.75 | D17: Vacant Rented Ready | E17: -- Vacant -- | J17: 600 | K17: 0 | L17: 0
A18: 1-117-A | B18: B1 | C18: 180 | D18: Occupied No Notice | E18: Kell, Jordon | F18: 45901 | G18: 45901 | H18: 46227 | J18: 650 | K18: 674.48 | L18: 650 | M18: 0 | N18: 250
A19: 1-117-B | B19: B1 | C19: 180 | D19: Occupied No Notice | E19: Rasmussen, Joshua | F19: 46037 | G19: 46037 | H19: 46227 | J19: 1450 | K19: 664.48 | L19: 640 | M19: 0 | N19: 250
A20: 1-118-A | B20: B1 | C20: 180 | D20: Occupied No Notice | E20: Contreraz, Jacob Jr | F20: 44774 | G20: 45860 | H20: 46227 | J20: 650 | K20: 721.33 | L20: 650 | M20: 0 | N20: 250
A21: 1-118-B | B21: B1 | C21: 180 | D21: Notice Unrented | E21: Dioquino, Jaron | F21: 45505 | G21: 45860 | H21: 46227 | I21: 46227 | J21: 650 | K21: 708.33 | L21: 650 | M21: 0 | N21: 250
A22: 1-121.5-A | B22: F1 | C22: 300 | D22: Vacant Unrented Ready | E22: -- Vacant -- | J22: 674 | K22: 0 | L22: 0 | N22: 0
A23: 1-121.5-B | B23: F1 | C23: 300 | D23: Occupied No Notice | E23: Whitman, James | F23: 45520 | G23: 45860 | H23: 46227 | J23: 599 | K23: 698.93 | L23: 599 | M23: -3581.96 | N23: 250
A24: 1-121-A | B24: OG | C24: 151.5 | D24: Occupied No Notice | E24: Murray, Adam | F24: 46174 | G24: 46174 | H24: 46592 | J24: 624 | K24: 592.5 | L24: 555 | M24: 0 | N24: 0
A25: 1-121-B | B25: OG | C25: 151.5 | D25: Occupied No Notice | E25: Murray, Adam | F25: 46174 | G25: 46174 | H25: 46592 | J25: 1248 | K25: 592.5 | L25: 555 | M25: 0 | N25: 0
A26: 1-122.5-A | B26: F1 | C26: 300 | D26: Occupied No Notice | E26: Long, Ryker | F26: 45505 | G26: 45860 | H26: 46227 | J26: 599 | K26: 640.74 | L26: 599 | M26: 0 | N26: 125
A27: 1-122.5-B | B27: F1 | C27: 300 | D27: Occupied No Notice | E27: Long, Ryker | F27: 45505 | G27: 45860 | H27: 46227 | J27: 599 | K27: 640.74 | L27: 599 | M27: 0 | N27: 125
A28: 1-122-A | B28: OG | C28: 262.5 | D28: Notice Unrented | E28: Cantu, Patricia | F28: 45520 | G28: 45860 | H28: 46227 | I28: 46227 | J28: 555 | K28: 645.59 | L28: 549 | M28: 371.35 | N28: 250
A29: 1-122-B | B29: OG | C29: 262.5 | D29: Vacant Unrented Not Ready | E29: -- Vacant -- | J29: 1248 | K29: 0 | L29: 0 | N29: 0
A30: 1-123-A | B30: B1 | C30: 180 | D30: Occupied No Notice | E30: Podmolik, Peyton | F30: 45890 | G30: 45890 | H30: 46227 | J30: 650 | K30: 719.73 | L30: 650 | M30: -23.12 | N30: 250
A31: 1-123-B | B31: B1 | C31: 180 | D31: Occupied No Notice | E31: Hodgson, Violet | F31: 45890 | G31: 45890 | H31: 46227 | J31: 650 | K31: 719.73 | L31: 650 | M31: 0 | N31: 250
A32: 1-124-A | B32: B1 | C32: 180 | D32: Occupied No Notice | E32: Hunt, Brennen | F32: 45474 | G32: 45860 | H32: 46227 | J32: 650 | K32: 695.49 | L32: 650 | M32: 0 | N32: 250
A33: 1-124-B | B33: B1 | C33: 180 | D33: Occupied No Notice | E33: Host, Kayden | F33: 45633 | G33: 45860 | H33: 46227 | J33: 650 | K33: 720.49 | L33: 675 | M33: 0 | N33: 250
A34: 1-125-A | B34: B1 | C34: 180 | D34: Occupied No Notice | E34: Baez, Angelika | F34: 45870 | G34: 45870 | H34: 46227 | J34: 650 | K34: 700.67 | L34: 650 | M34: 0 | N34: 250
A35: 1-125-B | B35: B1 | C35: 180 | D35: Occupied No Notice | E35: Mills, Jordyn | F35: 45870 | G35: 45890 | H35: 46227 | J35: 650 | K35: 700.67 | L35: 650 | M35: 0 | N35: 250
A36: 1-126-A | B36: B1 | C36: 180 | D36: Occupied No Notice | E36: Ruvalcaba, Marcela | F36: 46121 | G36: 46121 | H36: 46234 | J36: 650 | K36: 672.43 | L36: 650 | M36: 0 | N36: 250
A37: 1-126-B | B37: B1 | C37: 180 | D37: Occupied No Notice | E37: Silva-Gomez, Yasmeen | F37: 46146 | G37: 46146 | H37: 46234 | J37: 1450 | K37: 693 | L37: 693 | M37: 0 | N37: 0
A38: 1-127-A | B38: D1 | C38: 75.75 | D38: Vacant Unrented Ready | E38: -- Vacant -- | J38: 1200 | K38: 0 | L38: 0 | N38: 0
A39: 1-127-B | B39: D1 | C39: 75.75 | D39: Occupied No Notice | E39: Joseph, Jamaal | F39: 45505 | G39: 45860 | H39: 46227 | J39: 525 | K39: 608.09 | L39: 525 | M39: 0 | N39: 250
A40: 1-127-C | B40: D1 | C40: 75.75 | D40: Vacant Unrented Not Ready | E40: -- Vacant -- | J40: 600 | K40: 0 | L40: 0 | N40: 0
A41: 1-127-D | B41: D1 | C41: 75.75 | D41: Occupied No Notice | E41: Packebush, Campbell | F41: 45513 | G41: 45860 | H41: 46227 | J41: 525 | K41: 608.09 | L41: 525 | M41: 0 | N41: 250
A42: 1-128-A | B42: D1 | C42: 75.75 | D42: Occupied No Notice | E42: Havekost, Catelyn | F42: 46037 | G42: 46176 | H42: 46599 | J42: 600 | K42: 575.02 | L42: 525 | M42: 0 | N42: 250
A43: 1-128-B | B43: D1 | C43: 75.75 | D43: Occupied No Notice | E43: Ruter, Anna | F43: 46037 | G43: 46174 | H43: 46387 | J43: 600 | K43: 587.02 | L43: 550 | M43: 0 | N43: 250
A44: 1-128-C | B44: D1 | C44: 75.75 | D44: Vacant Rented Ready | E44: -- Vacant -- | J44: 1950 | K44: 0 | L44: 0
A45: 1-128-D | B45: D1 | C45: 75.75 | D45: Vacant Unrented Ready | E45: -- Vacant -- | J45: 600 | K45: 0 | L45: 0 | N45: 0
A46: 1-131-A | B46: D1 | C46: 131.25 | D46: Occupied No Notice | E46: Acheampong, Deborah | F46: 45870 | G46: 45870 | H46: 46227 | J46: 525 | K46: 488.86 | L46: 450 | M46: 0 | N46: 250
A47: 1-131-B | B47: D1 | C47: 131.25 | D47: Vacant Unrented Ready | E47: -- Vacant -- | J47: 600 | K47: 0 | L47: 0 | N47: 0
A48: 1-131-C | B48: D1 | C48: 131.25 | D48: Notice Unrented | E48: Tijerina, Torrance | F48: 45506 | G48: 45860 | H48: 46227 | I48: 46227 | J48: 1050 | K48: 538.86 | L48: 500 | M48: 0 | N48: 250
A49: 1-131-D | B49: D1 | C49: 131.25 | D49: Vacant Unrented Ready | E49: -- Vacant -- | J49: 600 | K49: 0 | L49: 0 | N49: 0
A50: 1-132.5-A | B50: F1 | C50: 300 | D50: Notice Unrented | E50: Wilson, Emily | F50: 45778 | G50: 45778 | H50: 46227 | I50: 46227 | J50: 600 | K50: 638.27 | L50: 599 | M50: 0 | N50: 250
A51: 1-132.5-B | B51: F1 | C51: 300 | D51: Notice Unrented | E51: Ramsey, Kenneth | F51: 45778 | G51: 45778 | H51: 46227 | I51: 46227 | J51: 1200 | K51: 711.11 | L51: 599 | M51: 0 | N51: 250
A52: 1-132-A | B52: OG | C52: 262.5 | D52: Occupied No Notice | E52: Rodriguez, Fredi | F52: 46183 | G52: 46184 | H52: 46387 | J52: 549 | K52: 461.35 | L52: 599 | M52: 0 | N52: 125
A53: 1-132-B | B53: OG | C53: 262.5 | D53: Occupied No Notice | E53: Rodriguez, Fredi | F53: 46183 | G53: 46184 | H53: 46387 | J53: 624 | K53: 461.35 | L53: 599 | M53: 0 | N53: 125
A54: 1-133-A | B54: B1 | C54: 180 | D54: Occupied No Notice | E54: Alshyef, Amin | F54: 46059 | G54: 46059 | H54: 46234 | J54: 725 | K54: 756.38 | L54: 650 | M54: 0 | N54: 250
A55: 1-133-B | B55: B1 | C55: 180 | D55: Occupied No Notice | E55: Alshaif, Bashir | F55: 46059 | G55: 46059 | H55: 46234 | J55: 1450 | K55: 743.38 | L55: 650 | M55: 0 | N55: 250
A56: 1-134-A | B56: B1 | C56: 180 | D56: Occupied No Notice | E56: Trammell, Dara | F56: 46175 | G56: 46175 | H56: 46599 | J56: 725 | K56: 625.1 | L56: 650 | M56: 100 | N56: 250
A57: 1-134-B | B57: B1 | C57: 180 | D57: Occupied No Notice | E57: Mescher, Lindsey | F57: 46185 | G57: 46185 | H57: 46538 | J57: 1450 | K57: 542.4 | L57: 725 | M57: 0 | N57: 250
A58: 1-135-A | B58: B1 | C58: 180 | D58: Occupied No Notice | E58: Myers, Quintine | F58: 46159 | G58: 46159 | H58: 46301 | J58: 725 | K58: 855.43 | L58: 770 | M58: 0 | N58: 250
A59: 1-135-B | B59: B1 | C59: 180 | D59: Occupied No Notice | E59: Rodriguez Sanchez, Hilda | F59: 46157 | G59: 46157 | H59: 46592 | J59: 1450 | K59: 650 | L59: 650 | M59: 0 | N59: 250
A60: 1-136-A | B60: B1 | C60: 180 | D60: Notice Unrented | E60: Estes, Emily | F60: 45890 | G60: 45890 | H60: 46227 | I60: 46227 | J60: 650 | K60: 700.9 | L60: 650 | M60: 0 | N60: 250
A61: 1-136-B | B61: B1 | C61: 180 | D61: Vacant Unrented Not Ready | E61: -- Vacant -- | J61: 650 | K61: 0 | L61: 0 | N61: 0
A62: 1-137-A | B62: D1 | C62: 75.75 | D62: Vacant Unrented Ready | E62: -- Vacant -- | J62: 600 | K62: 0 | L62: 0 | N62: 0
A63: 1-137-B | B63: D1 | C63: 75.75 | D63: Occupied No Notice | E63: Alba, Elena | F63: 45871 | G63: 45890 | H63: 46227 | J63: 525 | K63: 539.7 | L63: 500 | M63: 0 | N63: 250
A64: 1-137-C | B64: D1 | C64: 75.75 | D64: Occupied No Notice | E64: Salas, Janessa | F64: 45890 | G64: 45890 | H64: 46227 | J64: 525 | K64: 489.7 | L64: 450 | M64: 0 | N64: 250
A65: 1-137-D | B65: D1 | C65: 75.75 | D65: Occupied No Notice | E65: Escalante, Samantha | F65: 45870 | G65: 45870 | H65: 46227 | J65: 525 | K65: 589.65 | L65: 500 | M65: 0 | N65: 250
A66: 1-138-A | B66: D1 | C66: 75.75 | D66: Vacant Unrented Ready | E66: -- Vacant -- | J66: 600 | K66: 0 | L66: 0 | N66: 0
A67: 1-138-B | B67: D1 | C67: 75.75 | D67: Occupied No Notice | E67: High, Ava-Marie | F67: 45566 | G67: 45860 | H67: 46227 | J67: 525 | K67: 541.29 | L67: 500 | M67: 0 | N67: 250
A68: 1-138-C | B68: D1 | C68: 75.75 | D68: Occupied No Notice | E68: Monsalve, Elisa | F68: 46174 | G68: 46174 | H68: 46592 | J68: 1950 | K68: 362.13 | L68: 525 | M68: 12.13 | N68: 250
A69: 1-138-D | B69: D1 | C69: 75.75 | D69: Occupied No Notice | E69: Puentes, Ivonne | F69: 46174 | G69: 46174 | H69: 46592 | J69: 1200 | K69: 113 | L69: 525 | M69: 0 | N69: 250
A70: 2-211-A | B70: D1 | C70: 75.75 | D70: Occupied No Notice | E70: Bradshaw, Carson | F70: 45809 | G70: 45860 | H70: 46227 | J70: 525 | K70: 573.79 | L70: 525 | M70: 0 | N70: 250
A71: 2-211-B | B71: D1 | C71: 75.75 | D71: Notice Unrented | E71: Cumby, Kaden | F71: 45141 | G71: 45860 | H71: 46227 | I71: 46227 | J71: 1900 | K71: 548.79 | L71: 500 | M71: -575 | N71: 250
A72: 2-211-C | B72: D1 | C72: 75.75 | D72: Notice Unrented | E72: Osborne, Bryson | F72: 45883 | G72: 45890 | H72: 46227 | I72: 46227 | J72: 1900 | K72: 498.79 | L72: 450 | M72: 0 | N72: 250
A73: 2-211-D | B73: D1 | C73: 75.75 | D73: Vacant Unrented Ready | E73: -- Vacant -- | J73: 600 | K73: 0 | L73: 0 | N73: 0
A74: 2-212-A | B74: D1 | C74: 75.75 | D74: Occupied No Notice | E74: Salinas, Mavree | F74: 45864 | G74: 45864 | H74: 46227 | J74: 525 | K74: 506.01 | L74: 475 | M74: 0 | N74: 250
A75: 2-212-B | B75: D1 | C75: 75.75 | D75: Occupied No Notice | E75: Gilmore, Nicholas | F75: 45870 | G75: 45870 | H75: 46227 | J75: 525 | K75: 553.46 | L75: 475 | M75: 554.63 | N75: 250
A76: 2-212-C | B76: D1 | C76: 75.75 | D76: Occupied No Notice | E76: Carroll, Eleri | F76: 45863 | G76: 45863 | H76: 46227 | J76: 525 | K76: 519.01 | L76: 475 | M76: 0 | N76: 250
A77: 2-212-D | B77: D1 | C77: 75.75 | D77: Occupied No Notice | E77: Mckeel, Jazmyn | F77: 46143 | G77: 46143 | H77: 46592 | J77: 525 | K77: 525 | L77: 525 | M77: -300 | N77: 0
A78: 2-213-A | B78: B1 | C78: 180 | D78: Notice Unrented | E78: Cooper, Hayden | F78: 45878 | G78: 45890 | H78: 46227 | I78: 46227 | J78: 650 | K78: 746.16 | L78: 675 | M78: 0 | N78: 250
A79: 2-213-B | B79: B1 | C79: 180 | D79: Notice Unrented | E79: Shepard, Austin | F79: 45878 | G79: 45890 | H79: 46227 | I79: 46227 | J79: 650 | K79: 721.16 | L79: 650 | M79: 0 | N79: 250
A80: 2-214-A | B80: B1 | C80: 180 | D80: Occupied No Notice | E80: Jenkins, Andrew | F80: 46010 | G80: 46003 | H80: 46227 | J80: 650 | K80: 460.19 | L80: 650 | M80: -250 | N80: 250
A81: 2-214-B | B81: B1 | C81: 180 | D81: Occupied No Notice | E81: Pyle, Owen | F81: 46003 | G81: 46003 | H81: 46227 | J81: 650 | K81: 723.19 | L81: 650 | M81: 0 | N81: 250
A82: 2-215-A | B82: B1 | C82: 180 | D82: Notice Unrented | E82: Sawyer, Chloe | F82: 45878 | G82: 45878 | H82: 46227 | I82: 46227 | J82: 650 | K82: 747.21 | L82: 650 | M82: 504.21 | N82: 250
A83: 2-215-B | B83: B1 | C83: 180 | D83: Vacant Unrented Not Ready | E83: -- Vacant -- | J83: 650 | K83: 0 | L83: 0 | N83: 0
A84: 2-216-A | B84: B1 | C84: 180 | D84: Notice Rented | E84: Camargo, Krisa | F84: 45812 | G84: 45813 | H84: 46227 | I84: 46227 | J84: 650 | K84: 694.41 | L84: 650 | M84: 0 | N84: 125
A85: 2-216-B | B85: B1 | C85: 180 | D85: Notice Unrented | E85: Camargo, Krisa | F85: 45812 | G85: 45813 | H85: 46227 | I85: 46227 | J85: 650 | K85: 694.41 | L85: 650 | M85: 0 | N85: 125
A86: 2-217-A | B86: D1 | C86: 75.75 | D86: Vacant Unrented Ready | E86: -- Vacant -- | J86: 600 | K86: 0 | L86: 0 | N86: 0
A87: 2-217-B | B87: D1 | C87: 75.75 | D87: Occupied No Notice | E87: Keenan, Cole | F87: 43335 | G87: 45860 | H87: 46227 | J87: 525 | K87: 573.34 | L87: 500 | M87: -577.28 | N87: 250
A88: 2-217-C | B88: D1 | C88: 75.75 | D88: Vacant Unrented Ready | E88: -- Vacant -- | J88: 1200 | K88: 0 | L88: 0 | N88: 0
A89: 2-217-D | B89: D1 | C89: 75.75 | D89: Vacant Unrented Ready | E89: -- Vacant -- | J89: 600 | K89: 0 | L89: 0 | N89: 0
A90: 2-218-A | B90: D1 | C90: 75.75 | D90: Notice Unrented | E90: Green, Brandy | F90: 45413 | G90: 45860 | H90: 46227 | I90: 46227 | J90: 525 | K90: 537.73 | L90: 500 | M90: -550 | N90: 250
A91: 2-218-B | B91: D1 | C91: 75.75 | D91: Notice Unrented | E91: Soto, Nayeli | F91: 45413 | G91: 45860 | H91: 46227 | I91: 46227 | J91: 525 | K91: 537.73 | L91: 500 | M91: 0 | N91: 250
A92: 2-218-C | B92: D1 | C92: 75.75 | D92: Notice Unrented | E92: Garcia, Brenda | F92: 45505 | G92: 45860 | H92: 46227 | I92: 46227 | J92: 1900 | K92: 550.73 | L92: 500 | M92: 0 | N92: 250
A93: 2-218-D | B93: D1 | C93: 75.75 | D93: Occupied No Notice | E93: Tordt, Tesla | F93: 46157 | G93: 46157 | H93: 46592 | J93: 1950 | K93: 538 | L93: 525 | M93: 0 | N93: 250
A94: 2-221-A | B94: D1 | C94: 75.75 | D94: Occupied No Notice | E94: Stringer, Berkley | F94: 46174 | G94: 46174 | H94: 46599 | J94: 1200 | K94: 600 | L94: 525 | M94: 0 | N94: 0
A95: 2-221-B | B95: D1 | C95: 75.75 | D95: Vacant Rented Ready | E95: -- Vacant -- | J95: 1950 | K95: 0 | L95: 0 | N95: 0
A96: 2-221-C | B96: D1 | C96: 75.75 | D96: Occupied No Notice | E96: Hernandez, Tristan | F96: 46174 | G96: 46174 | H96: 46538 | J96: 1200 | K96: 688 | L96: 600 | M96: 13 | N96: 0
A97: 2-221-D | B97: D1 | C97: 75.75 | D97: Occupied No Notice | E97: Talley, Gideon | F97: 45538 | G97: 45860 | H97: 46227 | J97: 525 | K97: 604.88 | L97: 525 | M97: 0 | N97: 250
A98: 2-222-A | B98: D1 | C98: 75.75 | D98: Occupied No Notice | E98: Tajjiou-noble, Abdl-ille | F98: 46143 | G98: 46143 | H98: 46599 | J98: 1200 | K98: 560 | L98: 560 | M98: 0 | N98: 250
A99: 2-222-B | B99: D1 | C99: 75.75 | D99: Occupied No Notice | E99: Smith, Seth | F99: 46153 | G99: 46153 | H99: 46592 | J99: 600 | K99: 525 | L99: 525 | M99: 0 | N99: 250
A100: 2-222-C | B100: D1 | C100: 75.75 | D100: Occupied No Notice | E100: Julian, Dominic | F100: 45296 | G100: 45860 | H100: 46227 | J100: 525 | K100: 613.96 | L100: 525 | M100: -600 | N100: 250
...

Sheet Amarillo UW
A1: Amarillo Multifamily
A2: 112 units | Built 1975 | T-12: Apr 2025–Mar 2026 | Independent / Conservative Case
A4: KEY ASSUMPTIONS | D4: FINANCING & EXIT
A5: # Units | B5: 112 | D5: Loan-to-Price (LTV) | E5: 0.7
A6: Year Built | B6: 1975 | D6: Loan Amount | E6: =B8*E5 -> 3920000
A7: Total SF | B7: ='Amarillo RR'!E121 -> 83440 | D7: Interest Rate | E7: 0.07
A8: Purchase Price | B8: 5600000 | D8: Amortization (yrs) | E8: 30
A9: Price / Unit | B9: =B8/B5 -> 50000 | D9: Closing Costs (% price) | E9: 0.02
A10: Hold Period (yrs) | B10: 4 | D10: Going-in Cap (normalized) | E10: =B38/B8 -> 0.074137833
D11: Exit Cap Rate | E11: 0.0825
A12: Rent Growth (annual) | B12: 0.03 | D12: Selling Costs (% sale) | E12: 0.02
A13: Other Income Growth | B13: 0.03 | D13: Total Equity Required | E13: =B8+B19+B8*E9-E6 -> 3461000
A14: Expense Inflation | B14: 0.03
A15: Stabilized Econ. Vacancy | B15: 0.07
A16: Mgmt Fee (% EGI) | B16: 0.035
A17: Replacement Reserves ($/unit) | B17: 250
A18: Reno Premium ($/unit/mo) | B18: 100
A19: Renovation Budget ($) | B19: 1669000
A21: IN-PLACE OPERATING STATEMENT (T-12, Normalized) | B21: T-12 Actual
A22: Rental Income (net of concessions/vouchers) | B22: ='Amarillo T12'!N19 -> 982442.15
A23: Other Income (fees, utility, deposit/maint, misc) | B23: ='Amarillo T12'!N51-'Amarillo T12'!N19 -> 101005.74
A24: Effective Gross Income | B24: =B22+B23 -> 1083447.9
A25: Repairs & Maintenance | B25: ='Amarillo T12'!N71 -> 161237.61
A26: Contracted Services | B26: ='Amarillo T12'!N76 -> 35887.65
A27: Cleaning & Janitorial | B27: ='Amarillo T12'!N80 -> 30112.6
A28: Utilities | B28: ='Amarillo T12'!N86 -> 107499.58
A29: Property Taxes | B29: ='Amarillo T12'!N89 -> 61639.03
A30: Insurance | B30: ='Amarillo T12'!N92 -> 91105.88
A31: Onsite Salaries & Wages | B31: ='Amarillo T12'!N97 -> 99022.64
A32: General & Administrative (incl. existing mgmt fee) | B32: ='Amarillo T12'!N59 -> 39165.1
A33: Misc. Operating | B33: ='Amarillo T12'!N103 -> 6204.02
A34: Total Operating Expenses (reported) | B34: =SUM(B25:B33) -> 631874.11
A35: NOI (as reported) | B35: =B24-B34 -> 451573.78
A36: (–) Normalize mgmt fee up to 3.5% of EGI | B36: =-MAX(0,B16*B24-'Amarillo T12'!N57) -> -8401.9162
A37: (–) Add replacement reserves ($/unit) | B37: =-B5*B17 -> -28000
A38: Normalized In-Place NOI | B38: =B35+B36+B37 -> 415171.86
A39: Normalized Going-in Cap Rate | B39: =B38/B8 -> 0.074137833
A42: PRO FORMA CASH FLOW
B43: In-Place | C43: Year 1 | D43: Year 2 | E43: Year 3 | F43: Year 4
A44: Rental & Other Income (grown) | B44: =B24 -> 1083447.9 | C44: =B44*(1+$B$12) -> 1115951.3 | D44: =C44*(1+$B$12) -> 1149429.9 | E44: =D44*(1+$B$12) -> 1183912.8 | F44: =E44*(1+$B$12) -> 1219430.1
A45: Renovation premium % achieved | B45: 0 | C45: 0.4 | D45: 0.8 | E45: 1 | F45: 1
A46: (+) Renovation Premium ($) | B46: =$B$5*$B$18*12*B45 -> 0 | C46: =$B$5*$B$18*12*C45 -> 53760 | D46: =$B$5*$B$18*12*D45 -> 107520 | E46: =$B$5*$B$18*12*E45 -> 134400 | F46: =$B$5*$B$18*12*F45 -> 134400
A47: Effective Gross Income | B47: =B44+B46 -> 1083447.9 | C47: =C44+C46 -> 1169711.3 | D47: =D44+D46 -> 1256949.9 | E47: =E44+E46 -> 1318312.8 | F47: =F44+F46 -> 1353830.1
A49: Operating Expenses:
A50: Opex excl. mgmt fee & reserves (inflated) | B50: =B34-'Amarillo T12'!N57 -> 602355.35 | C50: =B50*(1+$B$14) -> 620426.01 | D50: =C50*(1+$B$14) -> 639038.79 | E50: =D50*(1+$B$14) -> 658209.95 | F50: =E50*(1+$B$14) -> 677956.25
A51: Management Fee (% EGI) | B51: =B47*$B$16 -> 37920.676 | C51: =C47*$B$16 -> 40939.896 | D51: =D47*$B$16 -> 43993.245 | E51: =E47*$B$16 -> 46140.947 | F51: =F47*$B$16 -> 47384.055
A52: Replacement Reserves | B52: =$B$5*$B$17 -> 28000 | C52: =$B$5*$B$17 -> 28000 | D52: =$B$5*$B$17 -> 28000 | E52: =$B$5*$B$17 -> 28000 | F52: =$B$5*$B$17 -> 28000
A53: Total Operating Expenses | B53: =SUM(B50:B52) -> 668276.03 | C53: =SUM(C50:C52) -> 689365.91 | D53: =SUM(D50:D52) -> 711032.04 | E53: =SUM(E50:E52) -> 732350.9 | F53: =SUM(F50:F52) -> 753340.31
A54: NET OPERATING INCOME | B54: =B47-B53 -> 415171.86 | C54: =C47-C53 -> 480345.42 | D54: =D47-D53 -> 545917.83 | E54: =E47-E53 -> 585961.86 | F54: =F47-F53 -> 600489.84
A55: NOI Margin | B55: =B54/B47 -> 0.38319505 | C55: =C54/C47 -> 0.41065296 | D55: =D54/D47 -> 0.43431949 | E55: =E54/E47 -> 0.44447864 | F55: =F54/F47 -> 0.44354887
A59: DEBT SCHEDULE & RETURNS
A60: Beginning Loan Balance | C60: =$E$6 -> 3920000 | D60: =C63 -> 3878501.3 | E60: =D63 -> 3834097.7 | F60: =E63 -> 3786585.8
A61: Interest | C61: =C60*$E$7 -> 274400 | D61: =D60*$E$7 -> 271495.09 | E61: =E60*$E$7 -> 268386.84 | F61: =F60*$E$7 -> 265061.01
A62: Principal Amortization | C62: =-PMT($E$7,$E$8,$E$6)-C61 -> 41498.702 | D62: =-PMT($E$7,$E$8,$E$6)-D61 -> 44403.611 | E62: =-PMT($E$7,$E$8,$E$6)-E61 -> 47511.864 | F62: =-PMT($E$7,$E$8,$E$6)-F61 -> 50837.694
A63: Ending Loan Balance | C63: =C60-C62 -> 3878501.3 | D63: =D60-D62 -> 3834097.7 | E63: =E60-E62 -> 3786585.8 | F63: =F60-F62 -> 3735748.1
A64: Annual Debt Service | C64: =C61+C62 -> 315898.7 | D64: =D61+D62 -> 315898.7 | E64: =E61+E62 -> 315898.7 | F64: =F61+F62 -> 315898.7
A66: Net Operating Income | C66: =C54 -> 480345.42 | D66: =D54 -> 545917.83 | E66: =E54 -> 585961.86 | F66: =F54 -> 600489.84
A67: Less: Debt Service | C67: =-C64 -> -315898.7 | D67: =-D64 -> -315898.7 | E67: =-E64 -> -315898.7 | F67: =-F64 -> -315898.7
A68: Levered Cash Flow from Operations | C68: =C66-C64 -> 164446.72 | D68: =D66-D64 -> 230019.13 | E68: =E66-E64 -> 270063.16 | F68: =F66-F64 -> 284591.14
A70: Exit Value (Yr-5 fwd NOI / Exit Cap) | F70: =F54*(1+$B$12)/$E$11 -> 7497024.6
A71: Less: Selling Costs | F71: =-F70*$E$12 -> -149940.49
A72: Less: Loan Payoff | F72: =-F63 -> -3735748.1
A73: Net Sale Proceeds to Equity | F73: =F70+F71+F72 -> 3611336
A75: Levered Equity Cash Flow | B75: =-E13 -> -3461000 | C75: =C68 -> 164446.72 | D75: =D68 -> 230019.13 | E75: =E68 -> 270063.16 | F75: =F68+F73 -> 3895927.1
A77: RETURNS (4-yr hold) | C77: Independent | E77: Sponsor
A78: Levered IRR | C78: =IRR(B75:F75) -> 0.077154978 | E78: 0.2239
A79: Equity Multiple | C79: =SUM(C75:F75)/-B75 -> 1.3176701 | E79: 2.03
A80: Avg. Cash-on-Cash | C80: =AVERAGE(C68:F68)/-B75 -> 0.06855823 | E80: 0.112
A81: Unlevered IRR | C81: =IRR(B82:F82) -> 0.073432383 | E81: n/a
A82: Unlevered Equity Cash Flow | B82: =-(B8+B19+B8*E9) -> -7381000 | C82: =C54 -> 480345.42 | D82: =D54 -> 545917.83 | E82: =E54 -> 585961.86 | F82: =F54+F70*(1+$E$12*-1) -> 7947574
A85: SENSITIVITY — Levered IRR
A86: Exit Cap \ Rent Growth | B86: 0.02 | C86: 0.025 | D86: 0.03 | E86: 0.035 | F86: 0.04
A87: 0.0725 | B87: =_xlfn.LET(_xlpm.growth,B$86,_xlpm.xcap,$A87,_xlpm.egibase,$B$24,_xlpm.infl,$B$14,_xlpm.mgmt,$B$16,_xlpm.opexb,$B$50,_xlpm.resv,$B$5*$B$17,_xlpm.dsvc,-PMT($E$7,$E$8,$E$6),_xlpm.equity,$E$13,_xlpm.payoff,$F$63,_xlpm.sellc,$E$12,_xlpm.inca,_xlpm.egibase*(1+_xlpm.growth)^1+$C$46,_xlpm.incb,_xlpm.egibase*(1+_xlpm.growth)^2+$D$46,_xlpm.incc,_xlpm.egibase*(1+_xlpm.growth)^3+$E$46,_xlpm.incd,_xlpm.egibase*(1+_xlpm.growth)^4+$F$46,_xlpm.noia,_xlpm.inca-(_xlpm.opexb*(1+_xlpm.infl)^1+_xlpm.mgmt*_xlpm.inca+_xlpm.resv),_xlpm.noib,_xlpm.incb-(_xlpm.opexb*(1+_xlpm.infl)^2+_xlpm.mgmt*_xlpm.incb+_xlpm.resv),_xlpm.noic,_xlpm.incc-(_xlpm.opexb*(1+_xlpm.infl)^3+_xlpm.mgmt*_xlpm.incc+_xlpm.resv),_xlpm.noid,_xlpm.incd-(_xlpm.opexb*(1+_xlpm.infl)^4+_xlpm.mgmt*_xlpm.incd+_xlpm.resv),_xlpm.exitv,_xlpm.noid*(1+_xlpm.growth)/_xlpm.xcap,_xlpm.netsale,_xlpm.exitv*(1-_xlpm.sellc)-_xlpm.payoff,IRR(_xlfn.HSTACK(-_xlpm.equity,_xlpm.noia-_xlpm.dsvc,_xlpm.noib-_xlpm.dsvc,_xlpm.noic-_xlpm.dsvc,_xlpm.noid-_xlpm.dsvc+_xlpm.netsale))) -> 0.088941155 | C87: =_xlfn.LET(_xlpm.growth,C$86,_xlpm.xcap,$A87,_xlpm.egibase,$B$24,_xlpm.infl,$B$14,_xlpm.mgmt,$B$16,_xlpm.opexb,$B$50,_xlpm.resv,$B$5*$B$17,_xlpm.dsvc,-PMT($E$7,$E$8,$E$6),_xlpm.equity,$E$13,_xlpm.payoff,$F$63,_xlpm.sellc,$E$12,_xlpm.inca,_xlpm.egibase*(1+_xlpm.growth)^1+$C$46,_xlpm.incb,_xlpm.egibase*(1+_xlpm.growth)^2+$D$46,_xlpm.incc,_xlpm.egibase*(1+_xlpm.growth)^3+$E$46,_xlpm.incd,_xlpm.egibase*(1+_xlpm.growth)^4+$F$46,_xlpm.noia,_xlpm.inca-(_xlpm.opexb*(1+_xlpm.infl)^1+_xlpm.mgmt*_xlpm.inca+_xlpm.resv),_xlpm.noib,_xlpm.incb-(_xlpm.opexb*(1+_xlpm.infl)^2+_xlpm.mgmt*_xlpm.incb+_xlpm.resv),_xlpm.noic,_xlpm.incc-(_xlpm.opexb*(1+_xlpm.infl)^3+_xlpm.mgmt*_xlpm.incc+_xlpm.resv),_xlpm.noid,_xlpm.incd-(_xlpm.opexb*(1+_xlpm.infl)^4+_xlpm.mgmt*_xlpm.incd+_xlpm.resv),_xlpm.exitv,_xlpm.noid*(1+_xlpm.growth)/_xlpm.xcap,_xlpm.netsale,_xlpm.exitv*(1-_xlpm.sellc)-_xlpm.payoff,IRR(_xlfn.HSTACK(-_xlpm.equity,_xlpm.noia-_xlpm.dsvc,_xlpm.noib-_xlpm.dsvc,_xlpm.noic-_xlpm.dsvc,_xlpm.noid-_xlpm.dsvc+_xlpm.netsale))) -> 0.1126618 | D87: =_xlfn.LET(_xlpm.growth,D$86,_xlpm.xcap,$A87,_xlpm.egibase,$B$24,_xlpm.infl,$B$14,_xlpm.mgmt,$B$16,_xlpm.opexb,$B$50,_xlpm.resv,$B$5*$B$17,_xlpm.dsvc,-PMT($E$7,$E$8,$E$6),_xlpm.equity,$E$13,_xlpm.payoff,$F$63,_xlpm.sellc,$E$12,_xlpm.inca,_xlpm.egibase*(1+_xlpm.growth)^1+$C$46,_xlpm.incb,_xlpm.egibase*(1+_xlpm.growth)^2+$D$46,_xlpm.incc,_xlpm.egibase*(1+_xlpm.growth)^3+$E$46,_xlpm.incd,_xlpm.egibase*(1+_xlpm.growth)^4+$F$46,_xlpm.noia,_xlpm.inca-(_xlpm.opexb*(1+_xlpm.infl)^1+_xlpm.mgmt*_xlpm.inca+_xlpm.resv),_xlpm.noib,_xlpm.incb-(_xlpm.opexb*(1+_xlpm.infl)^2+_xlpm.mgmt*_xlpm.incb+_xlpm.resv),_xlpm.noic,_xlpm.incc-(_xlpm.opexb*(1+_xlpm.infl)^3+_xlpm.mgmt*_xlpm.incc+_xlpm.resv),_xlpm.noid,_xlpm.incd-(_xlpm.opexb*(1+_xlpm.infl)^4+_xlpm.mgmt*_xlpm.incd+_xlpm.resv),_xlpm.exitv,_xlpm.noid*(1+_xlpm.growth)/_xlpm.xcap,_xlpm.netsale,_xlpm.exitv*(1-_xlpm.sellc)-_xlpm.payoff,IRR(_xlfn.HSTACK(-_xlpm.equity,_xlpm.noia-_xlpm.dsvc,_xlpm.noib-_xlpm.dsvc,_xlpm.noic-_xlpm.dsvc,_xlpm.noid-_xlpm.dsvc+_xlpm.netsale))) -> 0.13547742 | E87: =_xlfn.LET(_xlpm.growth,E$86,_xlpm.xcap,$A87,_xlpm.egibase,$B$24,_xlpm.infl,$B$14,_xlpm.mgmt,$B$16,_xlpm.opexb,$B$50,_xlpm.resv,$B$5*$B$17,_xlpm.dsvc,-PMT($E$7,$E$8,$E$6),_xlpm.equity,$E$13,_xlpm.payoff,$F$63,_xlpm.sellc,$E$12,_xlpm.inca,_xlpm.egibase*(1+_xlpm.growth)^1+$C$46,_xlpm.incb,_xlpm.egibase*(1+_xlpm.growth)^2+$D$46,_xlpm.incc,_xlpm.egibase*(1+_xlpm.growth)^3+$E$46,_xlpm.incd,_xlpm.egibase*(1+_xlpm.growth)^4+$F$46,_xlpm.noia,_xlpm.inca-(_xlpm.opexb*(1+_xlpm.infl)^1+_xlpm.mgmt*_xlpm.inca+_xlpm.resv),_xlpm.noib,_xlpm.incb-(_xlpm.opexb*(1+_xlpm.infl)^2+_xlpm.mgmt*_xlpm.incb+_xlpm.resv),_xlpm.noic,_xlpm.incc-(_xlpm.opexb*(1+_xlpm.infl)^3+_xlpm.mgmt*_xlpm.incc+_xlpm.resv),_xlpm.noid,_xlpm.incd-(_xlpm.opexb*(1+_xlpm.infl)^4+_xlpm.mgmt*_xlpm.incd+_xlpm.resv),_xlpm.exitv,_xlpm.noid*(1+_xlpm.growth)/_xlpm.xcap,_xlpm.netsale,_xlpm.exitv*(1-_xlpm.sellc)-_xlpm.payoff,IRR(_xlfn.HSTACK(-_xlpm.equity,_xlpm.noia-_xlpm.dsvc,_xlpm.noib-_xlpm.dsvc,_xlpm.noic-_xlpm.dsvc,_xlpm.noid-_xlpm.dsvc+_xlpm.netsale))) -> 0.15749411 | F87: =_xlfn.LET(_xlpm.growth,F$86,_xlpm.xcap,$A87,_xlpm.egibase,$B$24,_xlpm.infl,$B$14,_xlpm.mgmt,$B$16,_xlpm.opexb,$B$50,_xlpm.resv,$B$5*$B$17,_xlpm.dsvc,-PMT($E$7,$E$8,$E$6),_xlpm.equity,$E$13,_xlpm.payoff,$F$63,_xlpm.sellc,$E$12,_xlpm.inca,_xlpm.egibase*(1+_xlpm.growth)^1+$C$46,_xlpm.incb,_xlpm.egibase*(1+_xlpm.growth)^2+$D$46,_xlpm.incc,_xlpm.egibase*(1+_xlpm.growth)^3+$E$46,_xlpm.incd,_xlpm.egibase*(1+_xlpm.growth)^4+$F$46,_xlpm.noia,_xlpm.inca-(_xlpm.opexb*(1+_xlpm.infl)^1+_xlpm.mgmt*_xlpm.inca+_xlpm.resv),_xlpm.noib,_xlpm.incb-(_xlpm.opexb*(1+_xlpm.infl)^2+_xlpm.mgmt*_xlpm.incb+_xlpm.resv),_xlpm.noic,_xlpm.incc-(_xlpm.opexb*(1+_xlpm.infl)^3+_xlpm.mgmt*_xlpm.incc+_xlpm.resv),_xlpm.noid,_xlpm.incd-(_xlpm.opexb*(1+_xlpm.infl)^4+_xlpm.mgmt*_xlpm.incd+_xlpm.resv),_xlpm.exitv,_xlpm.noid*(1+_xlpm.growth)/_xlpm.xcap,_xlpm.netsale,_xlpm.exitv*(1-_xlpm.sellc)-_xlpm.payoff,IRR(_xlfn.HSTACK(-_xlpm.equity,_xlpm.noia-_xlpm.dsvc,_xlpm.noib-_xlpm.dsvc,_xlpm.noic-_xlpm.dsvc,_xlpm.noid-_xlpm.dsvc+_xlpm.netsale))) -> 0.17880019
A88: 0.0775 | B88: =_xlfn.LET(_xlpm.growth,B$86,_xlpm.xcap,$A88,_xlpm.egibase,$B$24,_xlpm.infl,$B$14,_xlpm.mgmt,$B$16,_xlpm.opexb,$B$50,_xlpm.resv,$B$5*$B$17,_xlpm.dsvc,-PMT($E$7,$E$8,$E$6),_xlpm.equity,$E$13,_xlpm.payoff,$F$63,_xlpm.sellc,$E$12,_xlpm.inca,_xlpm.egibase*(1+_xlpm.growth)^1+$C$46,_xlpm.incb,_xlpm.egibase*(1+_xlpm.growth)^2+$D$46,_xlpm.incc,_xlpm.egibase*(1+_xlpm.growth)^3+$E$46,_xlpm.incd,_xlpm.egibase*(1+_xlpm.growth)^4+$F$46,_xlpm.noia,_xlpm.inca-(_xlpm.opexb*(1+_xlpm.infl)^1+_xlpm.mgmt*_xlpm.inca+_xlpm.resv),_xlpm.noib,_xlpm.incb-(_xlpm.opexb*(1+_xlpm.infl)^2+_xlpm.mgmt*_xlpm.incb+_xlpm.resv),_xlpm.noic,_xlpm.incc-(_xlpm.opexb*(1+_xlpm.infl)^3+_xlpm.mgmt*_xlpm.incc+_xlpm.resv),_xlpm.noid,_xlpm.incd-(_xlpm.opexb*(1+_xlpm.infl)^4+_xlpm.mgmt*_xlpm.incd+_xlpm.resv),_xlpm.exitv,_xlpm.noid*(1+_xlpm.growth)/_xlpm.xcap,_xlpm.netsale,_xlpm.exitv*(1-_xlpm.sellc)-_xlpm.payoff,IRR(_xlfn.HSTACK(-_xlpm.equity,_xlpm.noia-_xlpm.dsvc,_xlpm.noib-_xlpm.dsvc,_xlpm.noic-_xlpm.dsvc,_xlpm.noid-_xlpm.dsvc+_xlpm.netsale))) -> 0.057883347 | C88: =_xlfn.LET(_xlpm.growth,C$86,_xlpm.xcap,$A88,_xlpm.egibase,$B$24,_xlpm.infl,$B$14,_xlpm.mgmt,$B$16,_xlpm.opexb,$B$50,_xlpm.resv,$B$5*$B$17,_xlpm.dsvc,-PMT($E$7,$E$8,$E$6),_xlpm.equity,$E$13,_xlpm.payoff,$F$63,_xlpm.sellc,$E$12,_xlpm.inca,_xlpm.egibase*(1+_xlpm.growth)^1+$C$46,_xlpm.incb,_xlpm.egibase*(1+_xlpm.growth)^2+$D$46,_xlpm.incc,_xlpm.egibase*(1+_xlpm.growth)^3+$E$46,_xlpm.incd,_xlpm.egibase*(1+_xlpm.growth)^4+$F$46,_xlpm.noia,_xlpm.inca-(_xlpm.opexb*(1+_xlpm.infl)^1+_xlpm.mgmt*_xlpm.inca+_xlpm.resv),_xlpm.noib,_xlpm.incb-(_xlpm.opexb*(1+_xlpm.infl)^2+_xlpm.mgmt*_xlpm.incb+_xlpm.resv),_xlpm.noic,_xlpm.incc-(_xlpm.opexb*(1+_xlpm.infl)^3+_xlpm.mgmt*_xlpm.incc+_xlpm.resv),_xlpm.noid,_xlpm.incd-(_xlpm.opexb*(1+_xlpm.infl)^4+_xlpm.mgmt*_xlpm.incd+_xlpm.resv),_xlpm.exitv,_xlpm.noid*(1+_xlpm.growth)/_xlpm.xcap,_xlpm.netsale,_xlpm.exitv*(1-_xlpm.sellc)-_xlpm.payoff,IRR(_xlfn.HSTACK(-_xlpm.equity,_xlpm.noia-_xlpm.dsvc,_xlpm.noib-_xlpm.dsvc,_xlpm.noic-_xlpm.dsvc,_xlpm.noid-_xlpm.dsvc+_xlpm.netsale))) -> 0.082266766 | D88: =_xlfn.LET(_xlpm.growth,D$86,_xlpm.xcap,$A88,_xlpm.egibase,$B$24,_xlpm.infl,$B$14,_xlpm.mgmt,$B$16,_xlpm.opexb,$B$50,_xlpm.resv,$B$5*$B$17,_xlpm.dsvc,-PMT($E$7,$E$8,$E$6),_xlpm.equity,$E$13,_xlpm.payoff,$F$63,_xlpm.sellc,$E$12,_xlpm.inca,_xlpm.egibase*(1+_xlpm.growth)^1+$C$46,_xlpm.incb,_xlpm.egibase*(1+_xlpm.growth)^2+$D$46,_xlpm.incc,_xlpm.egibase*(1+_xlpm.growth)^3+$E$46,_xlpm.incd,_xlpm.egibase*(1+_xlpm.growth)^4+$F$46,_xlpm.noia,_xlpm.inca-(_xlpm.opexb*(1+_xlpm.infl)^1+_xlpm.mgmt*_xlpm.inca+_xlpm.resv),_xlpm.noib,_xlpm.incb-(_xlpm.opexb*(1+_xlpm.infl)^2+_xlpm.mgmt*_xlpm.incb+_xlpm.resv),_xlpm.noic,_xlpm.incc-(_xlpm.opexb*(1+_xlpm.infl)^3+_xlpm.mgmt*_xlpm.incc+_xlpm.resv),_xlpm.noid,_xlpm.incd-(_xlpm.opexb*(1+_xlpm.infl)^4+_xlpm.mgmt*_xlpm.incd+_xlpm.resv),_xlpm.exitv,_xlpm.noid*(1+_xlpm.growth)/_xlpm.xcap,_xlpm.netsale,_xlpm.exitv*(1-_xlpm.sellc)-_xlpm.payoff,IRR(_xlfn.HSTACK(-_xlpm.equity,_xlpm.noia-_xlpm.dsvc,_xlpm.noib-_xlpm.dsvc,_xlpm.noic-_xlpm.dsvc,_xlpm.noid-_xlpm.dsvc+_xlpm.netsale))) -> 0.10563974 | E88: =_xlfn.LET(_xlpm.growth,E$86,_xlpm.xcap,$A88,_xlpm.egibase,$B$24,_xlpm.infl,$B$14,_xlpm.mgmt,$B$16,_xlpm.opexb,$B$50,_xlpm.resv,$B$5*$B$17,_xlpm.dsvc,-PMT($E$7,$E$8,$E$6),_xlpm.equity,$E$13,_xlpm.payoff,$F$63,_xlpm.sellc,$E$12,_xlpm.inca,_xlpm.egibase*(1+_xlpm.growth)^1+$C$46,_xlpm.incb,_xlpm.egibase*(1+_xlpm.growth)^2+$D$46,_xlpm.incc,_xlpm.egibase*(1+_xlpm.growth)^3+$E$46,_xlpm.incd,_xlpm.egibase*(1+_xlpm.growth)^4+$F$46,_xlpm.noia,_xlpm.inca-(_xlpm.opexb*(1+_xlpm.infl)^1+_xlpm.mgmt*_xlpm.inca+_xlpm.resv),_xlpm.noib,_xlpm.incb-(_xlpm.opexb*(1+_xlpm.infl)^2+_xlpm.mgmt*_xlpm.incb+_xlpm.resv),_xlpm.noic,_xlpm.incc-(_xlpm.opexb*(1+_xlpm.infl)^3+_xlpm.mgmt*_xlpm.incc+_xlpm.resv),_xlpm.noid,_xlpm.incd-(_xlpm.opexb*(1+_xlpm.infl)^4+_xlpm.mgmt*_xlpm.incd+_xlpm.resv),_xlpm.exitv,_xlpm.noid*(1+_xlpm.growth)/_xlpm.xcap,_xlpm.netsale,_xlpm.exitv*(1-_xlpm.sellc)-_xlpm.payoff,IRR(_xlfn.HSTACK(-_xlpm.equity,_xlpm.noia-_xlpm.dsvc,_xlpm.noib-_xlpm.dsvc,_xlpm.noic-_xlpm.dsvc,_xlpm.noid-_xlpm.dsvc+_xlpm.netsale))) -> 0.12812763 | F88: =_xlfn.LET(_xlpm.growth,F$86,_xlpm.xcap,$A88,_xlpm.egibase,$B$24,_xlpm.infl,$B$14,_xlpm.mgmt,$B$16,_xlpm.opexb,$B$50,_xlpm.resv,$B$5*$B$17,_xlpm.dsvc,-PMT($E$7,$E$8,$E$6),_xlpm.equity,$E$13,_xlpm.payoff,$F$63,_xlpm.sellc,$E$12,_xlpm.inca,_xlpm.egibase*(1+_xlpm.growth)^1+$C$46,_xlpm.incb,_xlpm.egibase*(1+_xlpm.growth)^2+$D$46,_xlpm.incc,_xlpm.egibase*(1+_xlpm.growth)^3+$E$46,_xlpm.incd,_xlpm.egibase*(1+_xlpm.growth)^4+$F$46,_xlpm.noia,_xlpm.inca-(_xlpm.opexb*(1+_xlpm.infl)^1+_xlpm.mgmt*_xlpm.inca+_xlpm.resv),_xlpm.noib,_xlpm.incb-(_xlpm.opexb*(1+_xlpm.infl)^2+_xlpm.mgmt*_xlpm.incb+_xlpm.resv),_xlpm.noic,_xlpm.incc-(_xlpm.opexb*(1+_xlpm.infl)^3+_xlpm.mgmt*_xlpm.incc+_xlpm.resv),_xlpm.noid,_xlpm.incd-(_xlpm.opexb*(1+_xlpm.infl)^4+_xlpm.mgmt*_xlpm.incd+_xlpm.resv),_xlpm.exitv,_xlpm.noid*(1+_xlpm.growth)/_xlpm.xcap,_xlpm.netsale,_xlpm.exitv*(1-_xlpm.sellc)-_xlpm.payoff,IRR(_xlfn.HSTACK(-_xlpm.equity,_xlpm.noia-_xlpm.dsvc,_xlpm.noib-_xlpm.dsvc,_xlpm.noic-_xlpm.dsvc,_xlpm.noid-_xlpm.dsvc+_xlpm.netsale))) -> 0.14983355
A89: 0.0825 | B89: =_xlfn.LET(_xlpm.growth,B$86,_xlpm.xcap,$A89,_xlpm.egibase,$B$24,_xlpm.infl,$B$14,_xlpm.mgmt,$B$16,_xlpm.opexb,$B$50,_xlpm.resv,$B$5*$B$17,_xlpm.dsvc,-PMT($E$7,$E$8,$E$6),_xlpm.equity,$E$13,_xlpm.payoff,$F$63,_xlpm.sellc,$E$12,_xlpm.inca,_xlpm.egibase*(1+_xlpm.growth)^1+$C$46,_xlpm.incb,_xlpm.egibase*(1+_xlpm.growth)^2+$D$46,_xlpm.incc,_xlpm.egibase*(1+_xlpm.growth)^3+$E$46,_xlpm.incd,_xlpm.egibase*(1+_xlpm.growth)^4+$F$46,_xlpm.noia,_xlpm.inca-(_xlpm.opexb*(1+_xlpm.infl)^1+_xlpm.mgmt*_xlpm.inca+_xlpm.resv),_xlpm.noib,_xlpm.incb-(_xlpm.opexb*(1+_xlpm.infl)^2+_xlpm.mgmt*_xlpm.incb+_xlpm.resv),_xlpm.noic,_xlpm.incc-(_xlpm.opexb*(1+_xlpm.infl)^3+_xlpm.mgmt*_xlpm.incc+_xlpm.resv),_xlpm.noid,_xlpm.incd-(_xlpm.opexb*(1+_xlpm.infl)^4+_xlpm.mgmt*_xlpm.incd+_xlpm.resv),_xlpm.exitv,_xlpm.noid*(1+_xlpm.growth)/_xlpm.xcap,_xlpm.netsale,_xlpm.exitv*(1-_xlpm.sellc)-_xlpm.payoff,IRR(_xlfn.HSTACK(-_xlpm.equity,_xlpm.noia-_xlpm.dsvc,_xlpm.noib-_xlpm.dsvc,_xlpm.noic-_xlpm.dsvc,_xlpm.noid-_xlpm.dsvc+_xlpm.netsale))) -> 0.028008358 | C89: =_xlfn.LET(_xlpm.growth,C$86,_xlpm.xcap,$A89,_xlpm.egibase,$B$24,_xlpm.infl,$B$14,_xlpm.mgmt,$B$16,_xlpm.opexb,$B$50,_xlpm.resv,$B$5*$B$17,_xlpm.dsvc,-PMT($E$7,$E$8,$E$6),_xlpm.equity,$E$13,_xlpm.payoff,$F$63,_xlpm.sellc,$E$12,_xlpm.inca,_xlpm.egibase*(1+_xlpm.growth)^1+$C$46,_xlpm.incb,_xlpm.egibase*(1+_xlpm.growth)^2+$D$46,_xlpm.incc,_xlpm.egibase*(1+_xlpm.growth)^3+$E$46,_xlpm.incd,_xlpm.egibase*(1+_xlpm.growth)^4+$F$46,_xlpm.noia,_xlpm.inca-(_xlpm.opexb*(1+_xlpm.infl)^1+_xlpm.mgmt*_xlpm.inca+_xlpm.resv),_xlpm.noib,_xlpm.incb-(_xlpm.opexb*(1+_xlpm.infl)^2+_xlpm.mgmt*_xlpm.incb+_xlpm.resv),_xlpm.noic,_xlpm.incc-(_xlpm.opexb*(1+_xlpm.infl)^3+_xlpm.mgmt*_xlpm.incc+_xlpm.resv),_xlpm.noid,_xlpm.incd-(_xlpm.opexb*(1+_xlpm.infl)^4+_xlpm.mgmt*_xlpm.incd+_xlpm.resv),_xlpm.exitv,_xlpm.noid*(1+_xlpm.growth)/_xlpm.xcap,_xlpm.netsale,_xlpm.exitv*(1-_xlpm.sellc)-_xlpm.payoff,IRR(_xlfn.HSTACK(-_xlpm.equity,_xlpm.noia-_xlpm.dsvc,_xlpm.noib-_xlpm.dsvc,_xlpm.noic-_xlpm.dsvc,_xlpm.noid-_xlpm.dsvc+_xlpm.netsale))) -> 0.053148274 | D89: =_xlfn.LET(_xlpm.growth,D$86,_xlpm.xcap,$A89,_xlpm.egibase,$B$24,_xlpm.infl,$B$14,_xlpm.mgmt,$B$16,_xlpm.opexb,$B$50,_xlpm.resv,$B$5*$B$17,_xlpm.dsvc,-PMT($E$7,$E$8,$E$6),_xlpm.equity,$E$13,_xlpm.payoff,$F$63,_xlpm.sellc,$E$12,_xlpm.inca,_xlpm.egibase*(1+_xlpm.growth)^1+$C$46,_xlpm.incb,_xlpm.egibase*(1+_xlpm.growth)^2+$D$46,_xlpm.incc,_xlpm.egibase*(1+_xlpm.growth)^3+$E$46,_xlpm.incd,_xlpm.egibase*(1+_xlpm.growth)^4+$F$46,_xlpm.noia,_xlpm.inca-(_xlpm.opexb*(1+_xlpm.infl)^1+_xlpm.mgmt*_xlpm.inca+_xlpm.resv),_xlpm.noib,_xlpm.incb-(_xlpm.opexb*(1+_xlpm.infl)^2+_xlpm.mgmt*_xlpm.incb+_xlpm.resv),_xlpm.noic,_xlpm.incc-(_xlpm.opexb*(1+_xlpm.infl)^3+_xlpm.mgmt*_xlpm.incc+_xlpm.resv),_xlpm.noid,_xlpm.incd-(_xlpm.opexb*(1+_xlpm.infl)^4+_xlpm.mgmt*_xlpm.incd+_xlpm.resv),_xlpm.exitv,_xlpm.noid*(1+_xlpm.growth)/_xlpm.xcap,_xlpm.netsale,_xlpm.exitv*(1-_xlpm.sellc)-_xlpm.payoff,IRR(_xlfn.HSTACK(-_xlpm.equity,_xlpm.noia-_xlpm.dsvc,_xlpm.noib-_xlpm.dsvc,_xlpm.noic-_xlpm.dsvc,_xlpm.noid-_xlpm.dsvc+_xlpm.netsale))) -> 0.077154978 | E89: =_xlfn.LET(_xlpm.growth,E$86,_xlpm.xcap,$A89,_xlpm.egibase,$B$24,_xlpm.infl,$B$14,_xlpm.mgmt,$B$16,_xlpm.opexb,$B$50,_xlpm.resv,$B$5*$B$17,_xlpm.dsvc,-PMT($E$7,$E$8,$E$6),_xlpm.equity,$E$13,_xlpm.payoff,$F$63,_xlpm.sellc,$E$12,_xlpm.inca,_xlpm.egibase*(1+_xlpm.growth)^1+$C$46,_xlpm.incb,_xlpm.egibase*(1+_xlpm.growth)^2+$D$46,_xlpm.incc,_xlpm.egibase*(1+_xlpm.growth)^3+$E$46,_xlpm.incd,_xlpm.egibase*(1+_xlpm.growth)^4+$F$46,_xlpm.noia,_xlpm.inca-(_xlpm.opexb*(1+_xlpm.infl)^1+_xlpm.mgmt*_xlpm.inca+_xlpm.resv),_xlpm.noib,_xlpm.incb-(_xlpm.opexb*(1+_xlpm.infl)^2+_xlpm.mgmt*_xlpm.incb+_xlpm.resv),_xlpm.noic,_xlpm.incc-(_xlpm.opexb*(1+_xlpm.infl)^3+_xlpm.mgmt*_xlpm.incc+_xlpm.resv),_xlpm.noid,_xlpm.incd-(_xlpm.opexb*(1+_xlpm.infl)^4+_xlpm.mgmt*_xlpm.incd+_xlpm.resv),_xlpm.exitv,_xlpm.noid*(1+_xlpm.growth)/_xlpm.xcap,_xlpm.netsale,_xlpm.exitv*(1-_xlpm.sellc)-_xlpm.payoff,IRR(_xlfn.HSTACK(-_xlpm.equity,_xlpm.noia-_xlpm.dsvc,_xlpm.noib-_xlpm.dsvc,_xlpm.noic-_xlpm.dsvc,_xlpm.noid-_xlpm.dsvc+_xlpm.netsale))) -> 0.10017752 | F89: =_xlfn.LET(_xlpm.growth,F$86,_xlpm.xcap,$A89,_xlpm.egibase,$B$24,_xlpm.infl,$B$14,_xlpm.mgmt,$B$16,_xlpm.opexb,$B$50,_xlpm.resv,$B$5*$B$17,_xlpm.dsvc,-PMT($E$7,$E$8,$E$6),_xlpm.equity,$E$13,_xlpm.payoff,$F$63,_xlpm.sellc,$E$12,_xlpm.inca,_xlpm.egibase*(1+_xlpm.growth)^1+$C$46,_xlpm.incb,_xlpm.egibase*(1+_xlpm.growth)^2+$D$46,_xlpm.incc,_xlpm.egibase*(1+_xlpm.growth)^3+$E$46,_xlpm.incd,_xlpm.egibase*(1+_xlpm.growth)^4+$F$46,_xlpm.noia,_xlpm.inca-(_xlpm.opexb*(1+_xlpm.infl)^1+_xlpm.mgmt*_xlpm.inca+_xlpm.resv),_xlpm.noib,_xlpm.incb-(_xlpm.opexb*(1+_xlpm.infl)^2+_xlpm.mgmt*_xlpm.incb+_xlpm.resv),_xlpm.noic,_xlpm.incc-(_xlpm.opexb*(1+_xlpm.infl)^3+_xlpm.mgmt*_xlpm.incc+_xlpm.resv),_xlpm.noid,_xlpm.incd-(_xlpm.opexb*(1+_xlpm.infl)^4+_xlpm.mgmt*_xlpm.incd+_xlpm.resv),_xlpm.exitv,_xlpm.noid*(1+_xlpm.growth)/_xlpm.xcap,_xlpm.netsale,_xlpm.exitv*(1-_xlpm.sellc)-_xlpm.payoff,IRR(_xlfn.HSTACK(-_xlpm.equity,_xlpm.noia-_xlpm.dsvc,_xlpm.noib-_xlpm.dsvc,_xlpm.noic-_xlpm.dsvc,_xlpm.noid-_xlpm.dsvc+_xlpm.netsale))) -> 0.12233698
A90: 0.0875 | B90: =_xlfn.LET(_xlpm.growth,B$86,_xlpm.xcap,$A90,_xlpm.egibase,$B$24,_xlpm.infl,$B$14,_xlpm.mgmt,$B$16,_xlpm.opexb,$B$50,_xlpm.resv,$B$5*$B$17,_xlpm.dsvc,-PMT($E$7,$E$8,$E$6),_xlpm.equity,$E$13,_xlpm.payoff,$F$63,_xlpm.sellc,$E$12,_xlpm.inca,_xlpm.egibase*(1+_xlpm.growth)^1+$C$46,_xlpm.incb,_xlpm.egibase*(1+_xlpm.growth)^2+$D$46,_xlpm.incc,_xlpm.egibase*(1+_xlpm.growth)^3+$E$46,_xlpm.incd,_xlpm.egibase*(1+_xlpm.growth)^4+$F$46,_xlpm.noia,_xlpm.inca-(_xlpm.opexb*(1+_xlpm.infl)^1+_xlpm.mgmt*_xlpm.inca+_xlpm.resv),_xlpm.noib,_xlpm.incb-(_xlpm.opexb*(1+_xlpm.infl)^2+_xlpm.mgmt*_xlpm.incb+_xlpm.resv),_xlpm.noic,_xlpm.incc-(_xlpm.opexb*(1+_xlpm.infl)^3+_xlpm.mgmt*_xlpm.incc+_xlpm.resv),_xlpm.noid,_xlpm.incd-(_xlpm.opexb*(1+_xlpm.infl)^4+_xlpm.mgmt*_xlpm.incd+_xlpm.resv),_xlpm.exitv,_xlpm.noid*(1+_xlpm.growth)/_xlpm.xcap,_xlpm.netsale,_xlpm.exitv*(1-_xlpm.sellc)-_xlpm.payoff,IRR(_xlfn.HSTACK(-_xlpm.equity,_xlpm.noia-_xlpm.dsvc,_xlpm.noib-_xlpm.dsvc,_xlpm.noic-_xlpm.dsvc,_xlpm.noid-_xlpm.dsvc+_xlpm.netsale))) -> -0.00094615103 | C90: =_xlfn.LET(_xlpm.growth,C$86,_xlpm.xcap,$A90,_xlpm.egibase,$B$24,_xlpm.infl,$B$14,_xlpm.mgmt,$B$16,_xlpm.opexb,$B$50,_xlpm.resv,$B$5*$B$17,_xlpm.dsvc,-PMT($E$7,$E$8,$E$6),_xlpm.equity,$E$13,_xlpm.payoff,$F$63,_xlpm.sellc,$E$12,_xlpm.inca,_xlpm.egibase*(1+_xlpm.growth)^1+$C$46,_xlpm.incb,_xlpm.egibase*(1+_xlpm.growth)^2+$D$46,_xlpm.incc,_xlpm.egibase*(1+_xlpm.growth)^3+$E$46,_xlpm.incd,_xlpm.egibase*(1+_xlpm.growth)^4+$F$46,_xlpm.noia,_xlpm.inca-(_xlpm.opexb*(1+_xlpm.infl)^1+_xlpm.mgmt*_xlpm.inca+_xlpm.resv),_xlpm.noib,_xlpm.incb-(_xlpm.opexb*(1+_xlpm.infl)^2+_xlpm.mgmt*_xlpm.incb+_xlpm.resv),_xlpm.noic,_xlpm.incc-(_xlpm.opexb*(1+_xlpm.infl)^3+_xlpm.mgmt*_xlpm.incc+_xlpm.resv),_xlpm.noid,_xlpm.incd-(_xlpm.opexb*(1+_xlpm.infl)^4+_xlpm.mgmt*_xlpm.incd+_xlpm.resv),_xlpm.exitv,_xlpm.noid*(1+_xlpm.growth)/_xlpm.xcap,_xlpm.netsale,_xlpm.exitv*(1-_xlpm.sellc)-_xlpm.payoff,IRR(_xlfn.HSTACK(-_xlpm.equity,_xlpm.noia-_xlpm.dsvc,_xlpm.noib-_xlpm.dsvc,_xlpm.noic-_xlpm.dsvc,_xlpm.noid-_xlpm.dsvc+_xlpm.netsale))) -> 0.025055444 | D90: =_xlfn.LET(_xlpm.growth,D$86,_xlpm.xcap,$A90,_xlpm.egibase,$B$24,_xlpm.infl,$B$14,_xlpm.mgmt,$B$16,_xlpm.opexb,$B$50,_xlpm.resv,$B$5*$B$17,_xlpm.dsvc,-PMT($E$7,$E$8,$E$6),_xlpm.equity,$E$13,_xlpm.payoff,$F$63,_xlpm.sellc,$E$12,_xlpm.inca,_xlpm.egibase*(1+_xlpm.growth)^1+$C$46,_xlpm.incb,_xlpm.egibase*(1+_xlpm.growth)^2+$D$46,_xlpm.incc,_xlpm.egibase*(1+_xlpm.growth)^3+$E$46,_xlpm.incd,_xlpm.egibase*(1+_xlpm.growth)^4+$F$46,_xlpm.noia,_xlpm.inca-(_xlpm.opexb*(1+_xlpm.infl)^1+_xlpm.mgmt*_xlpm.inca+_xlpm.resv),_xlpm.noib,_xlpm.incb-(_xlpm.opexb*(1+_xlpm.infl)^2+_xlpm.mgmt*_xlpm.incb+_xlpm.resv),_xlpm.noic,_xlpm.incc-(_xlpm.opexb*(1+_xlpm.infl)^3+_xlpm.mgmt*_xlpm.incc+_xlpm.resv),_xlpm.noid,_xlpm.incd-(_xlpm.opexb*(1+_xlpm.infl)^4+_xlpm.mgmt*_xlpm.incd+_xlpm.resv),_xlpm.exitv,_xlpm.noid*(1+_xlpm.growth)/_xlpm.xcap,_xlpm.netsale,_xlpm.exitv*(1-_xlpm.sellc)-_xlpm.payoff,IRR(_xlfn.HSTACK(-_xlpm.equity,_xlpm.noia-_xlpm.dsvc,_xlpm.noib-_xlpm.dsvc,_xlpm.noic-_xlpm.dsvc,_xlpm.noid-_xlpm.dsvc+_xlpm.netsale))) -> 0.049779729 | E90: =_xlfn.LET(_xlpm.growth,E$86,_xlpm.xcap,$A90,_xlpm.egibase,$B$24,_xlpm.infl,$B$14,_xlpm.mgmt,$B$16,_xlpm.opexb,$B$50,_xlpm.resv,$B$5*$B$17,_xlpm.dsvc,-PMT($E$7,$E$8,$E$6),_xlpm.equity,$E$13,_xlpm.payoff,$F$63,_xlpm.sellc,$E$12,_xlpm.inca,_xlpm.egibase*(1+_xlpm.growth)^1+$C$46,_xlpm.incb,_xlpm.egibase*(1+_xlpm.growth)^2+$D$46,_xlpm.incc,_xlpm.egibase*(1+_xlpm.growth)^3+$E$46,_xlpm.incd,_xlpm.egibase*(1+_xlpm.growth)^4+$F$46,_xlpm.noia,_xlpm.inca-(_xlpm.opexb*(1+_xlpm.infl)^1+_xlpm.mgmt*_xlpm.inca+_xlpm.resv),_xlpm.noib,_xlpm.incb-(_xlpm.opexb*(1+_xlpm.infl)^2+_xlpm.mgmt*_xlpm.incb+_xlpm.resv),_xlpm.noic,_xlpm.incc-(_xlpm.opexb*(1+_xlpm.infl)^3+_xlpm.mgmt*_xlpm.incc+_xlpm.resv),_xlpm.noid,_xlpm.incd-(_xlpm.opexb*(1+_xlpm.infl)^4+_xlpm.mgmt*_xlpm.incd+_xlpm.resv),_xlpm.exitv,_xlpm.noid*(1+_xlpm.growth)/_xlpm.xcap,_xlpm.netsale,_xlpm.exitv*(1-_xlpm.sellc)-_xlpm.payoff,IRR(_xlfn.HSTACK(-_xlpm.equity,_xlpm.noia-_xlpm.dsvc,_xlpm.noib-_xlpm.dsvc,_xlpm.noic-_xlpm.dsvc,_xlpm.noid-_xlpm.dsvc+_xlpm.netsale))) -> 0.073405249 | F90: =_xlfn.LET(_xlpm.growth,F$86,_xlpm.xcap,$A90,_xlpm.egibase,$B$24,_xlpm.infl,$B$14,_xlpm.mgmt,$B$16,_xlpm.opexb,$B$50,_xlpm.resv,$B$5*$B$17,_xlpm.dsvc,-PMT($E$7,$E$8,$E$6),_xlpm.equity,$E$13,_xlpm.payoff,$F$63,_xlpm.sellc,$E$12,_xlpm.inca,_xlpm.egibase*(1+_xlpm.growth)^1+$C$46,_xlpm.incb,_xlpm.egibase*(1+_xlpm.growth)^2+$D$46,_xlpm.incc,_xlpm.egibase*(1+_xlpm.growth)^3+$E$46,_xlpm.incd,_xlpm.egibase*(1+_xlpm.growth)^4+$F$46,_xlpm.noia,_xlpm.inca-(_xlpm.opexb*(1+_xlpm.infl)^1+_xlpm.mgmt*_xlpm.inca+_xlpm.resv),_xlpm.noib,_xlpm.incb-(_xlpm.opexb*(1+_xlpm.infl)^2+_xlpm.mgmt*_xlpm.incb+_xlpm.resv),_xlpm.noic,_xlpm.incc-(_xlpm.opexb*(1+_xlpm.infl)^3+_xlpm.mgmt*_xlpm.incc+_xlpm.resv),_xlpm.noid,_xlpm.incd-(_xlpm.opexb*(1+_xlpm.infl)^4+_xlpm.mgmt*_xlpm.incd+_xlpm.resv),_xlpm.exitv,_xlpm.noid*(1+_xlpm.growth)/_xlpm.xcap,_xlpm.netsale,_xlpm.exitv*(1-_xlpm.sellc)-_xlpm.payoff,IRR(_xlfn.HSTACK(-_xlpm.equity,_xlpm.noia-_xlpm.dsvc,_xlpm.noib-_xlpm.dsvc,_xlpm.noic-_xlpm.dsvc,_xlpm.noid-_xlpm.dsvc+_xlpm.netsale))) -> 0.096074984
A91: 0.0925 | B91: =_xlfn.LET(_xlpm.growth,B$86,_xlpm.xcap,$A91,_xlpm.egibase,$B$24,_xlpm.infl,$B$14,_xlpm.mgmt,$B$16,_xlpm.opexb,$B$50,_xlpm.resv,$B$5*$B$17,_xlpm.dsvc,-PMT($E$7,$E$8,$E$6),_xlpm.equity,$E$13,_xlpm.payoff,$F$63,_xlpm.sellc,$E$12,_xlpm.inca,_xlpm.egibase*(1+_xlpm.growth)^1+$C$46,_xlpm.incb,_xlpm.egibase*(1+_xlpm.growth)^2+$D$46,_xlpm.incc,_xlpm.egibase*(1+_xlpm.growth)^3+$E$46,_xlpm.incd,_xlpm.egibase*(1+_xlpm.growth)^4+$F$46,_xlpm.noia,_xlpm.inca-(_xlpm.opexb*(1+_xlpm.infl)^1+_xlpm.mgmt*_xlpm.inca+_xlpm.resv),_xlpm.noib,_xlpm.incb-(_xlpm.opexb*(1+_xlpm.infl)^2+_xlpm.mgmt*_xlpm.incb+_xlpm.resv),_xlpm.noic,_xlpm.incc-(_xlpm.opexb*(1+_xlpm.infl)^3+_xlpm.mgmt*_xlpm.incc+_xlpm.resv),_xlpm.noid,_xlpm.incd-(_xlpm.opexb*(1+_xlpm.infl)^4+_xlpm.mgmt*_xlpm.incd+_xlpm.resv),_xlpm.exitv,_xlpm.noid*(1+_xlpm.growth)/_xlpm.xcap,_xlpm.netsale,_xlpm.exitv*(1-_xlpm.sellc)-_xlpm.payoff,IRR(_xlfn.HSTACK(-_xlpm.equity,_xlpm.noia-_xlpm.dsvc,_xlpm.noib-_xlpm.dsvc,_xlpm.noic-_xlpm.dsvc,_xlpm.noid-_xlpm.dsvc+_xlpm.netsale))) -> -0.029214603 | C91: =_xlfn.LET(_xlpm.growth,C$86,_xlpm.xcap,$A91,_xlpm.egibase,$B$24,_xlpm.infl,$B$14,_xlpm.mgmt,$B$16,_xlpm.opexb,$B$50,_xlpm.resv,$B$5*$B$17,_xlpm.dsvc,-PMT($E$7,$E$8,$E$6),_xlpm.equity,$E$13,_xlpm.payoff,$F$63,_xlpm.sellc,$E$12,_xlpm.inca,_xlpm.egibase*(1+_xlpm.growth)^1+$C$46,_xlpm.incb,_xlpm.egibase*(1+_xlpm.growth)^2+$D$46,_xlpm.incc,_xlpm.egibase*(1+_xlpm.growth)^3+$E$46,_xlpm.incd,_xlpm.egibase*(1+_xlpm.growth)^4+$F$46,_xlpm.noia,_xlpm.inca-(_xlpm.opexb*(1+_xlpm.infl)^1+_xlpm.mgmt*_xlpm.inca+_xlpm.resv),_xlpm.noib,_xlpm.incb-(_xlpm.opexb*(1+_xlpm.infl)^2+_xlpm.mgmt*_xlpm.incb+_xlpm.resv),_xlpm.noic,_xlpm.incc-(_xlpm.opexb*(1+_xlpm.infl)^3+_xlpm.mgmt*_xlpm.incc+_xlpm.resv),_xlpm.noid,_xlpm.incd-(_xlpm.opexb*(1+_xlpm.infl)^4+_xlpm.mgmt*_xlpm.incd+_xlpm.resv),_xlpm.exitv,_xlpm.noid*(1+_xlpm.growth)/_xlpm.xcap,_xlpm.netsale,_xlpm.exitv*(1-_xlpm.sellc)-_xlpm.payoff,IRR(_xlfn.HSTACK(-_xlpm.equity,_xlpm.noia-_xlpm.dsvc,_xlpm.noib-_xlpm.dsvc,_xlpm.noic-_xlpm.dsvc,_xlpm.noid-_xlpm.dsvc+_xlpm.netsale))) -> -0.0022310207 | D91: =_xlfn.LET(_xlpm.growth,D$86,_xlpm.xcap,$A91,_xlpm.egibase,$B$24,_xlpm.infl,$B$14,_xlpm.mgmt,$B$16,_xlpm.opexb,$B$50,_xlpm.resv,$B$5*$B$17,_xlpm.dsvc,-PMT($E$7,$E$8,$E$6),_xlpm.equity,$E$13,_xlpm.payoff,$F$63,_xlpm.sellc,$E$12,_xlpm.inca,_xlpm.egibase*(1+_xlpm.growth)^1+$C$46,_xlpm.incb,_xlpm.egibase*(1+_xlpm.growth)^2+$D$46,_xlpm.incc,_xlpm.egibase*(1+_xlpm.growth)^3+$E$46,_xlpm.incd,_xlpm.egibase*(1+_xlpm.growth)^4+$F$46,_xlpm.noia,_xlpm.inca-(_xlpm.opexb*(1+_xlpm.infl)^1+_xlpm.mgmt*_xlpm.inca+_xlpm.resv),_xlpm.noib,_xlpm.incb-(_xlpm.opexb*(1+_xlpm.infl)^2+_xlpm.mgmt*_xlpm.incb+_xlpm.resv),_xlpm.noic,_xlpm.incc-(_xlpm.opexb*(1+_xlpm.infl)^3+_xlpm.mgmt*_xlpm.incc+_xlpm.resv),_xlpm.noid,_xlpm.incd-(_xlpm.opexb*(1+_xlpm.infl)^4+_xlpm.mgmt*_xlpm.incd+_xlpm.resv),_xlpm.exitv,_xlpm.noid*(1+_xlpm.growth)/_xlpm.xcap,_xlpm.netsale,_xlpm.exitv*(1-_xlpm.sellc)-_xlpm.payoff,IRR(_xlfn.HSTACK(-_xlpm.equity,_xlpm.noia-_xlpm.dsvc,_xlpm.noib-_xlpm.dsvc,_xlpm.noic-_xlpm.dsvc,_xlpm.noid-_xlpm.dsvc+_xlpm.netsale))) -> 0.023304623 | E91: =_xlfn.LET(_xlpm.growth,E$86,_xlpm.xcap,$A91,_xlpm.egibase,$B$24,_xlpm.infl,$B$14,_xlpm.mgmt,$B$16,_xlpm.opexb,$B$50,_xlpm.resv,$B$5*$B$17,_xlpm.dsvc,-PMT($E$7,$E$8,$E$6),_xlpm.equity,$E$13,_xlpm.payoff,$F$63,_xlpm.sellc,$E$12,_xlpm.inca,_xlpm.egibase*(1+_xlpm.growth)^1+$C$46,_xlpm.incb,_xlpm.egibase*(1+_xlpm.growth)^2+$D$46,_xlpm.incc,_xlpm.egibase*(1+_xlpm.growth)^3+$E$46,_xlpm.incd,_xlpm.egibase*(1+_xlpm.growth)^4+$F$46,_xlpm.noia,_xlpm.inca-(_xlpm.opexb*(1+_xlpm.infl)^1+_xlpm.mgmt*_xlpm.inca+_xlpm.resv),_xlpm.noib,_xlpm.incb-(_xlpm.opexb*(1+_xlpm.infl)^2+_xlpm.mgmt*_xlpm.incb+_xlpm.resv),_xlpm.noic,_xlpm.incc-(_xlpm.opexb*(1+_xlpm.infl)^3+_xlpm.mgmt*_xlpm.incc+_xlpm.resv),_xlpm.noid,_xlpm.incd-(_xlpm.opexb*(1+_xlpm.infl)^4+_xlpm.mgmt*_xlpm.incd+_xlpm.resv),_xlpm.exitv,_xlpm.noid*(1+_xlpm.growth)/_xlpm.xcap,_xlpm.netsale,_xlpm.exitv*(1-_xlpm.sellc)-_xlpm.payoff,IRR(_xlfn.HSTACK(-_xlpm.equity,_xlpm.noia-_xlpm.dsvc,_xlpm.noib-_xlpm.dsvc,_xlpm.noic-_xlpm.dsvc,_xlpm.noid-_xlpm.dsvc+_xlpm.netsale))) -> 0.047607975 | F91: =_xlfn.LET(_xlpm.growth,F$86,_xlpm.xcap,$A91,_xlpm.egibase,$B$24,_xlpm.infl,$B$14,_xlpm.mgmt,$B$16,_xlpm.opexb,$B$50,_xlpm.resv,$B$5*$B$17,_xlpm.dsvc,-PMT($E$7,$E$8,$E$6),_xlpm.equity,$E$13,_xlpm.payoff,$F$63,_xlpm.sellc,$E$12,_xlpm.inca,_xlpm.egibase*(1+_xlpm.growth)^1+$C$46,_xlpm.incb,_xlpm.egibase*(1+_xlpm.growth)^2+$D$46,_xlpm.incc,_xlpm.egibase*(1+_xlpm.growth)^3+$E$46,_xlpm.incd,_xlpm.egibase*(1+_xlpm.growth)^4+$F$46,_xlpm.noia,_xlpm.inca-(_xlpm.opexb*(1+_xlpm.infl)^1+_xlpm.mgmt*_xlpm.inca+_xlpm.resv),_xlpm.noib,_xlpm.incb-(_xlpm.opexb*(1+_xlpm.infl)^2+_xlpm.mgmt*_xlpm.incb+_xlpm.resv),_xlpm.noic,_xlpm.incc-(_xlpm.opexb*(1+_xlpm.infl)^3+_xlpm.mgmt*_xlpm.incc+_xlpm.resv),_xlpm.noid,_xlpm.incd-(_xlpm.opexb*(1+_xlpm.infl)^4+_xlpm.mgmt*_xlpm.incd+_xlpm.resv),_xlpm.exitv,_xlpm.noid*(1+_xlpm.growth)/_xlpm.xcap,_xlpm.netsale,_xlpm.exitv*(1-_xlpm.sellc)-_xlpm.payoff,IRR(_xlfn.HSTACK(-_xlpm.equity,_xlpm.noia-_xlpm.dsvc,_xlpm.noib-_xlpm.dsvc,_xlpm.noic-_xlpm.dsvc,_xlpm.noid-_xlpm.dsvc+_xlpm.netsale))) -> 0.070849015
A93: KEY FINDINGS vs. SPONSOR
A94: • Normalized in-place NOI of ~$415K ties to the sponsor's stated 7.41% going-in cap — their entry basis checks out.
A95: • Sponsor projects a Year-4 sale at ~$11.6M (>2x purchase). That implies exit NOI of ~$925K vs. my conservative ~$600K — a very aggressive NOI ramp.
A96: • On conservative assumptions (3% growth, $100 reno premium, 8.25% exit cap) the deal returns ~7.7% levered IRR / 1.32x — far below the sponsor's 22.4% / 2.03x.
A97: • Watch: TX property-tax reassessment to sale price could add materially to opex (T-12 taxes are only $62K). Reno funded in equity basis at close (conservative).
A98: • Only a one-pager was provided for Amarillo (no full rent-roll growth detail), so revenue is anchored to the T-12 effective income and grown.

Sheet Oak Cliff UW
A1: Oak Cliff Multifamily
A2: 136 units | Built 1974 | South Dallas | T-12 rolling 12mo | Independent / Conservative Case
A4: KEY ASSUMPTIONS | D4: FINANCING & EXIT
A5: # Units | B5: 136 | D5: Loan-to-Price (LTV) | E5: 0.7
A6: Year Built | B6: 1974 | D6: Loan Amount | E6: =B8*E5 -> 5075000
A7: Total SF | B7: ='Oak RR'!F140 -> 100302 | D7: Interest Rate | E7: 0.075
A8: Purchase Price | B8: 7250000 | D8: Amortization (yrs) | E8: 30
A9: Price / Unit | B9: =B8/B5 -> 53308.824 | D9: Closing Costs (% price) | E9: 0.02
A10: Hold Period (yrs) | B10: 5 | D10: Going-in Cap (normalized) | E10: =B33/B8 -> 0.096746066
D11: Exit Cap Rate | E11: 0.0925
A12: Rent Growth (annual) | B12: 0.03 | D12: Selling Costs (% sale) | E12: 0.02
A13: Other Income Growth | B13: 0.03 | D13: Total Equity Required | E13: =B8+B19+B8*E9-E6 -> 4156000
A14: Expense Inflation | B14: 0.03
A15: Stabilized Econ. Vacancy | B15: 0.07
A16: Mgmt Fee (% EGI) | B16: 0.035
A17: Replacement Reserves ($/unit) | B17: 250
A18: Rent Premium (reno + MTM, $/unit/mo) | B18: 110
A19: Renovation Budget ($) | B19: 1836000
A21: IN-PLACE OPERATING STATEMENT (T-12, Normalized) | B21: T-12 Actual
A22: Rental Income (net of concessions) | B22: ='Oak T-12'!N8+'Oak T-12'!N9 -> 1549904.8
A23: Other Income (fees, parking, misc) | B23: ='Oak T-12'!N23-('Oak T-12'!N8+'Oak T-12'!N9) -> 16842.91
A24: Effective Gross Income | B24: =B22+B23 -> 1566747.7
A25: Controllable Operating Expenses | B25: ='Oak T-12'!N44 -> 524060.05
A26: Management Fee | B26: ='Oak T-12'!N48 -> 62649.79
A27: Property Insurance | B27: ='Oak T-12'!N49 -> 73102.51
A28: Property Taxes | B28: ='Oak T-12'!N50 -> 179340
A29: Total Operating Expenses (reported) | B29: =SUM(B25:B28) -> 839152.35
A30: NOI (as reported) | B30: =B24-B29 -> 727595.36
A31: (±) Normalize mgmt fee to 3.5% of EGI | B31: ='Oak T-12'!N48-B16*B24 -> 7813.6201
A32: (–) Add replacement reserves ($/unit) | B32: =-B5*B17 -> -34000
A33: Normalized In-Place NOI | B33: =B30+B31+B32 -> 701408.98
A34: Normalized Going-in Cap Rate | B34: =B33/B8 -> 0.096746066
A42: PRO FORMA CASH FLOW
B43: In-Place | C43: Year 1 | D43: Year 2 | E43: Year 3 | F43: Year 4 | G43: Year 5
A44: Rental & Other Income (grown) | B44: =B24 -> 1566747.7 | C44: =B44*(1+$B$12) -> 1613750.1 | D44: =C44*(1+$B$12) -> 1662162.6 | E44: =D44*(1+$B$12) -> 1712027.5 | F44: =E44*(1+$B$12) -> 1763388.4 | G44: =F44*(1+$B$12) -> 1816290
A45: Rent premium % achieved | B45: 0 | C45: 0.4 | D45: 0.7 | E45: 1 | F45: 1 | G45: 1
A46: (+) Rent Premium ($) | B46: =$B$5*$B$18*12*B45 -> 0 | C46: =$B$5*$B$18*12*C45 -> 71808 | D46: =$B$5*$B$18*12*D45 -> 125664 | E46: =$B$5*$B$18*12*E45 -> 179520 | F46: =$B$5*$B$18*12*F45 -> 179520 | G46: =$B$5*$B$18*12*G45 -> 179520
A47: Effective Gross Income | B47: =B44+B46 -> 1566747.7 | C47: =C44+C46 -> 1685558.1 | D47: =D44+D46 -> 1787826.6 | E47: =E44+E46 -> 1891547.5 | F47: =F44+F46 -> 1942908.4 | G47: =G44+G46 -> 1995810
A49: Operating Expenses:
A50: Opex excl. mgmt fee & reserves (inflated) | B50: =B29-'Oak T-12'!N48 -> 776502.56 | C50: =B50*(1+$B$14) -> 799797.64 | D50: =C50*(1+$B$14) -> 823791.57 | E50: =D50*(1+$B$14) -> 848505.31 | F50: =E50*(1+$B$14) -> 873960.47 | G50: =F50*(1+$B$14) -> 900179.29
A51: Management Fee (% EGI) | B51: =B47*$B$16 -> 54836.17 | C51: =C47*$B$16 -> 58994.535 | D51: =D47*$B$16 -> 62573.933 | E51: =E47*$B$16 -> 66204.163 | F51: =F47*$B$16 -> 68001.792 | G51: =G47*$B$16 -> 69853.35
A52: Replacement Reserves | B52: =$B$5*$B$17 -> 34000 | C52: =$B$5*$B$17 -> 34000 | D52: =$B$5*$B$17 -> 34000 | E52: =$B$5*$B$17 -> 34000 | F52: =$B$5*$B$17 -> 34000 | G52: =$B$5*$B$17 -> 34000
A53: Total Operating Expenses | B53: =SUM(B50:B52) -> 865338.73 | C53: =SUM(C50:C52) -> 892792.17 | D53: =SUM(D50:D52) -> 920365.5 | E53: =SUM(E50:E52) -> 948709.48 | F53: =SUM(F50:F52) -> 975962.26 | G53: =SUM(G50:G52) -> 1004032.6
A54: NET OPERATING INCOME | B54: =B47-B53 -> 701408.98 | C54: =C47-C53 -> 792765.97 | D54: =D47-D53 -> 867461.15 | E54: =E47-E53 -> 942838.05 | F54: =F47-F53 -> 966946.09 | G54: =G47-G53 -> 991777.36
A55: NOI Margin | B55: =B54/B47 -> 0.4476847 | G55: =G54/G47 -> 0.49692975
A59: DEBT SCHEDULE & RETURNS
A60: Beginning Loan Balance | C60: =$E$6 -> 5075000 | D60: =C63 -> 5025918.5 | E60: =D63 -> 4973155.8 | F60: =E63 -> 4916436 | G60: =F63 -> 4855462.2
A61: Interest | C61: =C60*$E$7 -> 380625 | D61: =D60*$E$7 -> 376943.89 | E61: =E60*$E$7 -> 372986.69 | F61: =F60*$E$7 -> 368732.7 | G61: =G60*$E$7 -> 364159.66
A62: Principal Amortization | C62: =-PMT($E$7,$E$8,$E$6)-C61 -> 49081.522 | D62: =-PMT($E$7,$E$8,$E$6)-D61 -> 52762.636 | E62: =-PMT($E$7,$E$8,$E$6)-E61 -> 56719.833 | F62: =-PMT($E$7,$E$8,$E$6)-F61 -> 60973.821 | G62: =-PMT($E$7,$E$8,$E$6)-G61 -> 65546.857
A63: Ending Loan Balance | C63: =C60-C62 -> 5025918.5 | D63: =D60-D62 -> 4973155.8 | E63: =E60-E62 -> 4916436 | F63: =F60-F62 -> 4855462.2 | G63: =G60-G62 -> 4789915.3
A64: Annual Debt Service | C64: =C61+C62 -> 429706.52 | D64: =D61+D62 -> 429706.52 | E64: =E61+E62 -> 429706.52 | F64: =F61+F62 -> 429706.52 | G64: =G61+G62 -> 429706.52
A66: Net Operating Income | C66: =C54 -> 792765.97 | D66: =D54 -> 867461.15 | E66: =E54 -> 942838.05 | F66: =F54 -> 966946.09 | G66: =G54 -> 991777.36
A67: Less: Debt Service | C67: =-C64 -> -429706.52 | D67: =-D64 -> -429706.52 | E67: =-E64 -> -429706.52 | F67: =-F64 -> -429706.52 | G67: =-G64 -> -429706.52
A68: Levered Cash Flow from Operations | C68: =C66-C64 -> 363059.45 | D68: =D66-D64 -> 437754.63 | E68: =E66-E64 -> 513131.53 | F68: =F66-F64 -> 537239.56 | G68: =G66-G64 -> 562070.84
A70: Exit Value (fwd NOI / Exit Cap) | G70: =G54*(1+$B$12)/$E$11 -> 11043575
A71: Less: Selling Costs | G71: =-G70*$E$12 -> -220871.5
A72: Less: Loan Payoff | G72: =-G63 -> -4789915.3
A73: Net Sale Proceeds to Equity | G73: =G70+G71+G72 -> 6032788.1
A75: Levered Equity Cash Flow | B75: =-E13 -> -4156000 | C75: =C68 -> 363059.45 | D75: =D68 -> 437754.63 | E75: =E68 -> 513131.53 | F75: =F68 -> 537239.56 | G75: =G68+G73 -> 6594859
A77: RETURNS (5-yr hold) | C77: Independent | E77: Sponsor
A78: Levered IRR | C78: =IRR(B75:G75) -> 0.17584602 | E78: 0.4276
A79: Equity Multiple | C79: =SUM(C75:G75)/-B75 -> 2.0322532 | E79: 3
A80: Avg. Cash-on-Cash | C80: =AVERAGE(C68:G68)/-B75 -> 0.11613359 | E80: 0.1186
A81: Unlevered IRR | C81: =IRR(B82:G82) -> 0.12445983 | E81: n/a
A82: Unlevered Equity Cash Flow | B82: =-(B8+B19+B8*E9) -> -9231000 | C82: =C54 -> 792765.97 | D82: =D54 -> 867461.15 | E82: =E54 -> 942838.05 | F82: =F54 -> 966946.09 | G82: =G54+G70*(1-$E$12) -> 11814481
A85: SENSITIVITY — Levered IRR: Exit Cap (rows) × Rent Growth (cols)
A86: Exit Cap ↓ / Rent Growth → | B86: 0.02 | C86: 0.025 | D86: 0.03 | E86: 0.035 | F86: 0.04
A87: 0.0825 | B87: =_xlfn.LET(_xlpm.growth,B$86,_xlpm.xcap,$A87,_xlpm.egibase,$B$24,_xlpm.infl,$B$14,_xlpm.mgmt,$B$16,_xlpm.opexb,$B$50,_xlpm.resv,$B$5*$B$17,_xlpm.dsvc,-PMT($E$7,$E$8,$E$6),_xlpm.equity,$E$13,_xlpm.payoff,$G$63,_xlpm.sellc,$E$12,_xlpm.inca,_xlpm.egibase*(1+_xlpm.growth)^1+$C$46,_xlpm.incb,_xlpm.egibase*(1+_xlpm.growth)^2+$D$46,_xlpm.incc,_xlpm.egibase*(1+_xlpm.growth)^3+$E$46,_xlpm.incd,_xlpm.egibase*(1+_xlpm.growth)^4+$F$46,_xlpm.ince,_xlpm.egibase*(1+_xlpm.growth)^5+$G$46,_xlpm.noia,_xlpm.inca-(_xlpm.opexb*(1+_xlpm.infl)^1+_xlpm.mgmt*_xlpm.inca+_xlpm.resv),_xlpm.noib,_xlpm.incb-(_xlpm.opexb*(1+_xlpm.infl)^2+_xlpm.mgmt*_xlpm.incb+_xlpm.resv),_xlpm.noic,_xlpm.incc-(_xlpm.opexb*(1+_xlpm.infl)^3+_xlpm.mgmt*_xlpm.incc+_xlpm.resv),_xlpm.noid,_xlpm.incd-(_xlpm.opexb*(1+_xlpm.infl)^4+_xlpm.mgmt*_xlpm.incd+_xlpm.resv),_xlpm.noie,_xlpm.ince-(_xlpm.opexb*(1+_xlpm.infl)^5+_xlpm.mgmt*_xlpm.ince+_xlpm.resv),_xlpm.exitv,_xlpm.noie*(1+_xlpm.growth)/_xlpm.xcap,_xlpm.netsale,_xlpm.exitv*(1-_xlpm.sellc)-_xlpm.payoff,IRR(_xlfn.HSTACK(-_xlpm.equity,_xlpm.noia-_xlpm.dsvc,_xlpm.noib-_xlpm.dsvc,_xlpm.noic-_xlpm.dsvc,_xlpm.noid-_xlpm.dsvc,_xlpm.noie-_xlpm.dsvc+_xlpm.netsale))) -> 0.17224843 | C87: =_xlfn.LET(_xlpm.growth,C$86,_xlpm.xcap,$A87,_xlpm.egibase,$B$24,_xlpm.infl,$B$14,_xlpm.mgmt,$B$16,_xlpm.opexb,$B$50,_xlpm.resv,$B$5*$B$17,_xlpm.dsvc,-PMT($E$7,$E$8,$E$6),_xlpm.equity,$E$13,_xlpm.payoff,$G$63,_xlpm.sellc,$E$12,_xlpm.inca,_xlpm.egibase*(1+_xlpm.growth)^1+$C$46,_xlpm.incb,_xlpm.egibase*(1+_xlpm.growth)^2+$D$46,_xlpm.incc,_xlpm.egibase*(1+_xlpm.growth)^3+$E$46,_xlpm.incd,_xlpm.egibase*(1+_xlpm.growth)^4+$F$46,_xlpm.ince,_xlpm.egibase*(1+_xlpm.growth)^5+$G$46,_xlpm.noia,_xlpm.inca-(_xlpm.opexb*(1+_xlpm.infl)^1+_xlpm.mgmt*_xlpm.inca+_xlpm.resv),_xlpm.noib,_xlpm.incb-(_xlpm.opexb*(1+_xlpm.infl)^2+_xlpm.mgmt*_xlpm.incb+_xlpm.resv),_xlpm.noic,_xlpm.incc-(_xlpm.opexb*(1+_xlpm.infl)^3+_xlpm.mgmt*_xlpm.incc+_xlpm.resv),_xlpm.noid,_xlpm.incd-(_xlpm.opexb*(1+_xlpm.infl)^4+_xlpm.mgmt*_xlpm.incd+_xlpm.resv),_xlpm.noie,_xlpm.ince-(_xlpm.opexb*(1+_xlpm.infl)^5+_xlpm.mgmt*_xlpm.ince+_xlpm.resv),_xlpm.exitv,_xlpm.noie*(1+_xlpm.growth)/_xlpm.xcap,_xlpm.netsale,_xlpm.exitv*(1-_xlpm.sellc)-_xlpm.payoff,IRR(_xlfn.HSTACK(-_xlpm.equity,_xlpm.noia-_xlpm.dsvc,_xlpm.noib-_xlpm.dsvc,_xlpm.noic-_xlpm.dsvc,_xlpm.noid-_xlpm.dsvc,_xlpm.noie-_xlpm.dsvc+_xlpm.netsale))) -> 0.192569 | D87: =_xlfn.LET(_xlpm.growth,D$86,_xlpm.xcap,$A87,_xlpm.egibase,$B$24,_xlpm.infl,$B$14,_xlpm.mgmt,$B$16,_xlpm.opexb,$B$50,_xlpm.resv,$B$5*$B$17,_xlpm.dsvc,-PMT($E$7,$E$8,$E$6),_xlpm.equity,$E$13,_xlpm.payoff,$G$63,_xlpm.sellc,$E$12,_xlpm.inca,_xlpm.egibase*(1+_xlpm.growth)^1+$C$46,_xlpm.incb,_xlpm.egibase*(1+_xlpm.growth)^2+$D$46,_xlpm.incc,_xlpm.egibase*(1+_xlpm.growth)^3+$E$46,_xlpm.incd,_xlpm.egibase*(1+_xlpm.growth)^4+$F$46,_xlpm.ince,_xlpm.egibase*(1+_xlpm.growth)^5+$G$46,_xlpm.noia,_xlpm.inca-(_xlpm.opexb*(1+_xlpm.infl)^1+_xlpm.mgmt*_xlpm.inca+_xlpm.resv),_xlpm.noib,_xlpm.incb-(_xlpm.opexb*(1+_xlpm.infl)^2+_xlpm.mgmt*_xlpm.incb+_xlpm.resv),_xlpm.noic,_xlpm.incc-(_xlpm.opexb*(1+_xlpm.infl)^3+_xlpm.mgmt*_xlpm.incc+_xlpm.resv),_xlpm.noid,_xlpm.incd-(_xlpm.opexb*(1+_xlpm.infl)^4+_xlpm.mgmt*_xlpm.incd+_xlpm.resv),_xlpm.noie,_xlpm.ince-(_xlpm.opexb*(1+_xlpm.infl)^5+_xlpm.mgmt*_xlpm.ince+_xlpm.resv),_xlpm.exitv,_xlpm.noie*(1+_xlpm.growth)/_xlpm.xcap,_xlpm.netsale,_xlpm.exitv*(1-_xlpm.sellc)-_xlpm.payoff,IRR(_xlfn.HSTACK(-_xlpm.equity,_xlpm.noia-_xlpm.dsvc,_xlpm.noib-_xlpm.dsvc,_xlpm.noic-_xlpm.dsvc,_xlpm.noid-_xlpm.dsvc,_xlpm.noie-_xlpm.dsvc+_xlpm.netsale))) -> 0.21213983 | E87: =_xlfn.LET(_xlpm.growth,E$86,_xlpm.xcap,$A87,_xlpm.egibase,$B$24,_xlpm.infl,$B$14,_xlpm.mgmt,$B$16,_xlpm.opexb,$B$50,_xlpm.resv,$B$5*$B$17,_xlpm.dsvc,-PMT($E$7,$E$8,$E$6),_xlpm.equity,$E$13,_xlpm.payoff,$G$63,_xlpm.sellc,$E$12,_xlpm.inca,_xlpm.egibase*(1+_xlpm.growth)^1+$C$46,_xlpm.incb,_xlpm.egibase*(1+_xlpm.growth)^2+$D$46,_xlpm.incc,_xlpm.egibase*(1+_xlpm.growth)^3+$E$46,_xlpm.incd,_xlpm.egibase*(1+_xlpm.growth)^4+$F$46,_xlpm.ince,_xlpm.egibase*(1+_xlpm.growth)^5+$G$46,_xlpm.noia,_xlpm.inca-(_xlpm.opexb*(1+_xlpm.infl)^1+_xlpm.mgmt*_xlpm.inca+_xlpm.resv),_xlpm.noib,_xlpm.incb-(_xlpm.opexb*(1+_xlpm.infl)^2+_xlpm.mgmt*_xlpm.incb+_xlpm.resv),_xlpm.noic,_xlpm.incc-(_xlpm.opexb*(1+_xlpm.infl)^3+_xlpm.mgmt*_xlpm.incc+_xlpm.resv),_xlpm.noid,_xlpm.incd-(_xlpm.opexb*(1+_xlpm.infl)^4+_xlpm.mgmt*_xlpm.incd+_xlpm.resv),_xlpm.noie,_xlpm.ince-(_xlpm.opexb*(1+_xlpm.infl)^5+_xlpm.mgmt*_xlpm.ince+_xlpm.resv),_xlpm.exitv,_xlpm.noie*(1+_xlpm.growth)/_xlpm.xcap,_xlpm.netsale,_xlpm.exitv*(1-_xlpm.sellc)-_xlpm.payoff,IRR(_xlfn.HSTACK(-_xlpm.equity,_xlpm.noia-_xlpm.dsvc,_xlpm.noib-_xlpm.dsvc,_xlpm.noic-_xlpm.dsvc,_xlpm.noid-_xlpm.dsvc,_xlpm.noie-_xlpm.dsvc+_xlpm.netsale))) -> 0.23104753 | F87: =_xlfn.LET(_xlpm.growth,F$86,_xlpm.xcap,$A87,_xlpm.egibase,$B$24,_xlpm.infl,$B$14,_xlpm.mgmt,$B$16,_xlpm.opexb,$B$50,_xlpm.resv,$B$5*$B$17,_xlpm.dsvc,-PMT($E$7,$E$8,$E$6),_xlpm.equity,$E$13,_xlpm.payoff,$G$63,_xlpm.sellc,$E$12,_xlpm.inca,_xlpm.egibase*(1+_xlpm.growth)^1+$C$46,_xlpm.incb,_xlpm.egibase*(1+_xlpm.growth)^2+$D$46,_xlpm.incc,_xlpm.egibase*(1+_xlpm.growth)^3+$E$46,_xlpm.incd,_xlpm.egibase*(1+_xlpm.growth)^4+$F$46,_xlpm.ince,_xlpm.egibase*(1+_xlpm.growth)^5+$G$46,_xlpm.noia,_xlpm.inca-(_xlpm.opexb*(1+_xlpm.infl)^1+_xlpm.mgmt*_xlpm.inca+_xlpm.resv),_xlpm.noib,_xlpm.incb-(_xlpm.opexb*(1+_xlpm.infl)^2+_xlpm.mgmt*_xlpm.incb+_xlpm.resv),_xlpm.noic,_xlpm.incc-(_xlpm.opexb*(1+_xlpm.infl)^3+_xlpm.mgmt*_xlpm.incc+_xlpm.resv),_xlpm.noid,_xlpm.incd-(_xlpm.opexb*(1+_xlpm.infl)^4+_xlpm.mgmt*_xlpm.incd+_xlpm.resv),_xlpm.noie,_xlpm.ince-(_xlpm.opexb*(1+_xlpm.infl)^5+_xlpm.mgmt*_xlpm.ince+_xlpm.resv),_xlpm.exitv,_xlpm.noie*(1+_xlpm.growth)/_xlpm.xcap,_xlpm.netsale,_xlpm.exitv*(1-_xlpm.sellc)-_xlpm.payoff,IRR(_xlfn.HSTACK(-_xlpm.equity,_xlpm.noia-_xlpm.dsvc,_xlpm.noib-_xlpm.dsvc,_xlpm.noic-_xlpm.dsvc,_xlpm.noid-_xlpm.dsvc,_xlpm.noie-_xlpm.dsvc+_xlpm.netsale))) -> 0.24936448
A88: 0.0875 | B88: =_xlfn.LET(_xlpm.growth,B$86,_xlpm.xcap,$A88,_xlpm.egibase,$B$24,_xlpm.infl,$B$14,_xlpm.mgmt,$B$16,_xlpm.opexb,$B$50,_xlpm.resv,$B$5*$B$17,_xlpm.dsvc,-PMT($E$7,$E$8,$E$6),_xlpm.equity,$E$13,_xlpm.payoff,$G$63,_xlpm.sellc,$E$12,_xlpm.inca,_xlpm.egibase*(1+_xlpm.growth)^1+$C$46,_xlpm.incb,_xlpm.egibase*(1+_xlpm.growth)^2+$D$46,_xlpm.incc,_xlpm.egibase*(1+_xlpm.growth)^3+$E$46,_xlpm.incd,_xlpm.egibase*(1+_xlpm.growth)^4+$F$46,_xlpm.ince,_xlpm.egibase*(1+_xlpm.growth)^5+$G$46,_xlpm.noia,_xlpm.inca-(_xlpm.opexb*(1+_xlpm.infl)^1+_xlpm.mgmt*_xlpm.inca+_xlpm.resv),_xlpm.noib,_xlpm.incb-(_xlpm.opexb*(1+_xlpm.infl)^2+_xlpm.mgmt*_xlpm.incb+_xlpm.resv),_xlpm.noic,_xlpm.incc-(_xlpm.opexb*(1+_xlpm.infl)^3+_xlpm.mgmt*_xlpm.incc+_xlpm.resv),_xlpm.noid,_xlpm.incd-(_xlpm.opexb*(1+_xlpm.infl)^4+_xlpm.mgmt*_xlpm.incd+_xlpm.resv),_xlpm.noie,_xlpm.ince-(_xlpm.opexb*(1+_xlpm.infl)^5+_xlpm.mgmt*_xlpm.ince+_xlpm.resv),_xlpm.exitv,_xlpm.noie*(1+_xlpm.growth)/_xlpm.xcap,_xlpm.netsale,_xlpm.exitv*(1-_xlpm.sellc)-_xlpm.payoff,IRR(_xlfn.HSTACK(-_xlpm.equity,_xlpm.noia-_xlpm.dsvc,_xlpm.noib-_xlpm.dsvc,_xlpm.noic-_xlpm.dsvc,_xlpm.noid-_xlpm.dsvc,_xlpm.noie-_xlpm.dsvc+_xlpm.netsale))) -> 0.15294372 | C88: =_xlfn.LET(_xlpm.growth,C$86,_xlpm.xcap,$A88,_xlpm.egibase,$B$24,_xlpm.infl,$B$14,_xlpm.mgmt,$B$16,_xlpm.opexb,$B$50,_xlpm.resv,$B$5*$B$17,_xlpm.dsvc,-PMT($E$7,$E$8,$E$6),_xlpm.equity,$E$13,_xlpm.payoff,$G$63,_xlpm.sellc,$E$12,_xlpm.inca,_xlpm.egibase*(1+_xlpm.growth)^1+$C$46,_xlpm.incb,_xlpm.egibase*(1+_xlpm.growth)^2+$D$46,_xlpm.incc,_xlpm.egibase*(1+_xlpm.growth)^3+$E$46,_xlpm.incd,_xlpm.egibase*(1+_xlpm.growth)^4+$F$46,_xlpm.ince,_xlpm.egibase*(1+_xlpm.growth)^5+$G$46,_xlpm.noia,_xlpm.inca-(_xlpm.opexb*(1+_xlpm.infl)^1+_xlpm.mgmt*_xlpm.inca+_xlpm.resv),_xlpm.noib,_xlpm.incb-(_xlpm.opexb*(1+_xlpm.infl)^2+_xlpm.mgmt*_xlpm.incb+_xlpm.resv),_xlpm.noic,_xlpm.incc-(_xlpm.opexb*(1+_xlpm.infl)^3+_xlpm.mgmt*_xlpm.incc+_xlpm.resv),_xlpm.noid,_xlpm.incd-(_xlpm.opexb*(1+_xlpm.infl)^4+_xlpm.mgmt*_xlpm.incd+_xlpm.resv),_xlpm.noie,_xlpm.ince-(_xlpm.opexb*(1+_xlpm.infl)^5+_xlpm.mgmt*_xlpm.ince+_xlpm.resv),_xlpm.exitv,_xlpm.noie*(1+_xlpm.growth)/_xlpm.xcap,_xlpm.netsale,_xlpm.exitv*(1-_xlpm.sellc)-_xlpm.payoff,IRR(_xlfn.HSTACK(-_xlpm.equity,_xlpm.noia-_xlpm.dsvc,_xlpm.noib-_xlpm.dsvc,_xlpm.noic-_xlpm.dsvc,_xlpm.noid-_xlpm.dsvc,_xlpm.noie-_xlpm.dsvc+_xlpm.netsale))) -> 0.17365306 | D88: =_xlfn.LET(_xlpm.growth,D$86,_xlpm.xcap,$A88,_xlpm.egibase,$B$24,_xlpm.infl,$B$14,_xlpm.mgmt,$B$16,_xlpm.opexb,$B$50,_xlpm.resv,$B$5*$B$17,_xlpm.dsvc,-PMT($E$7,$E$8,$E$6),_xlpm.equity,$E$13,_xlpm.payoff,$G$63,_xlpm.sellc,$E$12,_xlpm.inca,_xlpm.egibase*(1+_xlpm.growth)^1+$C$46,_xlpm.incb,_xlpm.egibase*(1+_xlpm.growth)^2+$D$46,_xlpm.incc,_xlpm.egibase*(1+_xlpm.growth)^3+$E$46,_xlpm.incd,_xlpm.egibase*(1+_xlpm.growth)^4+$F$46,_xlpm.ince,_xlpm.egibase*(1+_xlpm.growth)^5+$G$46,_xlpm.noia,_xlpm.inca-(_xlpm.opexb*(1+_xlpm.infl)^1+_xlpm.mgmt*_xlpm.inca+_xlpm.resv),_xlpm.noib,_xlpm.incb-(_xlpm.opexb*(1+_xlpm.infl)^2+_xlpm.mgmt*_xlpm.incb+_xlpm.resv),_xlpm.noic,_xlpm.incc-(_xlpm.opexb*(1+_xlpm.infl)^3+_xlpm.mgmt*_xlpm.incc+_xlpm.resv),_xlpm.noid,_xlpm.incd-(_xlpm.opexb*(1+_xlpm.infl)^4+_xlpm.mgmt*_xlpm.incd+_xlpm.resv),_xlpm.noie,_xlpm.ince-(_xlpm.opexb*(1+_xlpm.infl)^5+_xlpm.mgmt*_xlpm.ince+_xlpm.resv),_xlpm.exitv,_xlpm.noie*(1+_xlpm.growth)/_xlpm.xcap,_xlpm.netsale,_xlpm.exitv*(1-_xlpm.sellc)-_xlpm.payoff,IRR(_xlfn.HSTACK(-_xlpm.equity,_xlpm.noia-_xlpm.dsvc,_xlpm.noib-_xlpm.dsvc,_xlpm.noic-_xlpm.dsvc,_xlpm.noid-_xlpm.dsvc,_xlpm.noie-_xlpm.dsvc+_xlpm.netsale))) -> 0.19355271 | E88: =_xlfn.LET(_xlpm.growth,E$86,_xlpm.xcap,$A88,_xlpm.egibase,$B$24,_xlpm.infl,$B$14,_xlpm.mgmt,$B$16,_xlpm.opexb,$B$50,_xlpm.resv,$B$5*$B$17,_xlpm.dsvc,-PMT($E$7,$E$8,$E$6),_xlpm.equity,$E$13,_xlpm.payoff,$G$63,_xlpm.sellc,$E$12,_xlpm.inca,_xlpm.egibase*(1+_xlpm.growth)^1+$C$46,_xlpm.incb,_xlpm.egibase*(1+_xlpm.growth)^2+$D$46,_xlpm.incc,_xlpm.egibase*(1+_xlpm.growth)^3+$E$46,_xlpm.incd,_xlpm.egibase*(1+_xlpm.growth)^4+$F$46,_xlpm.ince,_xlpm.egibase*(1+_xlpm.growth)^5+$G$46,_xlpm.noia,_xlpm.inca-(_xlpm.opexb*(1+_xlpm.infl)^1+_xlpm.mgmt*_xlpm.inca+_xlpm.resv),_xlpm.noib,_xlpm.incb-(_xlpm.opexb*(1+_xlpm.infl)^2+_xlpm.mgmt*_xlpm.incb+_xlpm.resv),_xlpm.noic,_xlpm.incc-(_xlpm.opexb*(1+_xlpm.infl)^3+_xlpm.mgmt*_xlpm.incc+_xlpm.resv),_xlpm.noid,_xlpm.incd-(_xlpm.opexb*(1+_xlpm.infl)^4+_xlpm.mgmt*_xlpm.incd+_xlpm.resv),_xlpm.noie,_xlpm.ince-(_xlpm.opexb*(1+_xlpm.infl)^5+_xlpm.mgmt*_xlpm.ince+_xlpm.resv),_xlpm.exitv,_xlpm.noie*(1+_xlpm.growth)/_xlpm.xcap,_xlpm.netsale,_xlpm.exitv*(1-_xlpm.sellc)-_xlpm.payoff,IRR(_xlfn.HSTACK(-_xlpm.equity,_xlpm.noia-_xlpm.dsvc,_xlpm.noib-_xlpm.dsvc,_xlpm.noic-_xlpm.dsvc,_xlpm.noid-_xlpm.dsvc,_xlpm.noie-_xlpm.dsvc+_xlpm.netsale))) -> 0.21273992 | F88: =_xlfn.LET(_xlpm.growth,F$86,_xlpm.xcap,$A88,_xlpm.egibase,$B$24,_xlpm.infl,$B$14,_xlpm.mgmt,$B$16,_xlpm.opexb,$B$50,_xlpm.resv,$B$5*$B$17,_xlpm.dsvc,-PMT($E$7,$E$8,$E$6),_xlpm.equity,$E$13,_xlpm.payoff,$G$63,_xlpm.sellc,$E$12,_xlpm.inca,_xlpm.egibase*(1+_xlpm.growth)^1+$C$46,_xlpm.incb,_xlpm.egibase*(1+_xlpm.growth)^2+$D$46,_xlpm.incc,_xlpm.egibase*(1+_xlpm.growth)^3+$E$46,_xlpm.incd,_xlpm.egibase*(1+_xlpm.growth)^4+$F$46,_xlpm.ince,_xlpm.egibase*(1+_xlpm.growth)^5+$G$46,_xlpm.noia,_xlpm.inca-(_xlpm.opexb*(1+_xlpm.infl)^1+_xlpm.mgmt*_xlpm.inca+_xlpm.resv),_xlpm.noib,_xlpm.incb-(_xlpm.opexb*(1+_xlpm.infl)^2+_xlpm.mgmt*_xlpm.incb+_xlpm.resv),_xlpm.noic,_xlpm.incc-(_xlpm.opexb*(1+_xlpm.infl)^3+_xlpm.mgmt*_xlpm.incc+_xlpm.resv),_xlpm.noid,_xlpm.incd-(_xlpm.opexb*(1+_xlpm.infl)^4+_xlpm.mgmt*_xlpm.incd+_xlpm.resv),_xlpm.noie,_xlpm.ince-(_xlpm.opexb*(1+_xlpm.infl)^5+_xlpm.mgmt*_xlpm.ince+_xlpm.resv),_xlpm.exitv,_xlpm.noie*(1+_xlpm.growth)/_xlpm.xcap,_xlpm.netsale,_xlpm.exitv*(1-_xlpm.sellc)-_xlpm.payoff,IRR(_xlfn.HSTACK(-_xlpm.equity,_xlpm.noia-_xlpm.dsvc,_xlpm.noib-_xlpm.dsvc,_xlpm.noic-_xlpm.dsvc,_xlpm.noid-_xlpm.dsvc,_xlpm.noie-_xlpm.dsvc+_xlpm.netsale))) -> 0.23129529
A89: 0.0925 | B89: =_xlfn.LET(_xlpm.growth,B$86,_xlpm.xcap,$A89,_xlpm.egibase,$B$24,_xlpm.infl,$B$14,_xlpm.mgmt,$B$16,_xlpm.opexb,$B$50,_xlpm.resv,$B$5*$B$17,_xlpm.dsvc,-PMT($E$7,$E$8,$E$6),_xlpm.equity,$E$13,_xlpm.payoff,$G$63,_xlpm.sellc,$E$12,_xlpm.inca,_xlpm.egibase*(1+_xlpm.growth)^1+$C$46,_xlpm.incb,_xlpm.egibase*(1+_xlpm.growth)^2+$D$46,_xlpm.incc,_xlpm.egibase*(1+_xlpm.growth)^3+$E$46,_xlpm.incd,_xlpm.egibase*(1+_xlpm.growth)^4+$F$46,_xlpm.ince,_xlpm.egibase*(1+_xlpm.growth)^5+$G$46,_xlpm.noia,_xlpm.inca-(_xlpm.opexb*(1+_xlpm.infl)^1+_xlpm.mgmt*_xlpm.inca+_xlpm.resv),_xlpm.noib,_xlpm.incb-(_xlpm.opexb*(1+_xlpm.infl)^2+_xlpm.mgmt*_xlpm.incb+_xlpm.resv),_xlpm.noic,_xlpm.incc-(_xlpm.opexb*(1+_xlpm.infl)^3+_xlpm.mgmt*_xlpm.incc+_xlpm.resv),_xlpm.noid,_xlpm.incd-(_xlpm.opexb*(1+_xlpm.infl)^4+_xlpm.mgmt*_xlpm.incd+_xlpm.resv),_xlpm.noie,_xlpm.ince-(_xlpm.opexb*(1+_xlpm.infl)^5+_xlpm.mgmt*_xlpm.ince+_xlpm.resv),_xlpm.exitv,_xlpm.noie*(1+_xlpm.growth)/_xlpm.xcap,_xlpm.netsale,_xlpm.exitv*(1-_xlpm.sellc)-_xlpm.payoff,IRR(_xlfn.HSTACK(-_xlpm.equity,_xlpm.noia-_xlpm.dsvc,_xlpm.noib-_xlpm.dsvc,_xlpm.noic-_xlpm.dsvc,_xlpm.noid-_xlpm.dsvc,_xlpm.noie-_xlpm.dsvc+_xlpm.netsale))) -> 0.13445878 | C89: =_xlfn.LET(_xlpm.growth,C$86,_xlpm.xcap,$A89,_xlpm.egibase,$B$24,_xlpm.infl,$B$14,_xlpm.mgmt,$B$16,_xlpm.opexb,$B$50,_xlpm.resv,$B$5*$B$17,_xlpm.dsvc,-PMT($E$7,$E$8,$E$6),_xlpm.equity,$E$13,_xlpm.payoff,$G$63,_xlpm.sellc,$E$12,_xlpm.inca,_xlpm.egibase*(1+_xlpm.growth)^1+$C$46,_xlpm.incb,_xlpm.egibase*(1+_xlpm.growth)^2+$D$46,_xlpm.incc,_xlpm.egibase*(1+_xlpm.growth)^3+$E$46,_xlpm.incd,_xlpm.egibase*(1+_xlpm.growth)^4+$F$46,_xlpm.ince,_xlpm.egibase*(1+_xlpm.growth)^5+$G$46,_xlpm.noia,_xlpm.inca-(_xlpm.opexb*(1+_xlpm.infl)^1+_xlpm.mgmt*_xlpm.inca+_xlpm.resv),_xlpm.noib,_xlpm.incb-(_xlpm.opexb*(1+_xlpm.infl)^2+_xlpm.mgmt*_xlpm.incb+_xlpm.resv),_xlpm.noic,_xlpm.incc-(_xlpm.opexb*(1+_xlpm.infl)^3+_xlpm.mgmt*_xlpm.incc+_xlpm.resv),_xlpm.noid,_xlpm.incd-(_xlpm.opexb*(1+_xlpm.infl)^4+_xlpm.mgmt*_xlpm.incd+_xlpm.resv),_xlpm.noie,_xlpm.ince-(_xlpm.opexb*(1+_xlpm.infl)^5+_xlpm.mgmt*_xlpm.ince+_xlpm.resv),_xlpm.exitv,_xlpm.noie*(1+_xlpm.growth)/_xlpm.xcap,_xlpm.netsale,_xlpm.exitv*(1-_xlpm.sellc)-_xlpm.payoff,IRR(_xlfn.HSTACK(-_xlpm.equity,_xlpm.noia-_xlpm.dsvc,_xlpm.noib-_xlpm.dsvc,_xlpm.noic-_xlpm.dsvc,_xlpm.noid-_xlpm.dsvc,_xlpm.noie-_xlpm.dsvc+_xlpm.netsale))) -> 0.15559017 | D89: =_xlfn.LET(_xlpm.growth,D$86,_xlpm.xcap,$A89,_xlpm.egibase,$B$24,_xlpm.infl,$B$14,_xlpm.mgmt,$B$16,_xlpm.opexb,$B$50,_xlpm.resv,$B$5*$B$17,_xlpm.dsvc,-PMT($E$7,$E$8,$E$6),_xlpm.equity,$E$13,_xlpm.payoff,$G$63,_xlpm.sellc,$E$12,_xlpm.inca,_xlpm.egibase*(1+_xlpm.growth)^1+$C$46,_xlpm.incb,_xlpm.egibase*(1+_xlpm.growth)^2+$D$46,_xlpm.incc,_xlpm.egibase*(1+_xlpm.growth)^3+$E$46,_xlpm.incd,_xlpm.egibase*(1+_xlpm.growth)^4+$F$46,_xlpm.ince,_xlpm.egibase*(1+_xlpm.growth)^5+$G$46,_xlpm.noia,_xlpm.inca-(_xlpm.opexb*(1+_xlpm.infl)^1+_xlpm.mgmt*_xlpm.inca+_xlpm.resv),_xlpm.noib,_xlpm.incb-(_xlpm.opexb*(1+_xlpm.infl)^2+_xlpm.mgmt*_xlpm.incb+_xlpm.resv),_xlpm.noic,_xlpm.incc-(_xlpm.opexb*(1+_xlpm.infl)^3+_xlpm.mgmt*_xlpm.incc+_xlpm.resv),_xlpm.noid,_xlpm.incd-(_xlpm.opexb*(1+_xlpm.infl)^4+_xlpm.mgmt*_xlpm.incd+_xlpm.resv),_xlpm.noie,_xlpm.ince-(_xlpm.opexb*(1+_xlpm.infl)^5+_xlpm.mgmt*_xlpm.ince+_xlpm.resv),_xlpm.exitv,_xlpm.noie*(1+_xlpm.growth)/_xlpm.xcap,_xlpm.netsale,_xlpm.exitv*(1-_xlpm.sellc)-_xlpm.payoff,IRR(_xlfn.HSTACK(-_xlpm.equity,_xlpm.noia-_xlpm.dsvc,_xlpm.noib-_xlpm.dsvc,_xlpm.noic-_xlpm.dsvc,_xlpm.noid-_xlpm.dsvc,_xlpm.noie-_xlpm.dsvc+_xlpm.netsale))) -> 0.17584602 | E89: =_xlfn.LET(_xlpm.growth,E$86,_xlpm.xcap,$A89,_xlpm.egibase,$B$24,_xlpm.infl,$B$14,_xlpm.mgmt,$B$16,_xlpm.opexb,$B$50,_xlpm.resv,$B$5*$B$17,_xlpm.dsvc,-PMT($E$7,$E$8,$E$6),_xlpm.equity,$E$13,_xlpm.payoff,$G$63,_xlpm.sellc,$E$12,_xlpm.inca,_xlpm.egibase*(1+_xlpm.growth)^1+$C$46,_xlpm.incb,_xlpm.egibase*(1+_xlpm.growth)^2+$D$46,_xlpm.incc,_xlpm.egibase*(1+_xlpm.growth)^3+$E$46,_xlpm.incd,_xlpm.egibase*(1+_xlpm.growth)^4+$F$46,_xlpm.ince,_xlpm.egibase*(1+_xlpm.growth)^5+$G$46,_xlpm.noia,_xlpm.inca-(_xlpm.opexb*(1+_xlpm.infl)^1+_xlpm.mgmt*_xlpm.inca+_xlpm.resv),_xlpm.noib,_xlpm.incb-(_xlpm.opexb*(1+_xlpm.infl)^2+_xlpm.mgmt*_xlpm.incb+_xlpm.resv),_xlpm.noic,_xlpm.incc-(_xlpm.opexb*(1+_xlpm.infl)^3+_xlpm.mgmt*_xlpm.incc+_xlpm.resv),_xlpm.noid,_xlpm.incd-(_xlpm.opexb*(1+_xlpm.infl)^4+_xlpm.mgmt*_xlpm.incd+_xlpm.resv),_xlpm.noie,_xlpm.ince-(_xlpm.opexb*(1+_xlpm.infl)^5+_xlpm.mgmt*_xlpm.ince+_xlpm.resv),_xlpm.exitv,_xlpm.noie*(1+_xlpm.growth)/_xlpm.xcap,_xlpm.netsale,_xlpm.exitv*(1-_xlpm.sellc)-_xlpm.payoff,IRR(_xlfn.HSTACK(-_xlpm.equity,_xlpm.noia-_xlpm.dsvc,_xlpm.noib-_xlpm.dsvc,_xlpm.noic-_xlpm.dsvc,_xlpm.noid-_xlpm.dsvc,_xlpm.noie-_xlpm.dsvc+_xlpm.netsale))) -> 0.19533566 | F89: =_xlfn.LET(_xlpm.growth,F$86,_xlpm.xcap,$A89,_xlpm.egibase,$B$24,_xlpm.infl,$B$14,_xlpm.mgmt,$B$16,_xlpm.opexb,$B$50,_xlpm.resv,$B$5*$B$17,_xlpm.dsvc,-PMT($E$7,$E$8,$E$6),_xlpm.equity,$E$13,_xlpm.payoff,$G$63,_xlpm.sellc,$E$12,_xlpm.inca,_xlpm.egibase*(1+_xlpm.growth)^1+$C$46,_xlpm.incb,_xlpm.egibase*(1+_xlpm.growth)^2+$D$46,_xlpm.incc,_xlpm.egibase*(1+_xlpm.growth)^3+$E$46,_xlpm.incd,_xlpm.egibase*(1+_xlpm.growth)^4+$F$46,_xlpm.ince,_xlpm.egibase*(1+_xlpm.growth)^5+$G$46,_xlpm.noia,_xlpm.inca-(_xlpm.opexb*(1+_xlpm.infl)^1+_xlpm.mgmt*_xlpm.inca+_xlpm.resv),_xlpm.noib,_xlpm.incb-(_xlpm.opexb*(1+_xlpm.infl)^2+_xlpm.mgmt*_xlpm.incb+_xlpm.resv),_xlpm.noic,_xlpm.incc-(_xlpm.opexb*(1+_xlpm.infl)^3+_xlpm.mgmt*_xlpm.incc+_xlpm.resv),_xlpm.noid,_xlpm.incd-(_xlpm.opexb*(1+_xlpm.infl)^4+_xlpm.mgmt*_xlpm.incd+_xlpm.resv),_xlpm.noie,_xlpm.ince-(_xlpm.opexb*(1+_xlpm.infl)^5+_xlpm.mgmt*_xlpm.ince+_xlpm.resv),_xlpm.exitv,_xlpm.noie*(1+_xlpm.growth)/_xlpm.xcap,_xlpm.netsale,_xlpm.exitv*(1-_xlpm.sellc)-_xlpm.payoff,IRR(_xlfn.HSTACK(-_xlpm.equity,_xlpm.noia-_xlpm.dsvc,_xlpm.noib-_xlpm.dsvc,_xlpm.noic-_xlpm.dsvc,_xlpm.noid-_xlpm.dsvc,_xlpm.noie-_xlpm.dsvc+_xlpm.netsale))) -> 0.21414903
A90: 0.0975 | B90: =_xlfn.LET(_xlpm.growth,B$86,_xlpm.xcap,$A90,_xlpm.egibase,$B$24,_xlpm.infl,$B$14,_xlpm.mgmt,$B$16,_xlpm.opexb,$B$50,_xlpm.resv,$B$5*$B$17,_xlpm.dsvc,-PMT($E$7,$E$8,$E$6),_xlpm.equity,$E$13,_xlpm.payoff,$G$63,_xlpm.sellc,$E$12,_xlpm.inca,_xlpm.egibase*(1+_xlpm.growth)^1+$C$46,_xlpm.incb,_xlpm.egibase*(1+_xlpm.growth)^2+$D$46,_xlpm.incc,_xlpm.egibase*(1+_xlpm.growth)^3+$E$46,_xlpm.incd,_xlpm.egibase*(1+_xlpm.growth)^4+$F$46,_xlpm.ince,_xlpm.egibase*(1+_xlpm.growth)^5+$G$46,_xlpm.noia,_xlpm.inca-(_xlpm.opexb*(1+_xlpm.infl)^1+_xlpm.mgmt*_xlpm.inca+_xlpm.resv),_xlpm.noib,_xlpm.incb-(_xlpm.opexb*(1+_xlpm.infl)^2+_xlpm.mgmt*_xlpm.incb+_xlpm.resv),_xlpm.noic,_xlpm.incc-(_xlpm.opexb*(1+_xlpm.infl)^3+_xlpm.mgmt*_xlpm.incc+_xlpm.resv),_xlpm.noid,_xlpm.incd-(_xlpm.opexb*(1+_xlpm.infl)^4+_xlpm.mgmt*_xlpm.incd+_xlpm.resv),_xlpm.noie,_xlpm.ince-(_xlpm.opexb*(1+_xlpm.infl)^5+_xlpm.mgmt*_xlpm.ince+_xlpm.resv),_xlpm.exitv,_xlpm.noie*(1+_xlpm.growth)/_xlpm.xcap,_xlpm.netsale,_xlpm.exitv*(1-_xlpm.sellc)-_xlpm.payoff,IRR(_xlfn.HSTACK(-_xlpm.equity,_xlpm.noia-_xlpm.dsvc,_xlpm.noib-_xlpm.dsvc,_xlpm.noic-_xlpm.dsvc,_xlpm.noid-_xlpm.dsvc,_xlpm.noie-_xlpm.dsvc+_xlpm.netsale))) -> 0.11667546 | C90: =_xlfn.LET(_xlpm.growth,C$86,_xlpm.xcap,$A90,_xlpm.egibase,$B$24,_xlpm.infl,$B$14,_xlpm.mgmt,$B$16,_xlpm.opexb,$B$50,_xlpm.resv,$B$5*$B$17,_xlpm.dsvc,-PMT($E$7,$E$8,$E$6),_xlpm.equity,$E$13,_xlpm.payoff,$G$63,_xlpm.sellc,$E$12,_xlpm.inca,_xlpm.egibase*(1+_xlpm.growth)^1+$C$46,_xlpm.incb,_xlpm.egibase*(1+_xlpm.growth)^2+$D$46,_xlpm.incc,_xlpm.egibase*(1+_xlpm.growth)^3+$E$46,_xlpm.incd,_xlpm.egibase*(1+_xlpm.growth)^4+$F$46,_xlpm.ince,_xlpm.egibase*(1+_xlpm.growth)^5+$G$46,_xlpm.noia,_xlpm.inca-(_xlpm.opexb*(1+_xlpm.infl)^1+_xlpm.mgmt*_xlpm.inca+_xlpm.resv),_xlpm.noib,_xlpm.incb-(_xlpm.opexb*(1+_xlpm.infl)^2+_xlpm.mgmt*_xlpm.incb+_xlpm.resv),_xlpm.noic,_xlpm.incc-(_xlpm.opexb*(1+_xlpm.infl)^3+_xlpm.mgmt*_xlpm.incc+_xlpm.resv),_xlpm.noid,_xlpm.incd-(_xlpm.opexb*(1+_xlpm.infl)^4+_xlpm.mgmt*_xlpm.incd+_xlpm.resv),_xlpm.noie,_xlpm.ince-(_xlpm.opexb*(1+_xlpm.infl)^5+_xlpm.mgmt*_xlpm.ince+_xlpm.resv),_xlpm.exitv,_xlpm.noie*(1+_xlpm.growth)/_xlpm.xcap,_xlpm.netsale,_xlpm.exitv*(1-_xlpm.sellc)-_xlpm.payoff,IRR(_xlfn.HSTACK(-_xlpm.equity,_xlpm.noia-_xlpm.dsvc,_xlpm.noib-_xlpm.dsvc,_xlpm.noic-_xlpm.dsvc,_xlpm.noid-_xlpm.dsvc,_xlpm.noie-_xlpm.dsvc+_xlpm.netsale))) -> 0.13826389 | D90: =_xlfn.LET(_xlpm.growth,D$86,_xlpm.xcap,$A90,_xlpm.egibase,$B$24,_xlpm.infl,$B$14,_xlpm.mgmt,$B$16,_xlpm.opexb,$B$50,_xlpm.resv,$B$5*$B$17,_xlpm.dsvc,-PMT($E$7,$E$8,$E$6),_xlpm.equity,$E$13,_xlpm.payoff,$G$63,_xlpm.sellc,$E$12,_xlpm.inca,_xlpm.egibase*(1+_xlpm.growth)^1+$C$46,_xlpm.incb,_xlpm.egibase*(1+_xlpm.growth)^2+$D$46,_xlpm.incc,_xlpm.egibase*(1+_xlpm.growth)^3+$E$46,_xlpm.incd,_xlpm.egibase*(1+_xlpm.growth)^4+$F$46,_xlpm.ince,_xlpm.egibase*(1+_xlpm.growth)^5+$G$46,_xlpm.noia,_xlpm.inca-(_xlpm.opexb*(1+_xlpm.infl)^1+_xlpm.mgmt*_xlpm.inca+_xlpm.resv),_xlpm.noib,_xlpm.incb-(_xlpm.opexb*(1+_xlpm.infl)^2+_xlpm.mgmt*_xlpm.incb+_xlpm.resv),_xlpm.noic,_xlpm.incc-(_xlpm.opexb*(1+_xlpm.infl)^3+_xlpm.mgmt*_xlpm.incc+_xlpm.resv),_xlpm.noid,_xlpm.incd-(_xlpm.opexb*(1+_xlpm.infl)^4+_xlpm.mgmt*_xlpm.incd+_xlpm.resv),_xlpm.noie,_xlpm.ince-(_xlpm.opexb*(1+_xlpm.infl)^5+_xlpm.mgmt*_xlpm.ince+_xlpm.resv),_xlpm.exitv,_xlpm.noie*(1+_xlpm.growth)/_xlpm.xcap,_xlpm.netsale,_xlpm.exitv*(1-_xlpm.sellc)-_xlpm.payoff,IRR(_xlfn.HSTACK(-_xlpm.equity,_xlpm.noia-_xlpm.dsvc,_xlpm.noib-_xlpm.dsvc,_xlpm.noic-_xlpm.dsvc,_xlpm.noid-_xlpm.dsvc,_xlpm.noie-_xlpm.dsvc+_xlpm.netsale))) -> 0.15890419 | E90: =_xlfn.LET(_xlpm.growth,E$86,_xlpm.xcap,$A90,_xlpm.egibase,$B$24,_xlpm.infl,$B$14,_xlpm.mgmt,$B$16,_xlpm.opexb,$B$50,_xlpm.resv,$B$5*$B$17,_xlpm.dsvc,-PMT($E$7,$E$8,$E$6),_xlpm.equity,$E$13,_xlpm.payoff,$G$63,_xlpm.sellc,$E$12,_xlpm.inca,_xlpm.egibase*(1+_xlpm.growth)^1+$C$46,_xlpm.incb,_xlpm.egibase*(1+_xlpm.growth)^2+$D$46,_xlpm.incc,_xlpm.egibase*(1+_xlpm.growth)^3+$E$46,_xlpm.incd,_xlpm.egibase*(1+_xlpm.growth)^4+$F$46,_xlpm.ince,_xlpm.egibase*(1+_xlpm.growth)^5+$G$46,_xlpm.noia,_xlpm.inca-(_xlpm.opexb*(1+_xlpm.infl)^1+_xlpm.mgmt*_xlpm.inca+_xlpm.resv),_xlpm.noib,_xlpm.incb-(_xlpm.opexb*(1+_xlpm.infl)^2+_xlpm.mgmt*_xlpm.incb+_xlpm.resv),_xlpm.noic,_xlpm.incc-(_xlpm.opexb*(1+_xlpm.infl)^3+_xlpm.mgmt*_xlpm.incc+_xlpm.resv),_xlpm.noid,_xlpm.incd-(_xlpm.opexb*(1+_xlpm.infl)^4+_xlpm.mgmt*_xlpm.incd+_xlpm.resv),_xlpm.noie,_xlpm.ince-(_xlpm.opexb*(1+_xlpm.infl)^5+_xlpm.mgmt*_xlpm.ince+_xlpm.resv),_xlpm.exitv,_xlpm.noie*(1+_xlpm.growth)/_xlpm.xcap,_xlpm.netsale,_xlpm.exitv*(1-_xlpm.sellc)-_xlpm.payoff,IRR(_xlfn.HSTACK(-_xlpm.equity,_xlpm.noia-_xlpm.dsvc,_xlpm.noib-_xlpm.dsvc,_xlpm.noic-_xlpm.dsvc,_xlpm.noid-_xlpm.dsvc,_xlpm.noie-_xlpm.dsvc+_xlpm.netsale))) -> 0.1787196 | F90: =_xlfn.LET(_xlpm.growth,F$86,_xlpm.xcap,$A90,_xlpm.egibase,$B$24,_xlpm.infl,$B$14,_xlpm.mgmt,$B$16,_xlpm.opexb,$B$50,_xlpm.resv,$B$5*$B$17,_xlpm.dsvc,-PMT($E$7,$E$8,$E$6),_xlpm.equity,$E$13,_xlpm.payoff,$G$63,_xlpm.sellc,$E$12,_xlpm.inca,_xlpm.egibase*(1+_xlpm.growth)^1+$C$46,_xlpm.incb,_xlpm.egibase*(1+_xlpm.growth)^2+$D$46,_xlpm.incc,_xlpm.egibase*(1+_xlpm.growth)^3+$E$46,_xlpm.incd,_xlpm.egibase*(1+_xlpm.growth)^4+$F$46,_xlpm.ince,_xlpm.egibase*(1+_xlpm.growth)^5+$G$46,_xlpm.noia,_xlpm.inca-(_xlpm.opexb*(1+_xlpm.infl)^1+_xlpm.mgmt*_xlpm.inca+_xlpm.resv),_xlpm.noib,_xlpm.incb-(_xlpm.opexb*(1+_xlpm.infl)^2+_xlpm.mgmt*_xlpm.incb+_xlpm.resv),_xlpm.noic,_xlpm.incc-(_xlpm.opexb*(1+_xlpm.infl)^3+_xlpm.mgmt*_xlpm.incc+_xlpm.resv),_xlpm.noid,_xlpm.incd-(_xlpm.opexb*(1+_xlpm.infl)^4+_xlpm.mgmt*_xlpm.incd+_xlpm.resv),_xlpm.noie,_xlpm.ince-(_xlpm.opexb*(1+_xlpm.infl)^5+_xlpm.mgmt*_xlpm.ince+_xlpm.resv),_xlpm.exitv,_xlpm.noie*(1+_xlpm.growth)/_xlpm.xcap,_xlpm.netsale,_xlpm.exitv*(1-_xlpm.sellc)-_xlpm.payoff,IRR(_xlfn.HSTACK(-_xlpm.equity,_xlpm.noia-_xlpm.dsvc,_xlpm.noib-_xlpm.dsvc,_xlpm.noic-_xlpm.dsvc,_xlpm.noid-_xlpm.dsvc,_xlpm.noie-_xlpm.dsvc+_xlpm.netsale))) -> 0.19781063
A91: 0.1025 | B91: =_xlfn.LET(_xlpm.growth,B$86,_xlpm.xcap,$A91,_xlpm.egibase,$B$24,_xlpm.infl,$B$14,_xlpm.mgmt,$B$16,_xlpm.opexb,$B$50,_xlpm.resv,$B$5*$B$17,_xlpm.dsvc,-PMT($E$7,$E$8,$E$6),_xlpm.equity,$E$13,_xlpm.payoff,$G$63,_xlpm.sellc,$E$12,_xlpm.inca,_xlpm.egibase*(1+_xlpm.growth)^1+$C$46,_xlpm.incb,_xlpm.egibase*(1+_xlpm.growth)^2+$D$46,_xlpm.incc,_xlpm.egibase*(1+_xlpm.growth)^3+$E$46,_xlpm.incd,_xlpm.egibase*(1+_xlpm.growth)^4+$F$46,_xlpm.ince,_xlpm.egibase*(1+_xlpm.growth)^5+$G$46,_xlpm.noia,_xlpm.inca-(_xlpm.opexb*(1+_xlpm.infl)^1+_xlpm.mgmt*_xlpm.inca+_xlpm.resv),_xlpm.noib,_xlpm.incb-(_xlpm.opexb*(1+_xlpm.infl)^2+_xlpm.mgmt*_xlpm.incb+_xlpm.resv),_xlpm.noic,_xlpm.incc-(_xlpm.opexb*(1+_xlpm.infl)^3+_xlpm.mgmt*_xlpm.incc+_xlpm.resv),_xlpm.noid,_xlpm.incd-(_xlpm.opexb*(1+_xlpm.infl)^4+_xlpm.mgmt*_xlpm.incd+_xlpm.resv),_xlpm.noie,_xlpm.ince-(_xlpm.opexb*(1+_xlpm.infl)^5+_xlpm.mgmt*_xlpm.ince+_xlpm.resv),_xlpm.exitv,_xlpm.noie*(1+_xlpm.growth)/_xlpm.xcap,_xlpm.netsale,_xlpm.exitv*(1-_xlpm.sellc)-_xlpm.payoff,IRR(_xlfn.HSTACK(-_xlpm.equity,_xlpm.noia-_xlpm.dsvc,_xlpm.noib-_xlpm.dsvc,_xlpm.noic-_xlpm.dsvc,_xlpm.noid-_xlpm.dsvc,_xlpm.noie-_xlpm.dsvc+_xlpm.netsale))) -> 0.099491976 | C91: =_xlfn.LET(_xlpm.growth,C$86,_xlpm.xcap,$A91,_xlpm.egibase,$B$24,_xlpm.infl,$B$14,_xlpm.mgmt,$B$16,_xlpm.opexb,$B$50,_xlpm.resv,$B$5*$B$17,_xlpm.dsvc,-PMT($E$7,$E$8,$E$6),_xlpm.equity,$E$13,_xlpm.payoff,$G$63,_xlpm.sellc,$E$12,_xlpm.inca,_xlpm.egibase*(1+_xlpm.growth)^1+$C$46,_xlpm.incb,_xlpm.egibase*(1+_xlpm.growth)^2+$D$46,_xlpm.incc,_xlpm.egibase*(1+_xlpm.growth)^3+$E$46,_xlpm.incd,_xlpm.egibase*(1+_xlpm.growth)^4+$F$46,_xlpm.ince,_xlpm.egibase*(1+_xlpm.growth)^5+$G$46,_xlpm.noia,_xlpm.inca-(_xlpm.opexb*(1+_xlpm.infl)^1+_xlpm.mgmt*_xlpm.inca+_xlpm.resv),_xlpm.noib,_xlpm.incb-(_xlpm.opexb*(1+_xlpm.infl)^2+_xlpm.mgmt*_xlpm.incb+_xlpm.resv),_xlpm.noic,_xlpm.incc-(_xlpm.opexb*(1+_xlpm.infl)^3+_xlpm.mgmt*_xlpm.incc+_xlpm.resv),_xlpm.noid,_xlpm.incd-(_xlpm.opexb*(1+_xlpm.infl)^4+_xlpm.mgmt*_xlpm.incd+_xlpm.resv),_xlpm.noie,_xlpm.ince-(_xlpm.opexb*(1+_xlpm.infl)^5+_xlpm.mgmt*_xlpm.ince+_xlpm.resv),_xlpm.exitv,_xlpm.noie*(1+_xlpm.growth)/_xlpm.xcap,_xlpm.netsale,_xlpm.exitv*(1-_xlpm.sellc)-_xlpm.payoff,IRR(_xlfn.HSTACK(-_xlpm.equity,_xlpm.noia-_xlpm.dsvc,_xlpm.noib-_xlpm.dsvc,_xlpm.noic-_xlpm.dsvc,_xlpm.noid-_xlpm.dsvc,_xlpm.noie-_xlpm.dsvc+_xlpm.netsale))) -> 0.12157459 | D91: =_xlfn.LET(_xlpm.growth,D$86,_xlpm.xcap,$A91,_xlpm.egibase,$B$24,_xlpm.infl,$B$14,_xlpm.mgmt,$B$16,_xlpm.opexb,$B$50,_xlpm.resv,$B$5*$B$17,_xlpm.dsvc,-PMT($E$7,$E$8,$E$6),_xlpm.equity,$E$13,_xlpm.payoff,$G$63,_xlpm.sellc,$E$12,_xlpm.inca,_xlpm.egibase*(1+_xlpm.growth)^1+$C$46,_xlpm.incb,_xlpm.egibase*(1+_xlpm.growth)^2+$D$46,_xlpm.incc,_xlpm.egibase*(1+_xlpm.growth)^3+$E$46,_xlpm.incd,_xlpm.egibase*(1+_xlpm.growth)^4+$F$46,_xlpm.ince,_xlpm.egibase*(1+_xlpm.growth)^5+$G$46,_xlpm.noia,_xlpm.inca-(_xlpm.opexb*(1+_xlpm.infl)^1+_xlpm.mgmt*_xlpm.inca+_xlpm.resv),_xlpm.noib,_xlpm.incb-(_xlpm.opexb*(1+_xlpm.infl)^2+_xlpm.mgmt*_xlpm.incb+_xlpm.resv),_xlpm.noic,_xlpm.incc-(_xlpm.opexb*(1+_xlpm.infl)^3+_xlpm.mgmt*_xlpm.incc+_xlpm.resv),_xlpm.noid,_xlpm.incd-(_xlpm.opexb*(1+_xlpm.infl)^4+_xlpm.mgmt*_xlpm.incd+_xlpm.resv),_xlpm.noie,_xlpm.ince-(_xlpm.opexb*(1+_xlpm.infl)^5+_xlpm.mgmt*_xlpm.ince+_xlpm.resv),_xlpm.exitv,_xlpm.noie*(1+_xlpm.growth)/_xlpm.xcap,_xlpm.netsale,_xlpm.exitv*(1-_xlpm.sellc)-_xlpm.payoff,IRR(_xlfn.HSTACK(-_xlpm.equity,_xlpm.noia-_xlpm.dsvc,_xlpm.noib-_xlpm.dsvc,_xlpm.noic-_xlpm.dsvc,_xlpm.noid-_xlpm.dsvc,_xlpm.noie-_xlpm.dsvc+_xlpm.netsale))) -> 0.14262889 | E91: =_xlfn.LET(_xlpm.growth,E$86,_xlpm.xcap,$A91,_xlpm.egibase,$B$24,_xlpm.infl,$B$14,_xlpm.mgmt,$B$16,_xlpm.opexb,$B$50,_xlpm.resv,$B$5*$B$17,_xlpm.dsvc,-PMT($E$7,$E$8,$E$6),_xlpm.equity,$E$13,_xlpm.payoff,$G$63,_xlpm.sellc,$E$12,_xlpm.inca,_xlpm.egibase*(1+_xlpm.growth)^1+$C$46,_xlpm.incb,_xlpm.egibase*(1+_xlpm.growth)^2+$D$46,_xlpm.incc,_xlpm.egibase*(1+_xlpm.growth)^3+$E$46,_xlpm.incd,_xlpm.egibase*(1+_xlpm.growth)^4+$F$46,_xlpm.ince,_xlpm.egibase*(1+_xlpm.growth)^5+$G$46,_xlpm.noia,_xlpm.inca-(_xlpm.opexb*(1+_xlpm.infl)^1+_xlpm.mgmt*_xlpm.inca+_xlpm.resv),_xlpm.noib,_xlpm.incb-(_xlpm.opexb*(1+_xlpm.infl)^2+_xlpm.mgmt*_xlpm.incb+_xlpm.resv),_xlpm.noic,_xlpm.incc-(_xlpm.opexb*(1+_xlpm.infl)^3+_xlpm.mgmt*_xlpm.incc+_xlpm.resv),_xlpm.noid,_xlpm.incd-(_xlpm.opexb*(1+_xlpm.infl)^4+_xlpm.mgmt*_xlpm.incd+_xlpm.resv),_xlpm.noie,_xlpm.ince-(_xlpm.opexb*(1+_xlpm.infl)^5+_xlpm.mgmt*_xlpm.ince+_xlpm.resv),_xlpm.exitv,_xlpm.noie*(1+_xlpm.growth)/_xlpm.xcap,_xlpm.netsale,_xlpm.exitv*(1-_xlpm.sellc)-_xlpm.payoff,IRR(_xlfn.HSTACK(-_xlpm.equity,_xlpm.noia-_xlpm.dsvc,_xlpm.noib-_xlpm.dsvc,_xlpm.noic-_xlpm.dsvc,_xlpm.noid-_xlpm.dsvc,_xlpm.noie-_xlpm.dsvc+_xlpm.netsale))) -> 0.1627941 | F91: =_xlfn.LET(_xlpm.growth,F$86,_xlpm.xcap,$A91,_xlpm.egibase,$B$24,_xlpm.infl,$B$14,_xlpm.mgmt,$B$16,_xlpm.opexb,$B$50,_xlpm.resv,$B$5*$B$17,_xlpm.dsvc,-PMT($E$7,$E$8,$E$6),_xlpm.equity,$E$13,_xlpm.payoff,$G$63,_xlpm.sellc,$E$12,_xlpm.inca,_xlpm.egibase*(1+_xlpm.growth)^1+$C$46,_xlpm.incb,_xlpm.egibase*(1+_xlpm.growth)^2+$D$46,_xlpm.incc,_xlpm.egibase*(1+_xlpm.growth)^3+$E$46,_xlpm.incd,_xlpm.egibase*(1+_xlpm.growth)^4+$F$46,_xlpm.ince,_xlpm.egibase*(1+_xlpm.growth)^5+$G$46,_xlpm.noia,_xlpm.inca-(_xlpm.opexb*(1+_xlpm.infl)^1+_xlpm.mgmt*_xlpm.inca+_xlpm.resv),_xlpm.noib,_xlpm.incb-(_xlpm.opexb*(1+_xlpm.infl)^2+_xlpm.mgmt*_xlpm.incb+_xlpm.resv),_xlpm.noic,_xlpm.incc-(_xlpm.opexb*(1+_xlpm.infl)^3+_xlpm.mgmt*_xlpm.incc+_xlpm.resv),_xlpm.noid,_xlpm.incd-(_xlpm.opexb*(1+_xlpm.infl)^4+_xlpm.mgmt*_xlpm.incd+_xlpm.resv),_xlpm.noie,_xlpm.ince-(_xlpm.opexb*(1+_xlpm.infl)^5+_xlpm.mgmt*_xlpm.ince+_xlpm.resv),_xlpm.exitv,_xlpm.noie*(1+_xlpm.growth)/_xlpm.xcap,_xlpm.netsale,_xlpm.exitv*(1-_xlpm.sellc)-_xlpm.payoff,IRR(_xlfn.HSTACK(-_xlpm.equity,_xlpm.noia-_xlpm.dsvc,_xlpm.noib-_xlpm.dsvc,_xlpm.noic-_xlpm.dsvc,_xlpm.noid-_xlpm.dsvc,_xlpm.noie-_xlpm.dsvc+_xlpm.netsale))) -> 0.18218269
A93: KEY FINDINGS vs. SPONSOR
A94: • Best in-place economics of the three: normalized ~9.7% going-in cap and ~$182/unit/mo loss-to-lease ($297K/yr) offer genuine mark-to-market upside.
A95: • My operating cash flow is credible — avg CoC 11.6% vs. sponsor 11.9%. The return GAP is almost entirely the sponsor's Year-2 refi (returns 100% of capital) and their 8.5% exit.
A96: • I did NOT credit the refinance (aggressive, rate/proceeds dependent) and used a 9.25% exit vs. sponsor 8.5% — my exit value $11.0M vs. their $15.8M.
A97: • Result: ~17.6% levered IRR / 2.03x on conservative assumptions — a solid deal even without the refi, vs. sponsor's 42.8% / 3.00x.
A98: • Watch: TX tax reassessment to $7.25M price (T-12 taxes $179K) and the ~$13.5K/unit reno budget executing on time.

Sheet WTAMSH UW
A1: West Texas A&M Student Housing
A2: 336 beds / 114 units | Built 2006 | Canyon, TX | Lease-up play (55% → stabilized) | Independent / Conservative Case
A4: KEY ASSUMPTIONS | D4: FINANCING & EXIT
A5: # Beds | B5: 336 | D5: Loan-to-Price (LTV) | E5: 0.65
A6: # Units | B6: 114 | D6: Loan Amount | E6: =B8*E5 -> 7637500
A7: Year Built | B7: 2006 | D7: Interest Rate | E7: 0.07
A8: Purchase Price | B8: 11750000 | D8: Amortization (yrs) | E8: 30
A9: Price / Bed | B9: =B8/B5 -> 34970.238 | D9: Closing Costs (% price) | E9: 0.02
A10: Hold Period (yrs) | B10: 4 | D10: Going-in Cap (in-place, seller tax) | E10: =B36/B8 -> 0.060234551
D11: Exit Cap Rate | E11: 0.0825
A12: Effective Rent / Bed / Mo | B12: 540 | D12: Selling Costs (% sale) | E12: 0.02
A13: Rent Growth (annual) | B13: 0.03 | D13: Total Equity Required | E13: =B8+B19+B8*E9-E6 -> 4597500
A14: Expense Inflation | B14: 0.03
A15: Other Income Growth | B15: 0.03
A16: Mgmt Fee (% EGI) | B16: 0.04
A17: Replacement Reserves ($/bed) | B17: 150
A18: Property Tax Rate (% of price) | B18: 0.02
A19: Lease-up / Working Capital Reserve | B19: 250000
A21: IN-PLACE OPERATING STATEMENT (T-12, Normalized) | B21: T-12 (~55% occ)
A22: Rental Income (scheduled, ~55% occ) | B22: ='WTAMSH T-12'!O7 -> 1329425
A23: Other Income (fees, utility reimb.) | B23: ='WTAMSH T-12'!O34-'WTAMSH T-12'!O7 -> 204850.79
A24: Effective Gross Income | B24: =B22+B23 -> 1534275.8
A25: Payroll & Related | B25: ='WTAMSH T-12'!O41 -> 185595.96
A26: Repairs & Maintenance | B26: ='WTAMSH T-12'!O47 -> 107896.73
A27: Utilities (common + unit + turnover) | B27: ='WTAMSH T-12'!O58+'WTAMSH T-12'!O63+'WTAMSH T-12'!O51 -> 196648.14
A28: Marketing | B28: ='WTAMSH T-12'!O73 -> 11768.05
A29: Insurance | B29: ='WTAMSH T-12'!O105 -> 54009.71
A30: G&A & Other | B30: ='WTAMSH T-12'!O92+'WTAMSH T-12'!O101+'WTAMSH T-12'!O77 -> 19201.19
A31: Property Taxes (seller basis) | B31: ='WTAMSH T-12'!O138 -> 139629
A32: Total True Operating Expenses | B32: =SUM(B25:B31) -> 714748.78
A33: NOI before mgmt fee & reserves | B33: =B24-B32 -> 819527
A34: (–) Management Fee (% EGI) | B34: =-B24*B16 -> -61371.031
A35: (–) Replacement Reserves ($/bed) | B35: =-B5*B17 -> -50400
A36: Normalized In-Place NOI | B36: =B33+B34+B35 -> 707755.97
A37: Going-in Cap (in-place, seller tax) | B37: =B36/B8 -> 0.060234551
A38: Note: T-12 buried mortgage ($460K), owner distributions ($133K) & capex ($12K) in opex — excluded here to isolate true property NOI. In-place NOI is depressed by 55% occupancy.
A42: PRO FORMA CASH FLOW (Lease-Up)
B43: In-Place | C43: Year 1 | D43: Year 2 | E43: Year 3 | F43: Year 4
A44: Gross Potential Rent (100% occ) | B44: =B22/B45 -> 2417136.3 | C44: =$B$5*$B$12*12 -> 2177280 | D44: =C44*(1+$B$13) -> 2242598.4 | E44: =D44*(1+$B$13) -> 2309876.4 | F44: =E44*(1+$B$13) -> 2379172.6
A45: Economic Occupancy % | B45: 0.55 | C45: 0.75 | D45: 0.82 | E45: 0.86 | F45: 0.88
A46: Net Rental Income | B46: =B44*B45 -> 1329425 | C46: =C44*C45 -> 1632960 | D46: =D44*D45 -> 1838930.7 | E46: =E44*E45 -> 1986493.7 | F46: =F44*F45 -> 2093671.9
A47: Other Income (inflated) | B47: =B23 -> 204850.79 | C47: =B47*(1+$B$15) -> 210996.31 | D47: =C47*(1+$B$15) -> 217326.2 | E47: =D47*(1+$B$15) -> 223845.99 | F47: =E47*(1+$B$15) -> 230561.37
A48: Effective Gross Income | B48: =B46+B47 -> 1534275.8 | C48: =C46+C47 -> 1843956.3 | D48: =D46+D47 -> 2056256.9 | E48: =E46+E47 -> 2210339.7 | F48: =F46+F47 -> 2324233.3
A49: Operating Expenses:
A50: Variable Opex (scales w/ occ & infl.) | B50: =$B$25+$B$26+$B$27+$B$28 -> 501908.88 | C50: =($B$25+$B$26+$B$27+$B$28)*(1+$B$14)^1*(C45/$B$45) -> 704953.84 | D50: =($B$25+$B$26+$B$27+$B$28)*(1+$B$14)^2*(D45/$B$45) -> 793872.01 | E50: =($B$25+$B$26+$B$27+$B$28)*(1+$B$14)^3*(E45/$B$45) -> 857575.4 | F50: =($B$25+$B$26+$B$27+$B$28)*(1+$B$14)^4*(F45/$B$45) -> 903844.59
A51: Fixed Opex – Insurance & Admin (infl.) | B51: =$B$29+$B$30 -> 73210.9 | C51: =($B$29+$B$30)*(1+$B$14)^1 -> 75407.227 | D51: =($B$29+$B$30)*(1+$B$14)^2 -> 77669.444 | E51: =($B$29+$B$30)*(1+$B$14)^3 -> 79999.527 | F51: =($B$29+$B$30)*(1+$B$14)^4 -> 82399.513
A52: Property Taxes (reassessed to price) | B52: =B31 -> 139629 | C52: =$B$8*$B$18 -> 235000 | D52: =C52*(1+$B$14) -> 242050 | E52: =D52*(1+$B$14) -> 249311.5 | F52: =E52*(1+$B$14) -> 256790.85
A53: Management Fee (% EGI) | B53: =B48*$B$16 -> 61371.031 | C53: =C48*$B$16 -> 73758.253 | D53: =D48*$B$16 -> 82250.276 | E53: =E48*$B$16 -> 88413.586 | F53: =F48*$B$16 -> 92969.332
A54: Replacement Reserves ($/bed) | B54: =$B$5*$B$17 -> 50400 | C54: =$B$5*$B$17 -> 50400 | D54: =$B$5*$B$17 -> 50400 | E54: =$B$5*$B$17 -> 50400 | F54: =$B$5*$B$17 -> 50400
A55: Total Operating Expenses | B55: =SUM(B50:B54) -> 826519.81 | C55: =SUM(C50:C54) -> 1139519.3 | D55: =SUM(D50:D54) -> 1246241.7 | E55: =SUM(E50:E54) -> 1325700 | F55: =SUM(F50:F54) -> 1386404.3
A56: NET OPERATING INCOME | B56: =B48-B55 -> 707755.97 | C56: =C48-C55 -> 704437 | D56: =D48-D55 -> 810015.16 | E56: =E48-E55 -> 884639.64 | F56: =F48-F55 -> 937829.02
A57: NOI Margin | B57: =B56/B48 -> 0.46129645 | F57: =F56/F48 -> 0.40350038
A59: DEBT SCHEDULE & RETURNS
A60: Beginning Loan Balance | C60: =$E$6 -> 7637500 | D60: =C63 -> 7556646.3 | E60: =D63 -> 7470132.9 | F60: =E63 -> 7377563.6
A61: Interest | C61: =C60*$E$7 -> 534625 | D61: =D60*$E$7 -> 528965.24 | E61: =E60*$E$7 -> 522909.31 | F61: =F60*$E$7 -> 516429.45
A62: Principal Amortization | C62: =-PMT($E$7,$E$8,$E$6)-C61 -> 80853.657 | D62: =-PMT($E$7,$E$8,$E$6)-D61 -> 86513.413 | E62: =-PMT($E$7,$E$8,$E$6)-E61 -> 92569.352 | F62: =-PMT($E$7,$E$8,$E$6)-F61 -> 99049.206
A63: Ending Loan Balance | C63: =C60-C62 -> 7556646.3 | D63: =D60-D62 -> 7470132.9 | E63: =E60-E62 -> 7377563.6 | F63: =F60-F62 -> 7278514.4
A64: Annual Debt Service | C64: =C61+C62 -> 615478.66 | D64: =D61+D62 -> 615478.66 | E64: =E61+E62 -> 615478.66 | F64: =F61+F62 -> 615478.66
A66: Net Operating Income | C66: =C56 -> 704437 | D66: =D56 -> 810015.16 | E66: =E56 -> 884639.64 | F66: =F56 -> 937829.02
A67: Less: Debt Service | C67: =-C64 -> -615478.66 | D67: =-D64 -> -615478.66 | E67: =-E64 -> -615478.66 | F67: =-F64 -> -615478.66
A68: Levered Cash Flow from Operations | C68: =C66-C64 -> 88958.341 | D68: =D66-D64 -> 194536.5 | E68: =E66-E64 -> 269160.98 | F68: =F66-F64 -> 322350.36
A70: Exit Value (fwd NOI / Exit Cap) | F70: =F56*(1+$B$13)/$E$11 -> 11708653
A71: Less: Selling Costs | F71: =-F70*$E$12 -> -234173.06
A72: Less: Loan Payoff | F72: =-F63 -> -7278514.4
A73: Net Sale Proceeds to Equity | F73: =F70+F71+F72 -> 4195965.8
A75: Levered Equity Cash Flow | B75: =-E13 -> -4597500 | C75: =C68 -> 88958.341 | D75: =D68 -> 194536.5 | E75: =E68 -> 269160.98 | F75: =F68+F73 -> 4518316.1
A77: RETURNS (4-yr hold) | C77: Independent | E77: Sponsor
A78: Levered IRR | C78: =IRR(B75:F75) -> 0.026038357 | E78: 0.3104
A79: Equity Multiple | C79: =SUM(C75:F75)/-B75 -> 1.1029847 | E79: 2.63
A80: Avg. Cash-on-Cash | C80: =AVERAGE(C68:F68)/-B75 -> 0.047580543 | E80: 0.126
A81: Unlevered IRR | C81: =IRR(B82:F82) -> 0.053422262 | E81: n/a
A82: Unlevered Equity Cash Flow | B82: =-(B8+B19+B8*E9) -> -12235000 | C82: =C56 -> 704437 | D82: =D56 -> 810015.16 | E82: =E56 -> 884639.64 | F82: =F56+F70*(1-$E$12) -> 12412309
A85: SENSITIVITY — Levered IRR: Exit Cap (rows) × Rent/Bed (cols)
A86: Exit Cap ↓ / Rent/Bed → | B86: 500 | C86: 520 | D86: 540 | E86: 560 | F86: 580
A87: 0.0725 | B87: =_xlfn.LET(_xlpm.growth,$B$13, _xlpm.rent,B$86, _xlpm.xcap,$A87, _xlpm.beds,$B$5, _xlpm.infl,$B$14, _xlpm.oinfl,$B$15, _xlpm.mgmt,$B$16, _xlpm.resv,$B$5*$B$17, _xlpm.taxr,$B$18, _xlpm.dsvc,-PMT($E$7,$E$8,$E$6), _xlpm.equity,$E$13, _xlpm.payoff,$F$63, _xlpm.sellc,$E$12, _xlpm.price,$B$8, _xlpm.occa,$C$45, _xlpm.occb,$D$45, _xlpm.occc,$E$45, _xlpm.occd,$F$45, _xlpm.varb,($B$25+$B$26+$B$27+$B$28), _xlpm.fixb,($B$29+$B$30), _xlpm.othb,$B$23, _xlpm.ipocc,$B$45, _xlpm.egia,(_xlpm.beds*_xlpm.rent*12)*_xlpm.occa+_xlpm.othb*(1+_xlpm.oinfl)^1, _xlpm.egib,(_xlpm.beds*_xlpm.rent*12*(1+_xlpm.growth)^1)*_xlpm.occb+_xlpm.othb*(1+_xlpm.oinfl)^2, _xlpm.egic,(_xlpm.beds*_xlpm.rent*12*(1+_xlpm.growth)^2)*_xlpm.occc+_xlpm.othb*(1+_xlpm.oinfl)^3, _xlpm.egid,(_xlpm.beds*_xlpm.rent*12*(1+_xlpm.growth)^3)*_xlpm.occd+_xlpm.othb*(1+_xlpm.oinfl)^4, _xlpm.noia,_xlpm.egia-(_xlpm.varb*(1+_xlpm.infl)^1*(_xlpm.occa/_xlpm.ipocc)+_xlpm.fixb*(1+_xlpm.infl)^1+_xlpm.price*_xlpm.taxr+_xlpm.egia*_xlpm.mgmt+_xlpm.resv), _xlpm.noib,_xlpm.egib-(_xlpm.varb*(1+_xlpm.infl)^2*(_xlpm.occb/_xlpm.ipocc)+_xlpm.fixb*(1+_xlpm.infl)^2+_xlpm.price*_xlpm.taxr*(1+_xlpm.infl)^1+_xlpm.egib*_xlpm.mgmt+_xlpm.resv), _xlpm.noic,_xlpm.egic-(_xlpm.varb*(1+_xlpm.infl)^3*(_xlpm.occc/_xlpm.ipocc)+_xlpm.fixb*(1+_xlpm.infl)^3+_xlpm.price*_xlpm.taxr*(1+_xlpm.infl)^2+_xlpm.egic*_xlpm.mgmt+_xlpm.resv), _xlpm.noid,_xlpm.egid-(_xlpm.varb*(1+_xlpm.infl)^4*(_xlpm.occd/_xlpm.ipocc)+_xlpm.fixb*(1+_xlpm.infl)^4+_xlpm.price*_xlpm.taxr*(1+_xlpm.infl)^3+_xlpm.egid*_xlpm.mgmt+_xlpm.resv), _xlpm.exitv,_xlpm.noid*(1+_xlpm.growth)/_xlpm.xcap, _xlpm.netsale,_xlpm.exitv*(1-_xlpm.sellc)-_xlpm.payoff, IRR(_xlfn.HSTACK(-_xlpm.equity,_xlpm.noia-_xlpm.dsvc,_xlpm.noib-_xlpm.dsvc,_xlpm.noic-_xlpm.dsvc,_xlpm.noid-_xlpm.dsvc+_xlpm.netsale))) -> -0.031908879 | C87: =_xlfn.LET(_xlpm.growth,$B$13, _xlpm.rent,C$86, _xlpm.xcap,$A87, _xlpm.beds,$B$5, _xlpm.infl,$B$14, _xlpm.oinfl,$B$15, _xlpm.mgmt,$B$16, _xlpm.resv,$B$5*$B$17, _xlpm.taxr,$B$18, _xlpm.dsvc,-PMT($E$7,$E$8,$E$6), _xlpm.equity,$E$13, _xlpm.payoff,$F$63, _xlpm.sellc,$E$12, _xlpm.price,$B$8, _xlpm.occa,$C$45, _xlpm.occb,$D$45, _xlpm.occc,$E$45, _xlpm.occd,$F$45, _xlpm.varb,($B$25+$B$26+$B$27+$B$28), _xlpm.fixb,($B$29+$B$30), _xlpm.othb,$B$23, _xlpm.ipocc,$B$45, _xlpm.egia,(_xlpm.beds*_xlpm.rent*12)*_xlpm.occa+_xlpm.othb*(1+_xlpm.oinfl)^1, _xlpm.egib,(_xlpm.beds*_xlpm.rent*12*(1+_xlpm.growth)^1)*_xlpm.occb+_xlpm.othb*(1+_xlpm.oinfl)^2, _xlpm.egic,(_xlpm.beds*_xlpm.rent*12*(1+_xlpm.growth)^2)*_xlpm.occc+_xlpm.othb*(1+_xlpm.oinfl)^3, _xlpm.egid,(_xlpm.beds*_xlpm.rent*12*(1+_xlpm.growth)^3)*_xlpm.occd+_xlpm.othb*(1+_xlpm.oinfl)^4, _xlpm.noia,_xlpm.egia-(_xlpm.varb*(1+_xlpm.infl)^1*(_xlpm.occa/_xlpm.ipocc)+_xlpm.fixb*(1+_xlpm.infl)^1+_xlpm.price*_xlpm.taxr+_xlpm.egia*_xlpm.mgmt+_xlpm.resv), _xlpm.noib,_xlpm.egib-(_xlpm.varb*(1+_xlpm.infl)^2*(_xlpm.occb/_xlpm.ipocc)+_xlpm.fixb*(1+_xlpm.infl)^2+_xlpm.price*_xlpm.taxr*(1+_xlpm.infl)^1+_xlpm.egib*_xlpm.mgmt+_xlpm.resv), _xlpm.noic,_xlpm.egic-(_xlpm.varb*(1+_xlpm.infl)^3*(_xlpm.occc/_xlpm.ipocc)+_xlpm.fixb*(1+_xlpm.infl)^3+_xlpm.price*_xlpm.taxr*(1+_xlpm.infl)^2+_xlpm.egic*_xlpm.mgmt+_xlpm.resv), _xlpm.noid,_xlpm.egid-(_xlpm.varb*(1+_xlpm.infl)^4*(_xlpm.occd/_xlpm.ipocc)+_xlpm.fixb*(1+_xlpm.infl)^4+_xlpm.price*_xlpm.taxr*(1+_xlpm.infl)^3+_xlpm.egid*_xlpm.mgmt+_xlpm.resv), _xlpm.exitv,_xlpm.noid*(1+_xlpm.growth)/_xlpm.xcap, _xlpm.netsale,_xlpm.exitv*(1-_xlpm.sellc)-_xlpm.payoff, IRR(_xlfn.HSTACK(-_xlpm.equity,_xlpm.noia-_xlpm.dsvc,_xlpm.noib-_xlpm.dsvc,_xlpm.noic-_xlpm.dsvc,_xlpm.noid-_xlpm.dsvc+_xlpm.netsale))) -> 0.039633042 | D87: =_xlfn.LET(_xlpm.growth,$B$13, _xlpm.rent,D$86, _xlpm.xcap,$A87, _xlpm.beds,$B$5, _xlpm.infl,$B$14, _xlpm.oinfl,$B$15, _xlpm.mgmt,$B$16, _xlpm.resv,$B$5*$B$17, _xlpm.taxr,$B$18, _xlpm.dsvc,-PMT($E$7,$E$8,$E$6), _xlpm.equity,$E$13, _xlpm.payoff,$F$63, _xlpm.sellc,$E$12, _xlpm.price,$B$8, _xlpm.occa,$C$45, _xlpm.occb,$D$45, _xlpm.occc,$E$45, _xlpm.occd,$F$45, _xlpm.varb,($B$25+$B$26+$B$27+$B$28), _xlpm.fixb,($B$29+$B$30), _xlpm.othb,$B$23, _xlpm.ipocc,$B$45, _xlpm.egia,(_xlpm.beds*_xlpm.rent*12)*_xlpm.occa+_xlpm.othb*(1+_xlpm.oinfl)^1, _xlpm.egib,(_xlpm.beds*_xlpm.rent*12*(1+_xlpm.growth)^1)*_xlpm.occb+_xlpm.othb*(1+_xlpm.oinfl)^2, _xlpm.egic,(_xlpm.beds*_xlpm.rent*12*(1+_xlpm.growth)^2)*_xlpm.occc+_xlpm.othb*(1+_xlpm.oinfl)^3, _xlpm.egid,(_xlpm.beds*_xlpm.rent*12*(1+_xlpm.growth)^3)*_xlpm.occd+_xlpm.othb*(1+_xlpm.oinfl)^4, _xlpm.noia,_xlpm.egia-(_xlpm.varb*(1+_xlpm.infl)^1*(_xlpm.occa/_xlpm.ipocc)+_xlpm.fixb*(1+_xlpm.infl)^1+_xlpm.price*_xlpm.taxr+_xlpm.egia*_xlpm.mgmt+_xlpm.resv), _xlpm.noib,_xlpm.egib-(_xlpm.varb*(1+_xlpm.infl)^2*(_xlpm.occb/_xlpm.ipocc)+_xlpm.fixb*(1+_xlpm.infl)^2+_xlpm.price*_xlpm.taxr*(1+_xlpm.infl)^1+_xlpm.egib*_xlpm.mgmt+_xlpm.resv), _xlpm.noic,_xlpm.egic-(_xlpm.varb*(1+_xlpm.infl)^3*(_xlpm.occc/_xlpm.ipocc)+_xlpm.fixb*(1+_xlpm.infl)^3+_xlpm.price*_xlpm.taxr*(1+_xlpm.infl)^2+_xlpm.egic*_xlpm.mgmt+_xlpm.resv), _xlpm.noid,_xlpm.egid-(_xlpm.varb*(1+_xlpm.infl)^4*(_xlpm.occd/_xlpm.ipocc)+_xlpm.fixb*(1+_xlpm.infl)^4+_xlpm.price*_xlpm.taxr*(1+_xlpm.infl)^3+_xlpm.egid*_xlpm.mgmt+_xlpm.resv), _xlpm.exitv,_xlpm.noid*(1+_xlpm.growth)/_xlpm.xcap, _xlpm.netsale,_xlpm.exitv*(1-_xlpm.sellc)-_xlpm.payoff, IRR(_xlfn.HSTACK(-_xlpm.equity,_xlpm.noia-_xlpm.dsvc,_xlpm.noib-_xlpm.dsvc,_xlpm.noic-_xlpm.dsvc,_xlpm.noid-_xlpm.dsvc+_xlpm.netsale))) -> 0.1008377 | E87: =_xlfn.LET(_xlpm.growth,$B$13, _xlpm.rent,E$86, _xlpm.xcap,$A87, _xlpm.beds,$B$5, _xlpm.infl,$B$14, _xlpm.oinfl,$B$15, _xlpm.mgmt,$B$16, _xlpm.resv,$B$5*$B$17, _xlpm.taxr,$B$18, _xlpm.dsvc,-PMT($E$7,$E$8,$E$6), _xlpm.equity,$E$13, _xlpm.payoff,$F$63, _xlpm.sellc,$E$12, _xlpm.price,$B$8, _xlpm.occa,$C$45, _xlpm.occb,$D$45, _xlpm.occc,$E$45, _xlpm.occd,$F$45, _xlpm.varb,($B$25+$B$26+$B$27+$B$28), _xlpm.fixb,($B$29+$B$30), _xlpm.othb,$B$23, _xlpm.ipocc,$B$45, _xlpm.egia,(_xlpm.beds*_xlpm.rent*12)*_xlpm.occa+_xlpm.othb*(1+_xlpm.oinfl)^1, _xlpm.egib,(_xlpm.beds*_xlpm.rent*12*(1+_xlpm.growth)^1)*_xlpm.occb+_xlpm.othb*(1+_xlpm.oinfl)^2, _xlpm.egic,(_xlpm.beds*_xlpm.rent*12*(1+_xlpm.growth)^2)*_xlpm.occc+_xlpm.othb*(1+_xlpm.oinfl)^3, _xlpm.egid,(_xlpm.beds*_xlpm.rent*12*(1+_xlpm.growth)^3)*_xlpm.occd+_xlpm.othb*(1+_xlpm.oinfl)^4, _xlpm.noia,_xlpm.egia-(_xlpm.varb*(1+_xlpm.infl)^1*(_xlpm.occa/_xlpm.ipocc)+_xlpm.fixb*(1+_xlpm.infl)^1+_xlpm.price*_xlpm.taxr+_xlpm.egia*_xlpm.mgmt+_xlpm.resv), _xlpm.noib,_xlpm.egib-(_xlpm.varb*(1+_xlpm.infl)^2*(_xlpm.occb/_xlpm.ipocc)+_xlpm.fixb*(1+_xlpm.infl)^2+_xlpm.price*_xlpm.taxr*(1+_xlpm.infl)^1+_xlpm.egib*_xlpm.mgmt+_xlpm.resv), _xlpm.noic,_xlpm.egic-(_xlpm.varb*(1+_xlpm.infl)^3*(_xlpm.occc/_xlpm.ipocc)+_xlpm.fixb*(1+_xlpm.infl)^3+_xlpm.price*_xlpm.taxr*(1+_xlpm.infl)^2+_xlpm.egic*_xlpm.mgmt+_xlpm.resv), _xlpm.noid,_xlpm.egid-(_xlpm.varb*(1+_xlpm.infl)^4*(_xlpm.occd/_xlpm.ipocc)+_xlpm.fixb*(1+_xlpm.infl)^4+_xlpm.price*_xlpm.taxr*(1+_xlpm.infl)^3+_xlpm.egid*_xlpm.mgmt+_xlpm.resv), _xlpm.exitv,_xlpm.noid*(1+_xlpm.growth)/_xlpm.xcap, _xlpm.netsale,_xlpm.exitv*(1-_xlpm.sellc)-_xlpm.payoff, IRR(_xlfn.HSTACK(-_xlpm.equity,_xlpm.noia-_xlpm.dsvc,_xlpm.noib-_xlpm.dsvc,_xlpm.noic-_xlpm.dsvc,_xlpm.noid-_xlpm.dsvc+_xlpm.netsale))) -> 0.15484292 | F87: =_xlfn.LET(_xlpm.growth,$B$13, _xlpm.rent,F$86, _xlpm.xcap,$A87, _xlpm.beds,$B$5, _xlpm.infl,$B$14, _xlpm.oinfl,$B$15, _xlpm.mgmt,$B$16, _xlpm.resv,$B$5*$B$17, _xlpm.taxr,$B$18, _xlpm.dsvc,-PMT($E$7,$E$8,$E$6), _xlpm.equity,$E$13, _xlpm.payoff,$F$63, _xlpm.sellc,$E$12, _xlpm.price,$B$8, _xlpm.occa,$C$45, _xlpm.occb,$D$45, _xlpm.occc,$E$45, _xlpm.occd,$F$45, _xlpm.varb,($B$25+$B$26+$B$27+$B$28), _xlpm.fixb,($B$29+$B$30), _xlpm.othb,$B$23, _xlpm.ipocc,$B$45, _xlpm.egia,(_xlpm.beds*_xlpm.rent*12)*_xlpm.occa+_xlpm.othb*(1+_xlpm.oinfl)^1, _xlpm.egib,(_xlpm.beds*_xlpm.rent*12*(1+_xlpm.growth)^1)*_xlpm.occb+_xlpm.othb*(1+_xlpm.oinfl)^2, _xlpm.egic,(_xlpm.beds*_xlpm.rent*12*(1+_xlpm.growth)^2)*_xlpm.occc+_xlpm.othb*(1+_xlpm.oinfl)^3, _xlpm.egid,(_xlpm.beds*_xlpm.rent*12*(1+_xlpm.growth)^3)*_xlpm.occd+_xlpm.othb*(1+_xlpm.oinfl)^4, _xlpm.noia,_xlpm.egia-(_xlpm.varb*(1+_xlpm.infl)^1*(_xlpm.occa/_xlpm.ipocc)+_xlpm.fixb*(1+_xlpm.infl)^1+_xlpm.price*_xlpm.taxr+_xlpm.egia*_xlpm.mgmt+_xlpm.resv), _xlpm.noib,_xlpm.egib-(_xlpm.varb*(1+_xlpm.infl)^2*(_xlpm.occb/_xlpm.ipocc)+_xlpm.fixb*(1+_xlpm.infl)^2+_xlpm.price*_xlpm.taxr*(1+_xlpm.infl)^1+_xlpm.egib*_xlpm.mgmt+_xlpm.resv), _xlpm.noic,_xlpm.egic-(_xlpm.varb*(1+_xlpm.infl)^3*(_xlpm.occc/_xlpm.ipocc)+_xlpm.fixb*(1+_xlpm.infl)^3+_xlpm.price*_xlpm.taxr*(1+_xlpm.infl)^2+_xlpm.egic*_xlpm.mgmt+_xlpm.resv), _xlpm.noid,_xlpm.egid-(_xlpm.varb*(1+_xlpm.infl)^4*(_xlpm.occd/_xlpm.ipocc)+_xlpm.fixb*(1+_xlpm.infl)^4+_xlpm.price*_xlpm.taxr*(1+_xlpm.infl)^3+_xlpm.egid*_xlpm.mgmt+_xlpm.resv), _xlpm.exitv,_xlpm.noid*(1+_xlpm.growth)/_xlpm.xcap, _xlpm.netsale,_xlpm.exitv*(1-_xlpm.sellc)-_xlpm.payoff, IRR(_xlfn.HSTACK(-_xlpm.equity,_xlpm.noia-_xlpm.dsvc,_xlpm.noib-_xlpm.dsvc,_xlpm.noic-_xlpm.dsvc,_xlpm.noid-_xlpm.dsvc+_xlpm.netsale))) -> 0.20350915
A88: 0.0775 | B88: =_xlfn.LET(_xlpm.growth,$B$13, _xlpm.rent,B$86, _xlpm.xcap,$A88, _xlpm.beds,$B$5, _xlpm.infl,$B$14, _xlpm.oinfl,$B$15, _xlpm.mgmt,$B$16, _xlpm.resv,$B$5*$B$17, _xlpm.taxr,$B$18, _xlpm.dsvc,-PMT($E$7,$E$8,$E$6), _xlpm.equity,$E$13, _xlpm.payoff,$F$63, _xlpm.sellc,$E$12, _xlpm.price,$B$8, _xlpm.occa,$C$45, _xlpm.occb,$D$45, _xlpm.occc,$E$45, _xlpm.occd,$F$45, _xlpm.varb,($B$25+$B$26+$B$27+$B$28), _xlpm.fixb,($B$29+$B$30), _xlpm.othb,$B$23, _xlpm.ipocc,$B$45, _xlpm.egia,(_xlpm.beds*_xlpm.rent*12)*_xlpm.occa+_xlpm.othb*(1+_xlpm.oinfl)^1, _xlpm.egib,(_xlpm.beds*_xlpm.rent*12*(1+_xlpm.growth)^1)*_xlpm.occb+_xlpm.othb*(1+_xlpm.oinfl)^2, _xlpm.egic,(_xlpm.beds*_xlpm.rent*12*(1+_xlpm.growth)^2)*_xlpm.occc+_xlpm.othb*(1+_xlpm.oinfl)^3, _xlpm.egid,(_xlpm.beds*_xlpm.rent*12*(1+_xlpm.growth)^3)*_xlpm.occd+_xlpm.othb*(1+_xlpm.oinfl)^4, _xlpm.noia,_xlpm.egia-(_xlpm.varb*(1+_xlpm.infl)^1*(_xlpm.occa/_xlpm.ipocc)+_xlpm.fixb*(1+_xlpm.infl)^1+_xlpm.price*_xlpm.taxr+_xlpm.egia*_xlpm.mgmt+_xlpm.resv), _xlpm.noib,_xlpm.egib-(_xlpm.varb*(1+_xlpm.infl)^2*(_xlpm.occb/_xlpm.ipocc)+_xlpm.fixb*(1+_xlpm.infl)^2+_xlpm.price*_xlpm.taxr*(1+_xlpm.infl)^1+_xlpm.egib*_xlpm.mgmt+_xlpm.resv), _xlpm.noic,_xlpm.egic-(_xlpm.varb*(1+_xlpm.infl)^3*(_xlpm.occc/_xlpm.ipocc)+_xlpm.fixb*(1+_xlpm.infl)^3+_xlpm.price*_xlpm.taxr*(1+_xlpm.infl)^2+_xlpm.egic*_xlpm.mgmt+_xlpm.resv), _xlpm.noid,_xlpm.egid-(_xlpm.varb*(1+_xlpm.infl)^4*(_xlpm.occd/_xlpm.ipocc)+_xlpm.fixb*(1+_xlpm.infl)^4+_xlpm.price*_xlpm.taxr*(1+_xlpm.infl)^3+_xlpm.egid*_xlpm.mgmt+_xlpm.resv), _xlpm.exitv,_xlpm.noid*(1+_xlpm.growth)/_xlpm.xcap, _xlpm.netsale,_xlpm.exitv*(1-_xlpm.sellc)-_xlpm.payoff, IRR(_xlfn.HSTACK(-_xlpm.equity,_xlpm.noia-_xlpm.dsvc,_xlpm.noib-_xlpm.dsvc,_xlpm.noic-_xlpm.dsvc,_xlpm.noid-_xlpm.dsvc+_xlpm.netsale))) -> -0.078064663 | C88: =_xlfn.LET(_xlpm.growth,$B$13, _xlpm.rent,C$86, _xlpm.xcap,$A88, _xlpm.beds,$B$5, _xlpm.infl,$B$14, _xlpm.oinfl,$B$15, _xlpm.mgmt,$B$16, _xlpm.resv,$B$5*$B$17, _xlpm.taxr,$B$18, _xlpm.dsvc,-PMT($E$7,$E$8,$E$6), _xlpm.equity,$E$13, _xlpm.payoff,$F$63, _xlpm.sellc,$E$12, _xlpm.price,$B$8, _xlpm.occa,$C$45, _xlpm.occb,$D$45, _xlpm.occc,$E$45, _xlpm.occd,$F$45, _xlpm.varb,($B$25+$B$26+$B$27+$B$28), _xlpm.fixb,($B$29+$B$30), _xlpm.othb,$B$23, _xlpm.ipocc,$B$45, _xlpm.egia,(_xlpm.beds*_xlpm.rent*12)*_xlpm.occa+_xlpm.othb*(1+_xlpm.oinfl)^1, _xlpm.egib,(_xlpm.beds*_xlpm.rent*12*(1+_xlpm.growth)^1)*_xlpm.occb+_xlpm.othb*(1+_xlpm.oinfl)^2, _xlpm.egic,(_xlpm.beds*_xlpm.rent*12*(1+_xlpm.growth)^2)*_xlpm.occc+_xlpm.othb*(1+_xlpm.oinfl)^3, _xlpm.egid,(_xlpm.beds*_xlpm.rent*12*(1+_xlpm.growth)^3)*_xlpm.occd+_xlpm.othb*(1+_xlpm.oinfl)^4, _xlpm.noia,_xlpm.egia-(_xlpm.varb*(1+_xlpm.infl)^1*(_xlpm.occa/_xlpm.ipocc)+_xlpm.fixb*(1+_xlpm.infl)^1+_xlpm.price*_xlpm.taxr+_xlpm.egia*_xlpm.mgmt+_xlpm.resv), _xlpm.noib,_xlpm.egib-(_xlpm.varb*(1+_xlpm.infl)^2*(_xlpm.occb/_xlpm.ipocc)+_xlpm.fixb*(1+_xlpm.infl)^2+_xlpm.price*_xlpm.taxr*(1+_xlpm.infl)^1+_xlpm.egib*_xlpm.mgmt+_xlpm.resv), _xlpm.noic,_xlpm.egic-(_xlpm.varb*(1+_xlpm.infl)^3*(_xlpm.occc/_xlpm.ipocc)+_xlpm.fixb*(1+_xlpm.infl)^3+_xlpm.price*_xlpm.taxr*(1+_xlpm.infl)^2+_xlpm.egic*_xlpm.mgmt+_xlpm.resv), _xlpm.noid,_xlpm.egid-(_xlpm.varb*(1+_xlpm.infl)^4*(_xlpm.occd/_xlpm.ipocc)+_xlpm.fixb*(1+_xlpm.infl)^4+_xlpm.price*_xlpm.taxr*(1+_xlpm.infl)^3+_xlpm.egid*_xlpm.mgmt+_xlpm.resv), _xlpm.exitv,_xlpm.noid*(1+_xlpm.growth)/_xlpm.xcap, _xlpm.netsale,_xlpm.exitv*(1-_xlpm.sellc)-_xlpm.payoff, IRR(_xlfn.HSTACK(-_xlpm.equity,_xlpm.noia-_xlpm.dsvc,_xlpm.noib-_xlpm.dsvc,_xlpm.noic-_xlpm.dsvc,_xlpm.noid-_xlpm.dsvc+_xlpm.netsale))) -> -0.0013662365 | D88: =_xlfn.LET(_xlpm.growth,$B$13, _xlpm.rent,D$86, _xlpm.xcap,$A88, _xlpm.beds,$B$5, _xlpm.infl,$B$14, _xlpm.oinfl,$B$15, _xlpm.mgmt,$B$16, _xlpm.resv,$B$5*$B$17, _xlpm.taxr,$B$18, _xlpm.dsvc,-PMT($E$7,$E$8,$E$6), _xlpm.equity,$E$13, _xlpm.payoff,$F$63, _xlpm.sellc,$E$12, _xlpm.price,$B$8, _xlpm.occa,$C$45, _xlpm.occb,$D$45, _xlpm.occc,$E$45, _xlpm.occd,$F$45, _xlpm.varb,($B$25+$B$26+$B$27+$B$28), _xlpm.fixb,($B$29+$B$30), _xlpm.othb,$B$23, _xlpm.ipocc,$B$45, _xlpm.egia,(_xlpm.beds*_xlpm.rent*12)*_xlpm.occa+_xlpm.othb*(1+_xlpm.oinfl)^1, _xlpm.egib,(_xlpm.beds*_xlpm.rent*12*(1+_xlpm.growth)^1)*_xlpm.occb+_xlpm.othb*(1+_xlpm.oinfl)^2, _xlpm.egic,(_xlpm.beds*_xlpm.rent*12*(1+_xlpm.growth)^2)*_xlpm.occc+_xlpm.othb*(1+_xlpm.oinfl)^3, _xlpm.egid,(_xlpm.beds*_xlpm.rent*12*(1+_xlpm.growth)^3)*_xlpm.occd+_xlpm.othb*(1+_xlpm.oinfl)^4, _xlpm.noia,_xlpm.egia-(_xlpm.varb*(1+_xlpm.infl)^1*(_xlpm.occa/_xlpm.ipocc)+_xlpm.fixb*(1+_xlpm.infl)^1+_xlpm.price*_xlpm.taxr+_xlpm.egia*_xlpm.mgmt+_xlpm.resv), _xlpm.noib,_xlpm.egib-(_xlpm.varb*(1+_xlpm.infl)^2*(_xlpm.occb/_xlpm.ipocc)+_xlpm.fixb*(1+_xlpm.infl)^2+_xlpm.price*_xlpm.taxr*(1+_xlpm.infl)^1+_xlpm.egib*_xlpm.mgmt+_xlpm.resv), _xlpm.noic,_xlpm.egic-(_xlpm.varb*(1+_xlpm.infl)^3*(_xlpm.occc/_xlpm.ipocc)+_xlpm.fixb*(1+_xlpm.infl)^3+_xlpm.price*_xlpm.taxr*(1+_xlpm.infl)^2+_xlpm.egic*_xlpm.mgmt+_xlpm.resv), _xlpm.noid,_xlpm.egid-(_xlpm.varb*(1+_xlpm.infl)^4*(_xlpm.occd/_xlpm.ipocc)+_xlpm.fixb*(1+_xlpm.infl)^4+_xlpm.price*_xlpm.taxr*(1+_xlpm.infl)^3+_xlpm.egid*_xlpm.mgmt+_xlpm.resv), _xlpm.exitv,_xlpm.noid*(1+_xlpm.growth)/_xlpm.xcap, _xlpm.netsale,_xlpm.exitv*(1-_xlpm.sellc)-_xlpm.payoff, IRR(_xlfn.HSTACK(-_xlpm.equity,_xlpm.noia-_xlpm.dsvc,_xlpm.noib-_xlpm.dsvc,_xlpm.noic-_xlpm.dsvc,_xlpm.noid-_xlpm.dsvc+_xlpm.netsale))) -> 0.06305547 | E88: =_xlfn.LET(_xlpm.growth,$B$13, _xlpm.rent,E$86, _xlpm.xcap,$A88, _xlpm.beds,$B$5, _xlpm.infl,$B$14, _xlpm.oinfl,$B$15, _xlpm.mgmt,$B$16, _xlpm.resv,$B$5*$B$17, _xlpm.taxr,$B$18, _xlpm.dsvc,-PMT($E$7,$E$8,$E$6), _xlpm.equity,$E$13, _xlpm.payoff,$F$63, _xlpm.sellc,$E$12, _xlpm.price,$B$8, _xlpm.occa,$C$45, _xlpm.occb,$D$45, _xlpm.occc,$E$45, _xlpm.occd,$F$45, _xlpm.varb,($B$25+$B$26+$B$27+$B$28), _xlpm.fixb,($B$29+$B$30), _xlpm.othb,$B$23, _xlpm.ipocc,$B$45, _xlpm.egia,(_xlpm.beds*_xlpm.rent*12)*_xlpm.occa+_xlpm.othb*(1+_xlpm.oinfl)^1, _xlpm.egib,(_xlpm.beds*_xlpm.rent*12*(1+_xlpm.growth)^1)*_xlpm.occb+_xlpm.othb*(1+_xlpm.oinfl)^2, _xlpm.egic,(_xlpm.beds*_xlpm.rent*12*(1+_xlpm.growth)^2)*_xlpm.occc+_xlpm.othb*(1+_xlpm.oinfl)^3, _xlpm.egid,(_xlpm.beds*_xlpm.rent*12*(1+_xlpm.growth)^3)*_xlpm.occd+_xlpm.othb*(1+_xlpm.oinfl)^4, _xlpm.noia,_xlpm.egia-(_xlpm.varb*(1+_xlpm.infl)^1*(_xlpm.occa/_xlpm.ipocc)+_xlpm.fixb*(1+_xlpm.infl)^1+_xlpm.price*_xlpm.taxr+_xlpm.egia*_xlpm.mgmt+_xlpm.resv), _xlpm.noib,_xlpm.egib-(_xlpm.varb*(1+_xlpm.infl)^2*(_xlpm.occb/_xlpm.ipocc)+_xlpm.fixb*(1+_xlpm.infl)^2+_xlpm.price*_xlpm.taxr*(1+_xlpm.infl)^1+_xlpm.egib*_xlpm.mgmt+_xlpm.resv), _xlpm.noic,_xlpm.egic-(_xlpm.varb*(1+_xlpm.infl)^3*(_xlpm.occc/_xlpm.ipocc)+_xlpm.fixb*(1+_xlpm.infl)^3+_xlpm.price*_xlpm.taxr*(1+_xlpm.infl)^2+_xlpm.egic*_xlpm.mgmt+_xlpm.resv), _xlpm.noid,_xlpm.egid-(_xlpm.varb*(1+_xlpm.infl)^4*(_xlpm.occd/_xlpm.ipocc)+_xlpm.fixb*(1+_xlpm.infl)^4+_xlpm.price*_xlpm.taxr*(1+_xlpm.infl)^3+_xlpm.egid*_xlpm.mgmt+_xlpm.resv), _xlpm.exitv,_xlpm.noid*(1+_xlpm.growth)/_xlpm.xcap, _xlpm.netsale,_xlpm.exitv*(1-_xlpm.sellc)-_xlpm.payoff, IRR(_xlfn.HSTACK(-_xlpm.equity,_xlpm.noia-_xlpm.dsvc,_xlpm.noib-_xlpm.dsvc,_xlpm.noic-_xlpm.dsvc,_xlpm.noid-_xlpm.dsvc+_xlpm.netsale))) -> 0.11924066 | F88: =_xlfn.LET(_xlpm.growth,$B$13, _xlpm.rent,F$86, _xlpm.xcap,$A88, _xlpm.beds,$B$5, _xlpm.infl,$B$14, _xlpm.oinfl,$B$15, _xlpm.mgmt,$B$16, _xlpm.resv,$B$5*$B$17, _xlpm.taxr,$B$18, _xlpm.dsvc,-PMT($E$7,$E$8,$E$6), _xlpm.equity,$E$13, _xlpm.payoff,$F$63, _xlpm.sellc,$E$12, _xlpm.price,$B$8, _xlpm.occa,$C$45, _xlpm.occb,$D$45, _xlpm.occc,$E$45, _xlpm.occd,$F$45, _xlpm.varb,($B$25+$B$26+$B$27+$B$28), _xlpm.fixb,($B$29+$B$30), _xlpm.othb,$B$23, _xlpm.ipocc,$B$45, _xlpm.egia,(_xlpm.beds*_xlpm.rent*12)*_xlpm.occa+_xlpm.othb*(1+_xlpm.oinfl)^1, _xlpm.egib,(_xlpm.beds*_xlpm.rent*12*(1+_xlpm.growth)^1)*_xlpm.occb+_xlpm.othb*(1+_xlpm.oinfl)^2, _xlpm.egic,(_xlpm.beds*_xlpm.rent*12*(1+_xlpm.growth)^2)*_xlpm.occc+_xlpm.othb*(1+_xlpm.oinfl)^3, _xlpm.egid,(_xlpm.beds*_xlpm.rent*12*(1+_xlpm.growth)^3)*_xlpm.occd+_xlpm.othb*(1+_xlpm.oinfl)^4, _xlpm.noia,_xlpm.egia-(_xlpm.varb*(1+_xlpm.infl)^1*(_xlpm.occa/_xlpm.ipocc)+_xlpm.fixb*(1+_xlpm.infl)^1+_xlpm.price*_xlpm.taxr+_xlpm.egia*_xlpm.mgmt+_xlpm.resv), _xlpm.noib,_xlpm.egib-(_xlpm.varb*(1+_xlpm.infl)^2*(_xlpm.occb/_xlpm.ipocc)+_xlpm.fixb*(1+_xlpm.infl)^2+_xlpm.price*_xlpm.taxr*(1+_xlpm.infl)^1+_xlpm.egib*_xlpm.mgmt+_xlpm.resv), _xlpm.noic,_xlpm.egic-(_xlpm.varb*(1+_xlpm.infl)^3*(_xlpm.occc/_xlpm.ipocc)+_xlpm.fixb*(1+_xlpm.infl)^3+_xlpm.price*_xlpm.taxr*(1+_xlpm.infl)^2+_xlpm.egic*_xlpm.mgmt+_xlpm.resv), _xlpm.noid,_xlpm.egid-(_xlpm.varb*(1+_xlpm.infl)^4*(_xlpm.occd/_xlpm.ipocc)+_xlpm.fixb*(1+_xlpm.infl)^4+_xlpm.price*_xlpm.taxr*(1+_xlpm.infl)^3+_xlpm.egid*_xlpm.mgmt+_xlpm.resv), _xlpm.exitv,_xlpm.noid*(1+_xlpm.growth)/_xlpm.xcap, _xlpm.netsale,_xlpm.exitv*(1-_xlpm.sellc)-_xlpm.payoff, IRR(_xlfn.HSTACK(-_xlpm.equity,_xlpm.noia-_xlpm.dsvc,_xlpm.noib-_xlpm.dsvc,_xlpm.noic-_xlpm.dsvc,_xlpm.noid-_xlpm.dsvc+_xlpm.netsale))) -> 0.16946713
A89: 0.0825 | B89: =_xlfn.LET(_xlpm.growth,$B$13, _xlpm.rent,B$86, _xlpm.xcap,$A89, _xlpm.beds,$B$5, _xlpm.infl,$B$14, _xlpm.oinfl,$B$15, _xlpm.mgmt,$B$16, _xlpm.resv,$B$5*$B$17, _xlpm.taxr,$B$18, _xlpm.dsvc,-PMT($E$7,$E$8,$E$6), _xlpm.equity,$E$13, _xlpm.payoff,$F$63, _xlpm.sellc,$E$12, _xlpm.price,$B$8, _xlpm.occa,$C$45, _xlpm.occb,$D$45, _xlpm.occc,$E$45, _xlpm.occd,$F$45, _xlpm.varb,($B$25+$B$26+$B$27+$B$28), _xlpm.fixb,($B$29+$B$30), _xlpm.othb,$B$23, _xlpm.ipocc,$B$45, _xlpm.egia,(_xlpm.beds*_xlpm.rent*12)*_xlpm.occa+_xlpm.othb*(1+_xlpm.oinfl)^1, _xlpm.egib,(_xlpm.beds*_xlpm.rent*12*(1+_xlpm.growth)^1)*_xlpm.occb+_xlpm.othb*(1+_xlpm.oinfl)^2, _xlpm.egic,(_xlpm.beds*_xlpm.rent*12*(1+_xlpm.growth)^2)*_xlpm.occc+_xlpm.othb*(1+_xlpm.oinfl)^3, _xlpm.egid,(_xlpm.beds*_xlpm.rent*12*(1+_xlpm.growth)^3)*_xlpm.occd+_xlpm.othb*(1+_xlpm.oinfl)^4, _xlpm.noia,_xlpm.egia-(_xlpm.varb*(1+_xlpm.infl)^1*(_xlpm.occa/_xlpm.ipocc)+_xlpm.fixb*(1+_xlpm.infl)^1+_xlpm.price*_xlpm.taxr+_xlpm.egia*_xlpm.mgmt+_xlpm.resv), _xlpm.noib,_xlpm.egib-(_xlpm.varb*(1+_xlpm.infl)^2*(_xlpm.occb/_xlpm.ipocc)+_xlpm.fixb*(1+_xlpm.infl)^2+_xlpm.price*_xlpm.taxr*(1+_xlpm.infl)^1+_xlpm.egib*_xlpm.mgmt+_xlpm.resv), _xlpm.noic,_xlpm.egic-(_xlpm.varb*(1+_xlpm.infl)^3*(_xlpm.occc/_xlpm.ipocc)+_xlpm.fixb*(1+_xlpm.infl)^3+_xlpm.price*_xlpm.taxr*(1+_xlpm.infl)^2+_xlpm.egic*_xlpm.mgmt+_xlpm.resv), _xlpm.noid,_xlpm.egid-(_xlpm.varb*(1+_xlpm.infl)^4*(_xlpm.occd/_xlpm.ipocc)+_xlpm.fixb*(1+_xlpm.infl)^4+_xlpm.price*_xlpm.taxr*(1+_xlpm.infl)^3+_xlpm.egid*_xlpm.mgmt+_xlpm.resv), _xlpm.exitv,_xlpm.noid*(1+_xlpm.growth)/_xlpm.xcap, _xlpm.netsale,_xlpm.exitv*(1-_xlpm.sellc)-_xlpm.payoff, IRR(_xlfn.HSTACK(-_xlpm.equity,_xlpm.noia-_xlpm.dsvc,_xlpm.noib-_xlpm.dsvc,_xlpm.noic-_xlpm.dsvc,_xlpm.noid-_xlpm.dsvc+_xlpm.netsale))) -> -0.12537994 | C89: =_xlfn.LET(_xlpm.growth,$B$13, _xlpm.rent,C$86, _xlpm.xcap,$A89, _xlpm.beds,$B$5, _xlpm.infl,$B$14, _xlpm.oinfl,$B$15, _xlpm.mgmt,$B$16, _xlpm.resv,$B$5*$B$17, _xlpm.taxr,$B$18, _xlpm.dsvc,-PMT($E$7,$E$8,$E$6), _xlpm.equity,$E$13, _xlpm.payoff,$F$63, _xlpm.sellc,$E$12, _xlpm.price,$B$8, _xlpm.occa,$C$45, _xlpm.occb,$D$45, _xlpm.occc,$E$45, _xlpm.occd,$F$45, _xlpm.varb,($B$25+$B$26+$B$27+$B$28), _xlpm.fixb,($B$29+$B$30), _xlpm.othb,$B$23, _xlpm.ipocc,$B$45, _xlpm.egia,(_xlpm.beds*_xlpm.rent*12)*_xlpm.occa+_xlpm.othb*(1+_xlpm.oinfl)^1, _xlpm.egib,(_xlpm.beds*_xlpm.rent*12*(1+_xlpm.growth)^1)*_xlpm.occb+_xlpm.othb*(1+_xlpm.oinfl)^2, _xlpm.egic,(_xlpm.beds*_xlpm.rent*12*(1+_xlpm.growth)^2)*_xlpm.occc+_xlpm.othb*(1+_xlpm.oinfl)^3, _xlpm.egid,(_xlpm.beds*_xlpm.rent*12*(1+_xlpm.growth)^3)*_xlpm.occd+_xlpm.othb*(1+_xlpm.oinfl)^4, _xlpm.noia,_xlpm.egia-(_xlpm.varb*(1+_xlpm.infl)^1*(_xlpm.occa/_xlpm.ipocc)+_xlpm.fixb*(1+_xlpm.infl)^1+_xlpm.price*_xlpm.taxr+_xlpm.egia*_xlpm.mgmt+_xlpm.resv), _xlpm.noib,_xlpm.egib-(_xlpm.varb*(1+_xlpm.infl)^2*(_xlpm.occb/_xlpm.ipocc)+_xlpm.fixb*(1+_xlpm.infl)^2+_xlpm.price*_xlpm.taxr*(1+_xlpm.infl)^1+_xlpm.egib*_xlpm.mgmt+_xlpm.resv), _xlpm.noic,_xlpm.egic-(_xlpm.varb*(1+_xlpm.infl)^3*(_xlpm.occc/_xlpm.ipocc)+_xlpm.fixb*(1+_xlpm.infl)^3+_xlpm.price*_xlpm.taxr*(1+_xlpm.infl)^2+_xlpm.egic*_xlpm.mgmt+_xlpm.resv), _xlpm.noid,_xlpm.egid-(_xlpm.varb*(1+_xlpm.infl)^4*(_xlpm.occd/_xlpm.ipocc)+_xlpm.fixb*(1+_xlpm.infl)^4+_xlpm.price*_xlpm.taxr*(1+_xlpm.infl)^3+_xlpm.egid*_xlpm.mgmt+_xlpm.resv), _xlpm.exitv,_xlpm.noid*(1+_xlpm.growth)/_xlpm.xcap, _xlpm.netsale,_xlpm.exitv*(1-_xlpm.sellc)-_xlpm.payoff, IRR(_xlfn.HSTACK(-_xlpm.equity,_xlpm.noia-_xlpm.dsvc,_xlpm.noib-_xlpm.dsvc,_xlpm.noic-_xlpm.dsvc,_xlpm.noid-_xlpm.dsvc+_xlpm.netsale))) -> -0.042222206 | D89: =_xlfn.LET(_xlpm.growth,$B$13, _xlpm.rent,D$86, _xlpm.xcap,$A89, _xlpm.beds,$B$5, _xlpm.infl,$B$14, _xlpm.oinfl,$B$15, _xlpm.mgmt,$B$16, _xlpm.resv,$B$5*$B$17, _xlpm.taxr,$B$18, _xlpm.dsvc,-PMT($E$7,$E$8,$E$6), _xlpm.equity,$E$13, _xlpm.payoff,$F$63, _xlpm.sellc,$E$12, _xlpm.price,$B$8, _xlpm.occa,$C$45, _xlpm.occb,$D$45, _xlpm.occc,$E$45, _xlpm.occd,$F$45, _xlpm.varb,($B$25+$B$26+$B$27+$B$28), _xlpm.fixb,($B$29+$B$30), _xlpm.othb,$B$23, _xlpm.ipocc,$B$45, _xlpm.egia,(_xlpm.beds*_xlpm.rent*12)*_xlpm.occa+_xlpm.othb*(1+_xlpm.oinfl)^1, _xlpm.egib,(_xlpm.beds*_xlpm.rent*12*(1+_xlpm.growth)^1)*_xlpm.occb+_xlpm.othb*(1+_xlpm.oinfl)^2, _xlpm.egic,(_xlpm.beds*_xlpm.rent*12*(1+_xlpm.growth)^2)*_xlpm.occc+_xlpm.othb*(1+_xlpm.oinfl)^3, _xlpm.egid,(_xlpm.beds*_xlpm.rent*12*(1+_xlpm.growth)^3)*_xlpm.occd+_xlpm.othb*(1+_xlpm.oinfl)^4, _xlpm.noia,_xlpm.egia-(_xlpm.varb*(1+_xlpm.infl)^1*(_xlpm.occa/_xlpm.ipocc)+_xlpm.fixb*(1+_xlpm.infl)^1+_xlpm.price*_xlpm.taxr+_xlpm.egia*_xlpm.mgmt+_xlpm.resv), _xlpm.noib,_xlpm.egib-(_xlpm.varb*(1+_xlpm.infl)^2*(_xlpm.occb/_xlpm.ipocc)+_xlpm.fixb*(1+_xlpm.infl)^2+_xlpm.price*_xlpm.taxr*(1+_xlpm.infl)^1+_xlpm.egib*_xlpm.mgmt+_xlpm.resv), _xlpm.noic,_xlpm.egic-(_xlpm.varb*(1+_xlpm.infl)^3*(_xlpm.occc/_xlpm.ipocc)+_xlpm.fixb*(1+_xlpm.infl)^3+_xlpm.price*_xlpm.taxr*(1+_xlpm.infl)^2+_xlpm.egic*_xlpm.mgmt+_xlpm.resv), _xlpm.noid,_xlpm.egid-(_xlpm.varb*(1+_xlpm.infl)^4*(_xlpm.occd/_xlpm.ipocc)+_xlpm.fixb*(1+_xlpm.infl)^4+_xlpm.price*_xlpm.taxr*(1+_xlpm.infl)^3+_xlpm.egid*_xlpm.mgmt+_xlpm.resv), _xlpm.exitv,_xlpm.noid*(1+_xlpm.growth)/_xlpm.xcap, _xlpm.netsale,_xlpm.exitv*(1-_xlpm.sellc)-_xlpm.payoff, IRR(_xlfn.HSTACK(-_xlpm.equity,_xlpm.noia-_xlpm.dsvc,_xlpm.noib-_xlpm.dsvc,_xlpm.noic-_xlpm.dsvc,_xlpm.noid-_xlpm.dsvc+_xlpm.netsale))) -> 0.026038357 | E89: =_xlfn.LET(_xlpm.growth,$B$13, _xlpm.rent,E$86, _xlpm.xcap,$A89, _xlpm.beds,$B$5, _xlpm.infl,$B$14, _xlpm.oinfl,$B$15, _xlpm.mgmt,$B$16, _xlpm.resv,$B$5*$B$17, _xlpm.taxr,$B$18, _xlpm.dsvc,-PMT($E$7,$E$8,$E$6), _xlpm.equity,$E$13, _xlpm.payoff,$F$63, _xlpm.sellc,$E$12, _xlpm.price,$B$8, _xlpm.occa,$C$45, _xlpm.occb,$D$45, _xlpm.occc,$E$45, _xlpm.occd,$F$45, _xlpm.varb,($B$25+$B$26+$B$27+$B$28), _xlpm.fixb,($B$29+$B$30), _xlpm.othb,$B$23, _xlpm.ipocc,$B$45, _xlpm.egia,(_xlpm.beds*_xlpm.rent*12)*_xlpm.occa+_xlpm.othb*(1+_xlpm.oinfl)^1, _xlpm.egib,(_xlpm.beds*_xlpm.rent*12*(1+_xlpm.growth)^1)*_xlpm.occb+_xlpm.othb*(1+_xlpm.oinfl)^2, _xlpm.egic,(_xlpm.beds*_xlpm.rent*12*(1+_xlpm.growth)^2)*_xlpm.occc+_xlpm.othb*(1+_xlpm.oinfl)^3, _xlpm.egid,(_xlpm.beds*_xlpm.rent*12*(1+_xlpm.growth)^3)*_xlpm.occd+_xlpm.othb*(1+_xlpm.oinfl)^4, _xlpm.noia,_xlpm.egia-(_xlpm.varb*(1+_xlpm.infl)^1*(_xlpm.occa/_xlpm.ipocc)+_xlpm.fixb*(1+_xlpm.infl)^1+_xlpm.price*_xlpm.taxr+_xlpm.egia*_xlpm.mgmt+_xlpm.resv), _xlpm.noib,_xlpm.egib-(_xlpm.varb*(1+_xlpm.infl)^2*(_xlpm.occb/_xlpm.ipocc)+_xlpm.fixb*(1+_xlpm.infl)^2+_xlpm.price*_xlpm.taxr*(1+_xlpm.infl)^1+_xlpm.egib*_xlpm.mgmt+_xlpm.resv), _xlpm.noic,_xlpm.egic-(_xlpm.varb*(1+_xlpm.infl)^3*(_xlpm.occc/_xlpm.ipocc)+_xlpm.fixb*(1+_xlpm.infl)^3+_xlpm.price*_xlpm.taxr*(1+_xlpm.infl)^2+_xlpm.egic*_xlpm.mgmt+_xlpm.resv), _xlpm.noid,_xlpm.egid-(_xlpm.varb*(1+_xlpm.infl)^4*(_xlpm.occd/_xlpm.ipocc)+_xlpm.fixb*(1+_xlpm.infl)^4+_xlpm.price*_xlpm.taxr*(1+_xlpm.infl)^3+_xlpm.egid*_xlpm.mgmt+_xlpm.resv), _xlpm.exitv,_xlpm.noid*(1+_xlpm.growth)/_xlpm.xcap, _xlpm.netsale,_xlpm.exitv*(1-_xlpm.sellc)-_xlpm.payoff, IRR(_xlfn.HSTACK(-_xlpm.equity,_xlpm.noia-_xlpm.dsvc,_xlpm.noib-_xlpm.dsvc,_xlpm.noic-_xlpm.dsvc,_xlpm.noid-_xlpm.dsvc+_xlpm.netsale))) -> 0.084751695 | F89: =_xlfn.LET(_xlpm.growth,$B$13, _xlpm.rent,F$86, _xlpm.xcap,$A89, _xlpm.beds,$B$5, _xlpm.infl,$B$14, _xlpm.oinfl,$B$15, _xlpm.mgmt,$B$16, _xlpm.resv,$B$5*$B$17, _xlpm.taxr,$B$18, _xlpm.dsvc,-PMT($E$7,$E$8,$E$6), _xlpm.equity,$E$13, _xlpm.payoff,$F$63, _xlpm.sellc,$E$12, _xlpm.price,$B$8, _xlpm.occa,$C$45, _xlpm.occb,$D$45, _xlpm.occc,$E$45, _xlpm.occd,$F$45, _xlpm.varb,($B$25+$B$26+$B$27+$B$28), _xlpm.fixb,($B$29+$B$30), _xlpm.othb,$B$23, _xlpm.ipocc,$B$45, _xlpm.egia,(_xlpm.beds*_xlpm.rent*12)*_xlpm.occa+_xlpm.othb*(1+_xlpm.oinfl)^1, _xlpm.egib,(_xlpm.beds*_xlpm.rent*12*(1+_xlpm.growth)^1)*_xlpm.occb+_xlpm.othb*(1+_xlpm.oinfl)^2, _xlpm.egic,(_xlpm.beds*_xlpm.rent*12*(1+_xlpm.growth)^2)*_xlpm.occc+_xlpm.othb*(1+_xlpm.oinfl)^3, _xlpm.egid,(_xlpm.beds*_xlpm.rent*12*(1+_xlpm.growth)^3)*_xlpm.occd+_xlpm.othb*(1+_xlpm.oinfl)^4, _xlpm.noia,_xlpm.egia-(_xlpm.varb*(1+_xlpm.infl)^1*(_xlpm.occa/_xlpm.ipocc)+_xlpm.fixb*(1+_xlpm.infl)^1+_xlpm.price*_xlpm.taxr+_xlpm.egia*_xlpm.mgmt+_xlpm.resv), _xlpm.noib,_xlpm.egib-(_xlpm.varb*(1+_xlpm.infl)^2*(_xlpm.occb/_xlpm.ipocc)+_xlpm.fixb*(1+_xlpm.infl)^2+_xlpm.price*_xlpm.taxr*(1+_xlpm.infl)^1+_xlpm.egib*_xlpm.mgmt+_xlpm.resv), _xlpm.noic,_xlpm.egic-(_xlpm.varb*(1+_xlpm.infl)^3*(_xlpm.occc/_xlpm.ipocc)+_xlpm.fixb*(1+_xlpm.infl)^3+_xlpm.price*_xlpm.taxr*(1+_xlpm.infl)^2+_xlpm.egic*_xlpm.mgmt+_xlpm.resv), _xlpm.noid,_xlpm.egid-(_xlpm.varb*(1+_xlpm.infl)^4*(_xlpm.occd/_xlpm.ipocc)+_xlpm.fixb*(1+_xlpm.infl)^4+_xlpm.price*_xlpm.taxr*(1+_xlpm.infl)^3+_xlpm.egid*_xlpm.mgmt+_xlpm.resv), _xlpm.exitv,_xlpm.noid*(1+_xlpm.growth)/_xlpm.xcap, _xlpm.netsale,_xlpm.exitv*(1-_xlpm.sellc)-_xlpm.payoff, IRR(_xlfn.HSTACK(-_xlpm.equity,_xlpm.noia-_xlpm.dsvc,_xlpm.noib-_xlpm.dsvc,_xlpm.noic-_xlpm.dsvc,_xlpm.noid-_xlpm.dsvc+_xlpm.netsale))) -> 0.13675545
